Workbook

Sheet Como usar
B1: Como usar este ficheiro
B2: O ficheiro reúne 224 estágios e programas de entrada com início em janeiro de 2027 (ou perto), sobretudo em private equity, M&A, banca de investimento e gestão de ativos, em Portugal e na Europa. Para cada vaga estima o encaixe com o teu CV e a probabilidade de seres aceite. Cada vaga tem link de candidatura.
B4: As folhas
B5: Resumo | C5: Visão geral numa página: números-chave, vagas por país, as 10 melhores candidaturas e notas importantes. Começa aqui.
B6: Decisão | C6: Uma linha por vaga, ordenada por probabilidade × interesse. É a folha para decidir: filtra por veredicto, país ou chance e usa 'Abrir' para ir ao link.
B7: Dados completos | C7: Toda a informação, vaga a vaga: descrição, requisitos, prazo, salário bruto estimado, fatores do match e notas. Passa o rato por cima dos cabeçalhos para veres o significado das colunas principais.
B8: Perfil e pressupostos | C8: O teu perfil, as línguas, os pesos do match e as taxas base de aceitação. As células a azul são editáveis e todo o ficheiro recalcula.
B9: Análise de match | C9: Estatística sobre as melhores vagas: Top 10, médias por país e dificuldade, quantas candidaturas fazer, sensibilidade aos pressupostos e correlações. Tem dois gráficos.
B11: Os gráficos
B12: Vagas por país (Resumo) | C12: Barras horizontais com o número de vagas listadas em cada país. Mostra onde está a oferta.
B13: Top 10: probabilidade estimada (Análise de match) | C13: Uma barra por vaga do Top 10, com a probabilidade estimada de aceitação. Serve para comparar as melhores vagas entre si.
B14: Prob. de ≥1 oferta vs. nº de candidaturas (Análise de match) | C14: Linha que mostra como sobe a probabilidade de receberes pelo menos uma oferta à medida que te candidatas a mais vagas (sempre às melhores do ranking). A curva tende a achatar: as candidaturas seguintes valem cada vez menos.
B16: Glossário
B17: Tipo de empresa | C17: Banca de investimento, boutique de M&A, VC e private equity, banca comercial, Big 4 e consultoria, big corporate, startup ou scale-up, PME, seguradora, serviços financeiros ou setor público.
B18: Veredicto | C18: Prioridade: score de 3,5 ou mais. Candidatar (reach): 3,0 a 3,4. Reserva: abaixo de 3. Monitorizar: vaga ainda não aberta. Prazo passado: já fechou.
B19: Score (60% fit + 40% facilidade) | C19: 0,6 × Fit + 0,4 × Facilidade. Vai de 1 a 5.
B20: Fit com PE/Finance (1-5) | C20: Quanto a vaga serve o teu interesse em private equity e finanças (5 = PE puro).
B21: Facilidade (1-5) | C21: Quão fácil é ser aceite, tendo em conta a dificuldade da vaga e o encaixe com o teu CV (5 = mais fácil).
B22: Match com o CV (0-100) | C22: Encaixe do teu CV com a vaga: média ponderada de Idioma, Experiência, Elegibilidade e Perfil. Os pesos estão em 'Perfil e pressupostos'.
B23: Prob. estimada de aceitação | C23: Estimativa comparativa: taxa base da dificuldade × fator do match. Não é uma estatística oficial.
B24: Chance | C24: Boa: 8% ou mais. Média: 3% a 8%. Baixa: menos de 3%.
B25: Dificuldade de ser aceite | C25: Julgamento meu sobre a concorrência: Muito alta, Alta, Média-alta ou Média.
B26: Qualidade da informação | C26: Verificada na página: li a oferta. Parcial: só título ou agregador. Por confirmar: indício fraco.
B27: Tipo de link | C27: Direto: site ou sistema de recrutamento da empresa. Anúncio em plataforma: JobTeaser, eFinancialCareers, etc. Página de carreiras: tens de procurar a vaga.
B28: Língua-chave | C28: A língua que mais pesa na vaga. A proficiência de cada língua está em 'Perfil e pressupostos'.
... B30: Probabilidade de ≥1 oferta | C30: Probabilidade de receberes pelo menos uma oferta com N candidaturas, tendo em conta que as candidaturas não são independentes (o mesmo CV é lido em todas).
B32: Como usar, passo a passo
B33: 1. Ver o Resumo | C33: Percebe o panorama geral e lê as notas no fim da folha.
B34: 2. Filtrar na Decisão | C34: Usa o filtro do cabeçalho para ver só 'Prioridade' ou 'Candidatar (reach)' e, se quiseres, só um país ou só chance 'Boa'.
B35: 3. Abrir o link | C35: Confirma o prazo, a elegibilidade e a língua na oferta. Nas vagas 'Parcial' a descrição aqui é genérica.
B36: 4. Ajustar o perfil | C36: Se melhorares uma língua ou ganhares experiência, muda os valores em 'Perfil e pressupostos' e os resultados recalculam.
B37: 5. Candidatar-te | C37: Começa pelas candidaturas 'rolling', que fecham quando a vaga é preenchida, e pelas com prazo mais próximo.
B39: Limites a ter em conta
B40: Probabilidades | C40: São estimativas comparativas, assentes em taxas base que eu assumi. Servem para ordenar vagas e não para prever resultados.
B41: Informação das vagas | C41: Muitas vagas só foram vistas em agregadores ou em páginas que não consegui abrir. Confirma sempre na oferta.
B42: Salários (valores brutos) | C42: Todos os valores são brutos mensais, antes de impostos e descontos. São estimativas de mercado, exceto o EIB (1.500 €/mês; a fonte não diz se é bruto ou líquido) e o IEFP (1.181,69 € brutos, bolsa de nível 6). Em Portugal, o valor líquido fica abaixo do bruto por causa dos descontos para a Segurança Social e do IRS.
B43: Atualização | C43: Pesquisa feita a 17-10-2026. Os prazos mudam e as vagas rolling fecham sem aviso.

Sheet Resumo
B1: Estágios de 6 meses · entrada em janeiro 2027
B2: Private equity, M&A e banca de investimento, gestão de ativos e finanças · Portugal e Europa · pesquisa de 17-10-2026 · inclui o encaixe com o teu CV
B3: Esta folha é o ponto de partida: números gerais, vagas por país e as 10 melhores candidaturas. Depois passa à folha Decisão para escolher vaga a vaga.
B4: Números-chave | E4: Por país | J4: Gráfico de barras: número de vagas listadas por país (inclui também as de prazo passado). Mostra onde está concentrada a oferta: a França e o Reino Unido dominam.
B5: Vagas e oportunidades listadas | C5: =COUNTA('Dados completos'!$B$4:$B$227) -> 224 | E5: País | F5: Nº | G5: Prob. média | H5: Chance Boa
B6: Com estado 'Aberta' (rolling ou com prazo) | C6: =COUNTIF('Dados completos'!$AK$4:$AK$227,"Aberta*") -> 35 | E6: Reino Unido | F6: =COUNTIF('Dados completos'!$F$4:$F$227,E6) -> 28 | G6: =IFERROR(AVERAGEIFS('Dados completos'!$AR$4:$AR$227,'Dados completos'!$F$4:$F$227,E6,'Dados completos'!$AQ$4:$AQ$227,1),"") -> 0.014680741 | H6: =COUNTIFS('Dados completos'!$F$4:$F$227,E6,'Dados completos'!$AI$4:$AI$227,"Boa") -> 0
B7: Por confirmar (visto em agregadores) | C7: =COUNTIF('Dados completos'!$AK$4:$AK$227,"Por confirmar") -> 160 | E7: Espanha | F7: =COUNTIF('Dados completos'!$F$4:$F$227,E7) -> 8 | G7: =IFERROR(AVERAGEIFS('Dados completos'!$AR$4:$AR$227,'Dados completos'!$F$4:$F$227,E7,'Dados completos'!$AQ$4:$AQ$227,1),"") -> 0.018547429 | H7: =COUNTIFS('Dados completos'!$F$4:$F$227,E7,'Dados completos'!$AI$4:$AI$227,"Boa") -> 0
B8: Prazo já expirado | C8: =COUNTIF('Dados completos'!$AK$4:$AK$227,"Prazo expirado") -> 7 | E8: França | F8: =COUNTIF('Dados completos'!$F$4:$F$227,E8) -> 62 | G8: =IFERROR(AVERAGEIFS('Dados completos'!$AR$4:$AR$227,'Dados completos'!$F$4:$F$227,E8,'Dados completos'!$AQ$4:$AQ$227,1),"") -> 0.016289967 | H8: =COUNTIFS('Dados completos'!$F$4:$F$227,E8,'Dados completos'!$AI$4:$AI$227,"Boa") -> 0
B9: Veredicto 'Prioridade' (fit + facilidade) | C9: =COUNTIF('Dados completos'!$AL$4:$AL$227,"Prioridade") -> 31 | E9: Alemanha | F9: =COUNTIF('Dados completos'!$F$4:$F$227,E9) -> 19 | G9: =IFERROR(AVERAGEIFS('Dados completos'!$AR$4:$AR$227,'Dados completos'!$F$4:$F$227,E9,'Dados completos'!$AQ$4:$AQ$227,1),"") -> 0.013674284 | H9: =COUNTIFS('Dados completos'!$F$4:$F$227,E9,'Dados completos'!$AI$4:$AI$227,"Boa") -> 0
B10: Chance 'Boa' (match com o CV) | C10: =COUNTIF('Dados completos'!$AI$4:$AI$227,"Boa") -> 43 | E10: Portugal | F10: =COUNTIF('Dados completos'!$F$4:$F$227,E10) -> 73 | G10: =IFERROR(AVERAGEIFS('Dados completos'!$AR$4:$AR$227,'Dados completos'!$F$4:$F$227,E10,'Dados completos'!$AQ$4:$AQ$227,1),"") -> 0.12364477 | H10: =COUNTIFS('Dados completos'!$F$4:$F$227,E10,'Dados completos'!$AI$4:$AI$227,"Boa") -> 42
B11: Match médio com o CV (0-100) | C11: ='Análise de match'!D21 -> 58.32425 | E11: Luxemburgo | F11: =COUNTIF('Dados completos'!$F$4:$F$227,E11) -> 6 | G11: =IFERROR(AVERAGEIFS('Dados completos'!$AR$4:$AR$227,'Dados completos'!$F$4:$F$227,E11,'Dados completos'!$AQ$4:$AQ$227,1),"") -> 0.052449667 | H11: =COUNTIFS('Dados completos'!$F$4:$F$227,E11,'Dados completos'!$AI$4:$AI$227,"Boa") -> 1
B12: Prob. de ≥1 oferta com as 10 melhores candidaturas | C12: ='Análise de match'!D62 -> 0.55110146 | E12: Suécia | F12: =COUNTIF('Dados completos'!$F$4:$F$227,E12) -> 4 | G12: =IFERROR(AVERAGEIFS('Dados completos'!$AR$4:$AR$227,'Dados completos'!$F$4:$F$227,E12,'Dados completos'!$AQ$4:$AQ$227,1),"") -> 0.0112585 | H12: =COUNTIFS('Dados completos'!$F$4:$F$227,E12,'Dados completos'!$AI$4:$AI$227,"Boa") -> 0
B13: Prob. de ≥1 oferta com as 20 melhores candidaturas | C13: ='Análise de match'!D64 -> 0.79373891 | E13: Suíça | F13: =COUNTIF('Dados completos'!$F$4:$F$227,E13) -> 9 | G13: =IFERROR(AVERAGEIFS('Dados completos'!$AR$4:$AR$227,'Dados completos'!$F$4:$F$227,E13,'Dados completos'!$AQ$4:$AQ$227,1),"") -> 0.015308444 | H13: =COUNTIFS('Dados completos'!$F$4:$F$227,E13,'Dados completos'!$AI$4:$AI$227,"Boa") -> 0
B14: Em Portugal | C14: =COUNTIF('Dados completos'!$F$4:$F$227,"Portugal") -> 73 | E14: Itália | F14: =COUNTIF('Dados completos'!$F$4:$F$227,E14) -> 8 | G14: =IFERROR(AVERAGEIFS('Dados completos'!$AR$4:$AR$227,'Dados completos'!$F$4:$F$227,E14,'Dados completos'!$AQ$4:$AQ$227,1),"") -> 0.014724 | H14: =COUNTIFS('Dados completos'!$F$4:$F$227,E14,'Dados completos'!$AI$4:$AI$227,"Boa") -> 0
E15: Polónia | F15: =COUNTIF('Dados completos'!$F$4:$F$227,E15) -> 1 | G15: =IFERROR(AVERAGEIFS('Dados completos'!$AR$4:$AR$227,'Dados completos'!$F$4:$F$227,E15,'Dados completos'!$AQ$4:$AQ$227,1),"") -> 0.03405 | H15: =COUNTIFS('Dados completos'!$F$4:$F$227,E15,'Dados completos'!$AI$4:$AI$227,"Boa") -> 0
E16: Bélgica | F16: =COUNTIF('Dados completos'!$F$4:$F$227,E16) -> 1 | G16: =IFERROR(AVERAGEIFS('Dados completos'!$AR$4:$AR$227,'Dados completos'!$F$4:$F$227,E16,'Dados completos'!$AQ$4:$AQ$227,1),"") -> 0.01126 | H16: =COUNTIFS('Dados completos'!$F$4:$F$227,E16,'Dados completos'!$AI$4:$AI$227,"Boa") -> 0
E17: Países Baixos | F17: =COUNTIF('Dados completos'!$F$4:$F$227,E17) -> 5 | G17: =IFERROR(AVERAGEIFS('Dados completos'!$AR$4:$AR$227,'Dados completos'!$F$4:$F$227,E17,'Dados completos'!$AQ$4:$AQ$227,1),"") -> 0.0195264 | H17: =COUNTIFS('Dados completos'!$F$4:$F$227,E17,'Dados completos'!$AI$4:$AI$227,"Boa") -> 0
B20: Top 10 por probabilidade × interesse (ver 'Análise de match')
B21: Empresa, role | C21: Cidade | D21: Modalidade | E21: Dificuldade | F21: Prob. aceit. | G21: Match CV | H21: Chance
B22: =Decisão!G5&", "&Decisão!H5 -> Santander Portugal, Estágio, Controlo e Governo de Riscos | C22: =Decisão!K5 -> Lisboa | D22: =Decisão!L5 -> Não indicado (provável presencial) | E22: =Decisão!O5 -> Média | F22: =Decisão!E5 -> 0.17904 | G22: =Decisão!D5 -> 91 | H22: =Decisão!F5 -> Boa
B23: =Decisão!G6&", "&Decisão!H6 -> Santander Portugal, Credit Risk Trainee | C23: =Decisão!K6 -> Lisboa | D23: =Decisão!L6 -> Não indicado (provável presencial) | E23: =Decisão!O6 -> Média | F23: =Decisão!E6 -> 0.17904 | G23: =Decisão!D6 -> 91 | H23: =Decisão!F6 -> Boa
B24: =Decisão!G7&", "&Decisão!H7 -> Banco Santander (Portugal), Programa de Estágios, Candidatura espontânea (Lisboa) | C24: =Decisão!K7 -> Lisboa | D24: =Decisão!L7 -> Não indicado (provável presencial) | E24: =Decisão!O7 -> Média | F24: =Decisão!E7 -> 0.17688 | G24: =Decisão!D7 -> 89.5 | H24: =Decisão!F7 -> Boa
B25: =Decisão!G8&", "&Decisão!H8 -> Qualquer empresa portuguesa (PE/VC/Corporate Finance), Estágio profissional via IEFP (Estágios +Talento) + candidatura espontânea | C25: =Decisão!K8 -> Lisboa (e outras) | D25: =Decisão!L8 -> Depende da empresa | E25: =Decisão!O8 -> Média | F25: =Decisão!E8 -> 0.17688 | G25: =Decisão!D8 -> 89.5 | H25: =Decisão!F8 -> Boa
B26: =Decisão!G9&", "&Decisão!H9 -> Caixa Geral de Depósitos, Estagiário(a), Direção de Mercados Financeiros | C26: =Decisão!K9 -> Lisboa | D26: =Decisão!L9 -> Não indicado (provável presencial) | E26: =Decisão!O9 -> Média-alta | F26: =Decisão!E9 -> 0.1172 | G26: =Decisão!D9 -> 88.75 | H26: =Decisão!F9 -> Boa
B27: =Decisão!G10&", "&Decisão!H10 -> EY-Parthenon, Business Analyst, EY-Parthenon M&A (Real Estate) (Lisboa) | C27: =Decisão!K10 -> Lisboa | D27: =Decisão!L10 -> Híbrido | E27: =Decisão!O10 -> Média-alta | F27: =Decisão!E10 -> 0.11792 | G27: =Decisão!D10 -> 89.5 | H27: =Decisão!F10 -> Boa
B28: =Decisão!G11&", "&Decisão!H11 -> BNP Paribas, Investment Banking Trainee, M&A Advisory (Lisboa) | C28: =Decisão!K11 -> Lisboa | D28: =Decisão!L11 -> Híbrido | E28: =Decisão!O11 -> Média-alta | F28: =Decisão!E11 -> 0.11648 | G28: =Decisão!D11 -> 88 | H28: =Decisão!F11 -> Boa
B29: =Decisão!G12&", "&Decisão!H12 -> Empresa por confirmar (gestora), Data Analyst Trainee, Real Assets (Lisboa) | C29: =Decisão!K12 -> Lisboa | D29: =Decisão!L12 -> Não indicado (provável presencial) | E29: =Decisão!O12 -> Média-alta | F29: =Decisão!E12 -> 0.116048 | G29: =Decisão!D12 -> 87.55 | H29: =Decisão!F12 -> Boa
B30: =Decisão!G13&", "&Decisão!H13 -> Euronext, Early Careers (programa de 2 anos nos mercados financeiros europeus) | C30: =Decisão!K13 -> Lisboa | D30: =Decisão!L13 -> Não indicado (provável presencial) | E30: =Decisão!O13 -> Média-alta | F30: =Decisão!E13 -> 0.115664 | G30: =Decisão!D13 -> 87.15 | H30: =Decisão!F13 -> Boa
B31: =Decisão!G14&", "&Decisão!H14 -> Hilton, Finance Intern / Trainee (Lisboa) | C31: =Decisão!K14 -> Lisboa | D31: =Decisão!L14 -> Não indicado (provável presencial) | E31: =Decisão!O14 -> Média | F31: =Decisão!E14 -> 0.179472 | G31: =Decisão!D14 -> 91.3 | H31: =Decisão!F14 -> Boa
B34: O que tens de saber antes de candidatar
B35: 1. Encaixe com o CV: o teu CV mostra liderança, logística, angariação de fundos, Excel certificado, Python e inglês C1, mas nenhum estágio em finanças nem francês ou alemão. Por isso o match é mais baixo nas vagas de PE em Paris e Frankfurt e nas que pedem experiência prévia. O cálculo está em 'Perfil e pressupostos' e 'Análise de match'.
B36: 2. Acabas o curso em janeiro e muitos programas off-cycle pedem que ainda estejas inscrita (a BlackRock exige o penúltimo ano; a Houlihan Lokey e a Ardian pedem mestrado ou convenção de estágio). Os que aceitam recém-licenciadas (Alantra Madrid, EIB, Blackstone, estágio IEFP, BNP) são os mais seguros.
B37: 3. Portugal tem poucas vagas públicas de PE e de banca de investimento. A melhor é a BNP Paribas Lisboa (M&A Advisory, híbrido). Para PE português, a via mais realista é a candidatura espontânea com o estágio IEFP (bolsa de 1.181,69 € brutos, em parte financiada pelo Estado; as empresas candidatam-se até 07-12-2026).
B38: 4. Salários: todos os valores são brutos mensais. Só o EIB (1.500 €/mês, bruto ou líquido não especificado pela fonte) e o IEFP (1.181,69 € brutos) vêm de fonte oficial. Os restantes são estimativas de mercado (ver a coluna sobre a fonte do salário bruto em 'Dados completos').
B39: 5. Prazos conhecidos: Houlihan Lokey Zurique 21-10-2026; Mastercard Lisboa 25-10-2026; Citi Zurique 06-11-2026; J.P. Morgan Estocolmo 07-11-2026; BlackRock Frankfurt e Munique 13-11-2026; MUFG Amesterdão 15-11-2026; Astorg Frankfurt 30-11-2026; IEFP (empresas) 07-12-2026. As candidaturas 'rolling' fecham quando a vaga é preenchida, por isso candidata-te cedo.
B40: 6. Qualidade da informação: 'Verificada na página' quer dizer que li a oferta. 'Parcial' quer dizer que só vi o título ou um agregador, ou que não consegui abrir a página; nesses casos a descrição e os requisitos são os típicos da categoria e dizem 'ver oferta'. 'Por confirmar' é um indício fraco. A maioria das vagas novas é 'Parcial', por isso confirma o prazo, a elegibilidade e a língua no link antes de te candidatares.
B41: 7. Links: cada vaga tem um link de candidatura (coluna 'Link' e botão 'Abrir'). A coluna 'Tipo de link' diz se é direto (site ou sistema de recrutamento da empresa), um anúncio numa plataforma (JobTeaser, eFinancialCareers, etc.) ou uma página de carreiras onde tens de procurar a vaga (UBS, Wells Fargo, Mizuho, Natixis, Evercore Londres).
B42: 8. Dificuldade, fit, facilidade e os fatores do match são julgamento meu (a azul, editáveis). As probabilidades servem para comparar vagas e não são estatísticas oficiais de aceitação.
B43: 9. Portugal: acrescentei vagas de bancos, Big 4, seguradoras, grandes empresas, scale-ups e candidaturas espontâneas a gestoras de VC. Muitos programas de trainees portugueses abrem de março a maio para entrada em setembro, por isso aparecem como 'Monitorizar' e não entram nos rankings até abrirem. Os que estão abertos agora (CGD, Jerónimo Martins, Coca-Cola, CP, Deloitte, BNP Paribas) são os mais urgentes.
B45: Deixei de fora: a DPE (o link é de 2026), a Mastercard de verão, funções jurídicas, de operações ou de wealth management, estágios só de verão, a Tikehau Bruxelas (fechada, pede neerlandês), a Cinven Londres (removida a 06-10-2026, pede neerlandês) e a Schroders Zurique (working student de 12 meses).
B47: O que significa cada parte desta folha
... B50: Top 10: As dez vagas com melhor combinação de probabilidade e interesse. Prob. aceit. e Match CV vêm do modelo; a chance é Boa (8% ou mais), Média (3% a 8%) ou Baixa.

Sheet Decisão
A1: Vista de decisão, vaga a vaga (ordenada por probabilidade × interesse)
A2: Uma linha por vaga, ordenada por probabilidade de aceitação × interesse. O veredicto junta interesse e facilidade (Score = 60% fit com PE e finanças + 40% facilidade). Match CV mede o encaixe do teu CV (0 a 100) e Prob. é uma estimativa comparativa, explicada em 'Perfil e pressupostos'. Os valores vêm de 'Dados completos'. A ordem ficou fixa na criação: usa o filtro do cabeçalho para reordenar. O botão 'Abrir' leva ao link da candidatura.
A4: # | B4: Veredicto | C4: Score | D4: Match CV | E4: Prob. aceitação | F4: Chance | G4: Empresa | H4: Role | I4: Tipo empresa | J4: País | K4: Cidade | L4: Modalidade | M4: Início | N4: Deadline | O4: Dificuldade | P4: Salário bruto est. (€/mês) | Q4: Idiomas | R4: Porquê (CV) | S4: Estado | T4: Info | U4: Tipo link | V4: Link
A5: ='Dados completos'!A178 -> 175 | B5: ='Dados completos'!AL178 -> Candidatar (reach) | C5: ='Dados completos'!Y178 -> 3.4 | D5: ='Dados completos'!AF178 -> 91 | E5: ='Dados completos'!AH178 -> 0.17904 | F5: ='Dados completos'!AI178 -> Boa | G5: ='Dados completos'!B178 -> Santander Portugal | H5: ='Dados completos'!C178 -> Estágio, Controlo e Governo de Riscos | I5: ='Dados completos'!E178 -> Banca comercial | J5: ='Dados completos'!F178 -> Portugal | K5: ='Dados completos'!G178 -> Lisboa | L5: ='Dados completos'!H178 -> Não indicado (provável presencial) | M5: ='Dados completos'!I178 -> Não indicado | N5: ='Dados completos'!O178 -> Não indicado | O5: ='Dados completos'!V178 -> Média | P5: =IF('Dados completos'!R178="","n/d",IF('Dados completos'!R178='Dados completos'!S178,TEXT('Dados completos'!R178,"#,##0"),TEXT('Dados completos'!R178,"#,##0")&", "&TEXT('Dados completos'!S178,"#,##0"))) -> 1,000, 1,300 | Q5: ='Dados completos'!M178 -> Inglês (ver oferta) | R5: ='Dados completos'!AJ178 -> Língua-chave PT (exigência 0.3); não exige experiência prévia em finanças; aceita recém-licenciadas. | S5: ='Dados completos'!AK178 -> Por confirmar | T5: ='Dados completos'!AP178 -> Parcial (agregador/título) | U5: ='Dados completos'!AO178 -> Anúncio em plataforma | V5: =HYPERLINK('Dados completos'!AN178,"Abrir") -> Abrir
A6: ='Dados completos'!A179 -> 176 | B6: ='Dados completos'!AL179 -> Candidatar (reach) | C6: ='Dados completos'!Y179 -> 3.4 | D6: ='Dados completos'!AF179 -> 91 | E6: ='Dados completos'!AH179 -> 0.17904 | F6: ='Dados completos'!AI179 -> Boa | G6: ='Dados completos'!B179 -> Santander Portugal | H6: ='Dados completos'!C179 -> Credit Risk Trainee | I6: ='Dados completos'!E179 -> Banca comercial | J6: ='Dados completos'!F179 -> Portugal | K6: ='Dados completos'!G179 -> Lisboa | L6: ='Dados completos'!H179 -> Não indicado (provável presencial) | M6: ='Dados completos'!I179 -> Não indicado | N6: ='Dados completos'!O179 -> Não indicado | O6: ='Dados completos'!V179 -> Média | P6: =IF('Dados completos'!R179="","n/d",IF('Dados completos'!R179='Dados completos'!S179,TEXT('Dados completos'!R179,"#,##0"),TEXT('Dados completos'!R179,"#,##0")&", "&TEXT('Dados completos'!S179,"#,##0"))) -> 1,000, 1,300 | Q6: ='Dados completos'!M179 -> Inglês (ver oferta) | R6: ='Dados completos'!AJ179 -> Língua-chave PT (exigência 0.3); não exige experiência prévia em finanças; aceita recém-licenciadas. | S6: ='Dados completos'!AK179 -> Por confirmar | T6: ='Dados completos'!AP179 -> Parcial (agregador/título) | U6: ='Dados completos'!AO179 -> Anúncio em plataforma | V6: =HYPERLINK('Dados completos'!AN179,"Abrir") -> Abrir
A7: ='Dados completos'!A38 -> 35 | B7: ='Dados completos'!AL38 -> Candidatar (reach) | C7: ='Dados completos'!Y38 -> 3.4 | D7: ='Dados completos'!AF38 -> 89.5 | E7: ='Dados completos'!AH38 -> 0.17688 | F7: ='Dados completos'!AI38 -> Boa | G7: ='Dados completos'!B38 -> Banco Santander (Portugal) | H7: ='Dados completos'!C38 -> Programa de Estágios, Candidatura espontânea (Lisboa) | I7: ='Dados completos'!E38 -> Banca comercial | J7: ='Dados completos'!F38 -> Portugal | K7: ='Dados completos'!G38 -> Lisboa | L7: ='Dados completos'!H38 -> Não indicado (provável presencial) | M7: ='Dados completos'!I38 -> Flexível | N7: ='Dados completos'!O38 -> Aberta (espontânea) | O7: ='Dados completos'!V38 -> Média | P7: =IF('Dados completos'!R38="","n/d",IF('Dados completos'!R38='Dados completos'!S38,TEXT('Dados completos'!R38,"#,##0"),TEXT('Dados completos'!R38,"#,##0")&", "&TEXT('Dados completos'!S38,"#,##0"))) -> 1,000, 1,300 | Q7: ='Dados completos'!M38 -> Português e inglês | R7: ='Dados completos'!AJ38 -> Língua-chave PT (exigência 1); não exige experiência prévia em finanças; aceita recém-licenciadas. | S7: ='Dados completos'!AK38 -> Aberta (rolling) | T7: ='Dados completos'!AP38 -> Parcial (agregador/título) | U7: ='Dados completos'!AO38 -> Página de carreiras (procurar a vaga) | V7: =HYPERLINK('Dados completos'!AN38,"Abrir") -> Abrir
A8: ='Dados completos'!A40 -> 37 | B8: ='Dados completos'!AL40 -> Prioridade | C8: ='Dados completos'!Y40 -> 3.6 | D8: ='Dados completos'!AF40 -> 89.5 | E8: ='Dados completos'!AH40 -> 0.17688 | F8: ='Dados completos'!AI40 -> Boa | G8: ='Dados completos'!B40 -> Qualquer empresa portuguesa (PE/VC/Corporate Finance) | H8: ='Dados completos'!C40 -> Estágio profissional via IEFP (Estágios +Talento) + candidatura espontânea | I8: ='Dados completos'!E40 -> Via de acesso | J8: ='Dados completos'!F40 -> Portugal | K8: ='Dados completos'!G40 -> Lisboa (e outras) | L8: ='Dados completos'!H40 -> Depende da empresa | M8: ='Dados completos'!I40 -> Flexível (empresa candidata 12-10 a 07-12-2026) | N8: ='Dados completos'!O40 -> 07-12-2026 (janela da empresa) | O8: ='Dados completos'!V40 -> Média | P8: =IF('Dados completos'!R40="","n/d",IF('Dados completos'!R40='Dados completos'!S40,TEXT('Dados completos'!R40,"#,##0"),TEXT('Dados completos'!R40,"#,##0")&", "&TEXT('Dados completos'!S40,"#,##0"))) -> 1,182 | Q8: ='Dados completos'!M40 -> Português | R8: ='Dados completos'!AJ40 -> Língua-chave PT (exigência 1); não exige experiência prévia em finanças; aceita recém-licenciadas. | S8: ='Dados completos'!AK40 -> Via a explorar | T8: ='Dados completos'!AP40 -> Verificada na página | U8: ='Dados completos'!AO40 -> Página de carreiras (procurar a vaga) | V8: =HYPERLINK('Dados completos'!AN40,"Abrir") -> Abrir
A9: ='Dados completos'!A174 -> 171 | B9: ='Dados completos'!AL174 -> Prioridade | C9: ='Dados completos'!Y174 -> 4.2 | D9: ='Dados completos'!AF174 -> 88.75 | E9: ='Dados completos'!AH174 -> 0.1172 | F9: ='Dados completos'!AI174 -> Boa | G9: ='Dados completos'!B174 -> Caixa Geral de Depósitos | H9: ='Dados completos'!C174 -> Estagiário(a), Direção de Mercados Financeiros | I9: ='Dados completos'!E174 -> Banca comercial | J9: ='Dados completos'!F174 -> Portugal | K9: ='Dados completos'!G174 -> Lisboa | L9: ='Dados completos'!H174 -> Não indicado (provável presencial) | M9: ='Dados completos'!I174 -> Não indicado | N9: ='Dados completos'!O174 -> Não indicado | O9: ='Dados completos'!V174 -> Média-alta | P9: =IF('Dados completos'!R174="","n/d",IF('Dados completos'!R174='Dados completos'!S174,TEXT('Dados completos'!R174,"#,##0"),TEXT('Dados completos'!R174,"#,##0")&", "&TEXT('Dados completos'!S174,"#,##0"))) -> 1,000, 1,300 | Q9: ='Dados completos'!M174 -> Português e inglês | R9: ='Dados completos'!AJ174 -> Língua-chave PT (exigência 0.3); não exige experiência prévia em finanças; aceita recém-licenciadas. | S9: ='Dados completos'!AK174 -> Aberta (prazo não indicado) | T9: ='Dados completos'!AP174 -> Parcial (agregador/título) | U9: ='Dados completos'!AO174 -> Direto (site/ATS da empresa) | V9: =HYPERLINK('Dados completos'!AN174,"Abrir") -> Abrir
A10: ='Dados completos'!A16 -> 13 | B10: ='Dados completos'!AL16 -> Prioridade | C10: ='Dados completos'!Y16 -> 3.8 | D10: ='Dados completos'!AF16 -> 89.5 | E10: ='Dados completos'!AH16 -> 0.11792 | F10: ='Dados completos'!AI16 -> Boa | G10: ='Dados completos'!B16 -> EY-Parthenon | H10: ='Dados completos'!C16 -> Business Analyst, EY-Parthenon M&A (Real Estate) (Lisboa) | I10: ='Dados completos'!E16 -> Big 4 / consultoria | J10: ='Dados completos'!F16 -> Portugal | K10: ='Dados completos'!G16 -> Lisboa | L10: ='Dados completos'!H16 -> Híbrido | M10: ='Dados completos'!I16 -> Imediato | N10: ='Dados completos'!O16 -> Não indicado (publicada 11-08-2026) | O10: ='Dados completos'!V16 -> Média-alta | P10: =IF('Dados completos'!R16="","n/d",IF('Dados completos'!R16='Dados completos'!S16,TEXT('Dados completos'!R16,"#,##0"),TEXT('Dados completos'!R16,"#,##0")&", "&TEXT('Dados completos'!S16,"#,##0"))) -> 1,300, 1,800 | Q10: ='Dados completos'!M16 -> Inglês e português | R10: ='Dados completos'!AJ16 -> Língua-chave EN (exigência 1); não exige experiência prévia em finanças; aceita recém-licenciadas. | S10: ='Dados completos'!AK16 -> Aberta (prazo não indicado) | T10: ='Dados completos'!AP16 -> Parcial (agregador/título) | U10: ='Dados completos'!AO16 -> Página de carreiras (procurar a vaga) | V10: =HYPERLINK('Dados completos'!AN16,"Abrir") -> Abrir
A11: ='Dados completos'!A15 -> 12 | B11: ='Dados completos'!AL15 -> Prioridade | C11: ='Dados completos'!Y15 -> 4 | D11: ='Dados completos'!AF15 -> 88 | E11: ='Dados completos'!AH15 -> 0.11648 | F11: ='Dados completos'!AI15 -> Boa | G11: ='Dados completos'!B15 -> BNP Paribas | H11: ='Dados completos'!C15 -> Investment Banking Trainee, M&A Advisory (Lisboa) | I11: ='Dados completos'!E15 -> Banca de investimento | J11: ='Dados completos'!F15 -> Portugal | K11: ='Dados completos'!G15 -> Lisboa | L11: ='Dados completos'!H15 -> Híbrido | M11: ='Dados completos'!I15 -> Não indicado (confirmar) | N11: ='Dados completos'!O15 -> Não indicado | O11: ='Dados completos'!V15 -> Média-alta | P11: =IF('Dados completos'!R15="","n/d",IF('Dados completos'!R15='Dados completos'!S15,TEXT('Dados completos'!R15,"#,##0"),TEXT('Dados completos'!R15,"#,##0")&", "&TEXT('Dados completos'!S15,"#,##0"))) -> 1,000, 1,400 | Q11: ='Dados completos'!M15 -> Inglês fluente (português) | R11: ='Dados completos'!AJ15 -> Língua-chave EN (exigência 1); não exige experiência prévia em finanças; aceita recém-licenciadas. | S11: ='Dados completos'!AK15 -> Aberta (prazo não indicado) | T11: ='Dados completos'!AP15 -> Verificada na página | U11: ='Dados completos'!AO15 -> Direto (site/ATS da empresa) | V11: =HYPERLINK('Dados completos'!AN15,"Abrir") -> Abrir
A12: ='Dados completos'!A195 -> 192 | B12: ='Dados completos'!AL195 -> Prioridade | C12: ='Dados completos'!Y195 -> 3.9 | D12: ='Dados completos'!AF195 -> 87.55 | E12: ='Dados completos'!AH195 -> 0.116048 | F12: ='Dados completos'!AI195 -> Boa | G12: ='Dados completos'!B195 -> Empresa por confirmar (gestora) | H12: ='Dados completos'!C195 -> Data Analyst Trainee, Real Assets (Lisboa) | I12: ='Dados completos'!E195 -> Serviços financeiros | J12: ='Dados completos'!F195 -> Portugal | K12: ='Dados completos'!G195 -> Lisboa | L12: ='Dados completos'!H195 -> Não indicado (provável presencial) | M12: ='Dados completos'!I195 -> Não indicado | N12: ='Dados completos'!O195 -> Não indicado | O12: ='Dados completos'!V195 -> Média-alta | P12: =IF('Dados completos'!R195="","n/d",IF('Dados completos'!R195='Dados completos'!S195,TEXT('Dados completos'!R195,"#,##0"),TEXT('Dados completos'!R195,"#,##0")&", "&TEXT('Dados completos'!S195,"#,##0"))) -> 1,100, 1,500 | Q12: ='Dados completos'!M195 -> Inglês (ver oferta) | R12: ='Dados completos'!AJ195 -> Língua-chave EN (exigência 0.8); não exige experiência prévia em finanças; aceita recém-licenciadas. | S12: ='Dados completos'!AK195 -> Por confirmar | T12: ='Dados completos'!AP195 -> Parcial (agregador/título) | U12: ='Dados completos'!AO195 -> Anúncio em plataforma | V12: =HYPERLINK('Dados completos'!AN195,"Abrir") -> Abrir
A13: ='Dados completos'!A192 -> 189 | B13: ='Dados completos'!AL192 -> Prioridade | C13: ='Dados completos'!Y192 -> 3.8 | D13: ='Dados completos'!AF192 -> 87.15 | E13: ='Dados completos'!AH192 -> 0.115664 | F13: ='Dados completos'!AI192 -> Boa | G13: ='Dados completos'!B192 -> Euronext | H13: ='Dados completos'!C192 -> Early Careers (programa de 2 anos nos mercados financeiros europeus) | I13: ='Dados completos'!E192 -> Serviços financeiros | J13: ='Dados completos'!F192 -> Portugal | K13: ='Dados completos'!G192 -> Lisboa | L13: ='Dados completos'!H192 -> Não indicado (provável presencial) | M13: ='Dados completos'!I192 -> Não indicado | N13: ='Dados completos'!O192 -> Não indicado | O13: ='Dados completos'!V192 -> Média-alta | P13: =IF('Dados completos'!R192="","n/d",IF('Dados completos'!R192='Dados completos'!S192,TEXT('Dados completos'!R192,"#,##0"),TEXT('Dados completos'!R192,"#,##0")&", "&TEXT('Dados completos'!S192,"#,##0"))) -> 1,200, 1,700 | Q13: ='Dados completos'!M192 -> Inglês obrigatório | R13: ='Dados completos'!AJ192 -> Língua-chave EN (exigência 0.9); não exige experiência prévia em finanças; aceita recém-licenciadas. | S13: ='Dados completos'!AK192 -> Por confirmar | T13: ='Dados completos'!AP192 -> Parcial (agregador/título) | U13: ='Dados completos'!AO192 -> Página de carreiras (procurar a vaga) | V13: =HYPERLINK('Dados completos'!AN192,"Abrir") -> Abrir
A14: ='Dados completos'!A221 -> 218 | B14: ='Dados completos'!AL221 -> Candidatar (reach) | C14: ='Dados completos'!Y221 -> 3.1 | D14: ='Dados completos'!AF221 -> 91.3 | E14: ='Dados completos'!AH221 -> 0.179472 | F14: ='Dados completos'!AI221 -> Boa | G14: ='Dados completos'!B221 -> Hilton | H14: ='Dados completos'!C221 -> Finance Intern / Trainee (Lisboa) | I14: ='Dados completos'!E221 -> Big corporate | J14: ='Dados completos'!F221 -> Portugal | K14: ='Dados completos'!G221 -> Lisboa | L14: ='Dados completos'!H221 -> Não indicado (provável presencial) | M14: ='Dados completos'!I221 -> Não indicado | N14: ='Dados completos'!O221 -> Não indicado | O14: ='Dados completos'!V221 -> Média | P14: =IF('Dados completos'!R221="","n/d",IF('Dados completos'!R221='Dados completos'!S221,TEXT('Dados completos'!R221,"#,##0"),TEXT('Dados completos'!R221,"#,##0")&", "&TEXT('Dados completos'!S221,"#,##0"))) -> 1,000, 1,300 | Q14: ='Dados completos'!M221 -> Inglês (ver oferta) | R14: ='Dados completos'!AJ221 -> Língua-chave EN (exigência 0.8); não exige experiência prévia em finanças; aceita recém-licenciadas. | S14: ='Dados completos'!AK221 -> Por confirmar | T14: ='Dados completos'!AP221 -> Parcial (agregador/título) | U14: ='Dados completos'!AO221 -> Anúncio em plataforma | V14: =HYPERLINK('Dados completos'!AN221,"Abrir") -> Abrir
A15: ='Dados completos'!A222 -> 219 | B15: ='Dados completos'!AL222 -> Candidatar (reach) | C15: ='Dados completos'!Y222 -> 3.1 | D15: ='Dados completos'!AF222 -> 91.3 | E15: ='Dados completos'!AH222 -> 0.179472 | F15: ='Dados completos'!AI222 -> Boa | G15: ='Dados completos'!B222 -> Solen Software Group | H15: ='Dados completos'!C222 -> Finance Internship (Lisboa) | I15: ='Dados completos'!E222 -> Startup / scale-up | J15: ='Dados completos'!F222 -> Portugal | K15: ='Dados completos'!G222 -> Lisboa | L15: ='Dados completos'!H222 -> Não indicado (provável presencial) | M15: ='Dados completos'!I222 -> Não indicado | N15: ='Dados completos'!O222 -> Não indicado | O15: ='Dados completos'!V222 -> Média | P15: =IF('Dados completos'!R222="","n/d",IF('Dados completos'!R222='Dados completos'!S222,TEXT('Dados completos'!R222,"#,##0"),TEXT('Dados completos'!R222,"#,##0")&", "&TEXT('Dados completos'!S222,"#,##0"))) -> 900, 1,200 | Q15: ='Dados completos'!M222 -> Inglês (ver oferta) | R15: ='Dados completos'!AJ222 -> Língua-chave EN (exigência 0.8); não exige experiência prévia em finanças; aceita recém-licenciadas. | S15: ='Dados completos'!AK222 -> Por confirmar | T15: ='Dados completos'!AP222 -> Parcial (agregador/título) | U15: ='Dados completos'!AO222 -> Anúncio em plataforma | V15: =HYPERLINK('Dados completos'!AN222,"Abrir") -> Abrir
A16: ='Dados completos'!A180 -> 177 | B16: ='Dados completos'!AL180 -> Prioridade | C16: ='Dados completos'!Y180 -> 3.7 | D16: ='Dados completos'!AF180 -> 89.5 | E16: ='Dados completos'!AH180 -> 0.11792 | F16: ='Dados completos'!AI180 -> Boa | G16: ='Dados completos'!B180 -> BNP Paribas CIB | H16: ='Dados completos'!C180 -> Strategy and Strategic Investments Trainee (Global Markets, Lisboa) | I16: ='Dados completos'!E180 -> Banca comercial | J16: ='Dados completos'!F180 -> Portugal | K16: ='Dados completos'!G180 -> Lisboa | L16: ='Dados completos'!H180 -> Não indicado (provável presencial) | M16: ='Dados completos'!I180 -> Não indicado | N16: ='Dados completos'!O180 -> Não indicado | O16: ='Dados completos'!V180 -> Média-alta | P16: =IF('Dados completos'!R180="","n/d",IF('Dados completos'!R180='Dados completos'!S180,TEXT('Dados completos'!R180,"#,##0"),TEXT('Dados completos'!R180,"#,##0")&", "&TEXT('Dados completos'!S180,"#,##0"))) -> 1,100, 1,500 | Q16: ='Dados completos'!M180 -> Inglês (candidatura só em inglês) | R16: ='Dados completos'!AJ180 -> Língua-chave EN (exigência 1); não exige experiência prévia em finanças; aceita recém-licenciadas. | S16: ='Dados completos'!AK180 -> Aberta (prazo não indicado) | T16: ='Dados completos'!AP180 -> Verificada na página | U16: ='Dados completos'!AO180 -> Direto (site/ATS da empresa) | V16: =HYPERLINK('Dados completos'!AN180,"Abrir") -> Abrir
A17: ='Dados completos'!A161 -> 158 | B17: ='Dados completos'!AL161 -> Prioridade | C17: ='Dados completos'!Y161 -> 3.6 | D17: ='Dados completos'!AF161 -> 87.25 | E17: ='Dados completos'!AH161 -> 0.11576 | F17: ='Dados completos'!AI161 -> Boa | G17: ='Dados completos'!B161 -> BNP Paribas | H17: ='Dados completos'!C161 -> Trainee Fixed Income Analyst (Lisboa) | I17: ='Dados completos'!E161 -> Banca de investimento | J17: ='Dados completos'!F161 -> Portugal | K17: ='Dados completos'!G161 -> Lisboa | L17: ='Dados completos'!H161 -> Não indicado (provável presencial) | M17: ='Dados completos'!I161 -> Não indicado | N17: ='Dados completos'!O161 -> Não indicado | O17: ='Dados completos'!V161 -> Média-alta | P17: =IF('Dados completos'!R161="","n/d",IF('Dados completos'!R161='Dados completos'!S161,TEXT('Dados completos'!R161,"#,##0"),TEXT('Dados completos'!R161,"#,##0")&", "&TEXT('Dados completos'!S161,"#,##0"))) -> 1,000, 1,400 | Q17: ='Dados completos'!M161 -> Inglês (ver oferta) | R17: ='Dados completos'!AJ161 -> Língua-chave EN (exigência 1); não exige experiência prévia em finanças; aceita recém-licenciadas. | S17: ='Dados completos'!AK161 -> Por confirmar | T17: ='Dados completos'!AP161 -> Parcial (agregador/título) | U17: ='Dados completos'!AO161 -> Direto (site/ATS da empresa) | V17: =HYPERLINK('Dados completos'!AN161,"Abrir") -> Abrir
A18: ='Dados completos'!A162 -> 159 | B18: ='Dados completos'!AL162 -> Prioridade | C18: ='Dados completos'!Y162 -> 3.6 | D18: ='Dados completos'!AF162 -> 87.25 | E18: ='Dados completos'!AH162 -> 0.11576 | F18: ='Dados completos'!AI162 -> Boa | G18: ='Dados completos'!B162 -> BNP Paribas | H18: ='Dados completos'!C162 -> Financial & International Markets Trainee (Lisboa) | I18: ='Dados completos'!E162 -> Banca de investimento | J18: ='Dados completos'!F162 -> Portugal | K18: ='Dados completos'!G162 -> Lisboa | L18: ='Dados completos'!H162 -> Não indicado (provável presencial) | M18: ='Dados completos'!I162 -> Não indicado | N18: ='Dados completos'!O162 -> Não indicado | O18: ='Dados completos'!V162 -> Média-alta | P18: =IF('Dados completos'!R162="","n/d",IF('Dados completos'!R162='Dados completos'!S162,TEXT('Dados completos'!R162,"#,##0"),TEXT('Dados completos'!R162,"#,##0")&", "&TEXT('Dados completos'!S162,"#,##0"))) -> 1,000, 1,400 | Q18: ='Dados completos'!M162 -> Inglês (ver oferta) | R18: ='Dados completos'!AJ162 -> Língua-chave EN (exigência 1); não exige experiência prévia em finanças; aceita recém-licenciadas. | S18: ='Dados completos'!AK162 -> Por confirmar | T18: ='Dados completos'!AP162 -> Parcial (agregador/título) | U18: ='Dados completos'!AO162 -> Direto (site/ATS da empresa) | V18: =HYPERLINK('Dados completos'!AN162,"Abrir") -> Abrir
A19: ='Dados completos'!A183 -> 180 | B19: ='Dados completos'!AL183 -> Prioridade | C19: ='Dados completos'!Y183 -> 3.5 | D19: ='Dados completos'!AF183 -> 92.5 | E19: ='Dados completos'!AH183 -> 0.1208 | F19: ='Dados completos'!AI183 -> Boa | G19: ='Dados completos'!B183 -> Deloitte Portugal | H19: ='Dados completos'!C183 -> Hello World 26/27, New Graduates (Financial Advisory, Risk Advisory, Consulting, Audit, Tax) | I19: ='Dados completos'!E183 -> Big 4 / consultoria | J19: ='Dados completos'!F183 -> Portugal | K19: ='Dados completos'!G183 -> Lisboa | L19: ='Dados completos'!H183 -> Não indicado (provável presencial) | M19: ='Dados completos'!I183 -> Não indicado | N19: ='Dados completos'!O183 -> Não indicado | O19: ='Dados completos'!V183 -> Média-alta | P19: =IF('Dados completos'!R183="","n/d",IF('Dados completos'!R183='Dados completos'!S183,TEXT('Dados completos'!R183,"#,##0"),TEXT('Dados completos'!R183,"#,##0")&", "&TEXT('Dados completos'!S183,"#,##0"))) -> 1,200, 1,500 | Q19: ='Dados completos'!M183 -> Português e inglês | R19: ='Dados completos'!AJ183 -> Língua-chave PT (exigência 0.3); não exige experiência prévia em finanças; aceita recém-licenciadas. | S19: ='Dados completos'!AK183 -> Aberta (prazo não indicado) | T19: ='Dados completos'!AP183 -> Verificada na página | U19: ='Dados completos'!AO183 -> Direto (site/ATS da empresa) | V19: =HYPERLINK('Dados completos'!AN183,"Abrir") -> Abrir
A20: ='Dados completos'!A184 -> 181 | B20: ='Dados completos'!AL184 -> Prioridade | C20: ='Dados completos'!Y184 -> 3.5 | D20: ='Dados completos'!AF184 -> 92.5 | E20: ='Dados completos'!AH184 -> 0.1208 | F20: ='Dados completos'!AI184 -> Boa | G20: ='Dados completos'!B184 -> Deloitte Portugal | H20: ='Dados completos'!C184 -> Candidatura espontânea (Lisboa) | I20: ='Dados completos'!E184 -> Big 4 / consultoria | J20: ='Dados completos'!F184 -> Portugal | K20: ='Dados completos'!G184 -> Lisboa | L20: ='Dados completos'!H184 -> Não indicado (provável presencial) | M20: ='Dados completos'!I184 -> Não indicado | N20: ='Dados completos'!O184 -> Não indicado | O20: ='Dados completos'!V184 -> Média-alta | P20: =IF('Dados completos'!R184="","n/d",IF('Dados completos'!R184='Dados completos'!S184,TEXT('Dados completos'!R184,"#,##0"),TEXT('Dados completos'!R184,"#,##0")&", "&TEXT('Dados completos'!S184,"#,##0"))) -> 1,200, 1,500 | Q20: ='Dados completos'!M184 -> Inglês (ver oferta) | R20: ='Dados completos'!AJ184 -> Língua-chave PT (exigência 0.3); não exige experiência prévia em finanças; aceita recém-licenciadas. | S20: ='Dados completos'!AK184 -> Aberta (prazo não indicado) | T20: ='Dados completos'!AP184 -> Parcial (agregador/título) | U20: ='Dados completos'!AO184 -> Direto (site/ATS da empresa) | V20: =HYPERLINK('Dados completos'!AN184,"Abrir") -> Abrir
A21: ='Dados completos'!A187 -> 184 | B21: ='Dados completos'!AL187 -> Prioridade | C21: ='Dados completos'!Y187 -> 3.5 | D21: ='Dados completos'!AF187 -> 92.5 | E21: ='Dados completos'!AH187 -> 0.1208 | F21: ='Dados completos'!AI187 -> Boa | G21: ='Dados completos'!B187 -> EY Portugal | H21: ='Dados completos'!C187 -> Oportunidades de início de carreira (estágios e programas) | I21: ='Dados completos'!E187 -> Big 4 / consultoria | J21: ='Dados completos'!F187 -> Portugal | K21: ='Dados completos'!G187 -> Lisboa | L21: ='Dados completos'!H187 -> Não indicado (provável presencial) | M21: ='Dados completos'!I187 -> Não indicado | N21: ='Dados completos'!O187 -> Não indicado | O21: ='Dados completos'!V187 -> Média-alta | P21: =IF('Dados completos'!R187="","n/d",IF('Dados completos'!R187='Dados completos'!S187,TEXT('Dados completos'!R187,"#,##0"),TEXT('Dados completos'!R187,"#,##0")&", "&TEXT('Dados completos'!S187,"#,##0"))) -> 1,100, 1,400 | Q21: ='Dados completos'!M187 -> Inglês (ver oferta) | R21: ='Dados completos'!AJ187 -> Língua-chave PT (exigência 0.3); não exige experiência prévia em finanças; aceita recém-licenciadas. | S21: ='Dados completos'!AK187 -> Aberta (prazo não indicado) | T21: ='Dados completos'!AP187 -> Parcial (agregador/título) | U21: ='Dados completos'!AO187 -> Página de carreiras (procurar a vaga) | V21: =HYPERLINK('Dados completos'!AN187,"Abrir") -> Abrir
A22: ='Dados completos'!A163 -> 160 | B22: ='Dados completos'!AL163 -> Reserva | C22: ='Dados completos'!Y163 -> 2.9 | D22: ='Dados completos'!AF163 -> 92.5 | E22: ='Dados completos'!AH163 -> 0.1812 | F22: ='Dados completos'!AI163 -> Boa | G22: ='Dados completos'!B163 -> Accenture | H22: ='Dados completos'!C163 -> Consulting Graduate Programme, January 2027 (Lisboa) | I22: ='Dados completos'!E163 -> Big 4 / consultoria | J22: ='Dados completos'!F163 -> Portugal | K22: ='Dados completos'!G163 -> Lisboa | L22: ='Dados completos'!H163 -> Não indicado (provável presencial) | M22: ='Dados completos'!I163 -> Jan 2027 | N22: ='Dados completos'!O163 -> Não indicado | O22: ='Dados completos'!V163 -> Média | P22: =IF('Dados completos'!R163="","n/d",IF('Dados completos'!R163='Dados completos'!S163,TEXT('Dados completos'!R163,"#,##0"),TEXT('Dados completos'!R163,"#,##0")&", "&TEXT('Dados completos'!S163,"#,##0"))) -> 1,000, 1,400 | Q22: ='Dados completos'!M163 -> Inglês (ver oferta) | R22: ='Dados completos'!AJ163 -> Língua-chave EN (exigência 1); não exige experiência prévia em finanças; aceita recém-licenciadas. | S22: ='Dados completos'!AK163 -> Por confirmar | T22: ='Dados completos'!AP163 -> Parcial (agregador/título) | U22: ='Dados completos'!AO163 -> Direto (site/ATS da empresa) | V22: =HYPERLINK('Dados completos'!AN163,"Abrir") -> Abrir
A23: ='Dados completos'!A176 -> 173 | B23: ='Dados completos'!AL176 -> Reserva | C23: ='Dados completos'!Y176 -> 2.9 | D23: ='Dados completos'!AF176 -> 92.5 | E23: ='Dados completos'!AH176 -> 0.1812 | F23: ='Dados completos'!AI176 -> Boa | G23: ='Dados completos'!B176 -> Santander Portugal | H23: ='Dados completos'!C176 -> Estágio, Área de Universidades (Evergreen) | I23: ='Dados completos'!E176 -> Banca comercial | J23: ='Dados completos'!F176 -> Portugal | K23: ='Dados completos'!G176 -> Lisboa | L23: ='Dados completos'!H176 -> Não indicado (provável presencial) | M23: ='Dados completos'!I176 -> Não indicado | N23: ='Dados completos'!O176 -> Não indicado | O23: ='Dados completos'!V176 -> Média | P23: =IF('Dados completos'!R176="","n/d",IF('Dados completos'!R176='Dados completos'!S176,TEXT('Dados completos'!R176,"#,##0"),TEXT('Dados completos'!R176,"#,##0")&", "&TEXT('Dados completos'!S176,"#,##0"))) -> 1,000, 1,300 | Q23: ='Dados completos'!M176 -> Inglês (ver oferta) | R23: ='Dados completos'!AJ176 -> Língua-chave PT (exigência 0.3); não exige experiência prévia em finanças; aceita recém-licenciadas. | S23: ='Dados completos'!AK176 -> Por confirmar | T23: ='Dados completos'!AP176 -> Parcial (agregador/título) | U23: ='Dados completos'!AO176 -> Direto (site/ATS da empresa) | V23: =HYPERLINK('Dados completos'!AN176,"Abrir") -> Abrir
A24: ='Dados completos'!A188 -> 185 | B24: ='Dados completos'!AL188 -> Reserva | C24: ='Dados completos'!Y188 -> 2.9 | D24: ='Dados completos'!AF188 -> 92.5 | E24: ='Dados completos'!AH188 -> 0.1812 | F24: ='Dados completos'!AI188 -> Boa | G24: ='Dados completos'!B188 -> EY Portugal | H24: ='Dados completos'!C188 -> Estágios, Confirmation Team (Lisboa e Viseu) | I24: ='Dados completos'!E188 -> Big 4 / consultoria | J24: ='Dados completos'!F188 -> Portugal | K24: ='Dados completos'!G188 -> Lisboa | L24: ='Dados completos'!H188 -> Não indicado (provável presencial) | M24: ='Dados completos'!I188 -> Não indicado | N24: ='Dados completos'!O188 -> Não indicado | O24: ='Dados completos'!V188 -> Média | P24: =IF('Dados completos'!R188="","n/d",IF('Dados completos'!R188='Dados completos'!S188,TEXT('Dados completos'!R188,"#,##0"),TEXT('Dados completos'!R188,"#,##0")&", "&TEXT('Dados completos'!S188,"#,##0"))) -> 1,000, 1,300 | Q24: ='Dados completos'!M188 -> Inglês (ver oferta) | R24: ='Dados completos'!AJ188 -> Língua-chave PT (exigência 0.3); não exige experiência prévia em finanças; aceita recém-licenciadas. | S24: ='Dados completos'!AK188 -> Por confirmar | T24: ='Dados completos'!AP188 -> Parcial (agregador/título) | U24: ='Dados completos'!AO188 -> Direto (site/ATS da empresa) | V24: =HYPERLINK('Dados completos'!AN188,"Abrir") -> Abrir
A25: ='Dados completos'!A220 -> 217 | B25: ='Dados completos'!AL220 -> Reserva | C25: ='Dados completos'!Y220 -> 2.9 | D25: ='Dados completos'!AF220 -> 92.5 | E25: ='Dados completos'!AH220 -> 0.1812 | F25: ='Dados completos'!AI220 -> Boa | G25: ='Dados completos'!B220 -> DHL | H25: ='Dados completos'!C220 -> Estágios locais, AIESEC e programa G100 (EMEA) | I25: ='Dados completos'!E220 -> Big corporate | J25: ='Dados completos'!F220 -> Portugal | K25: ='Dados completos'!G220 -> Lisboa | L25: ='Dados completos'!H220 -> Não indicado (provável presencial) | M25: ='Dados completos'!I220 -> Não indicado | N25: ='Dados completos'!O220 -> Não indicado | O25: ='Dados completos'!V220 -> Média | P25: =IF('Dados completos'!R220="","n/d",IF('Dados completos'!R220='Dados completos'!S220,TEXT('Dados completos'!R220,"#,##0"),TEXT('Dados completos'!R220,"#,##0")&", "&TEXT('Dados completos'!S220,"#,##0"))) -> 1,000, 1,400 | Q25: ='Dados completos'!M220 -> Inglês (ver oferta) | R25: ='Dados completos'!AJ220 -> Língua-chave PT (exigência 0.3); não exige experiência prévia em finanças; aceita recém-licenciadas. | S25: ='Dados completos'!AK220 -> Por confirmar | T25: ='Dados completos'!AP220 -> Parcial (agregador/título) | U25: ='Dados completos'!AO220 -> Página de carreiras (procurar a vaga) | V25: =HYPERLINK('Dados completos'!AN220,"Abrir") -> Abrir
A26: ='Dados completos'!A193 -> 190 | B26: ='Dados completos'!AL193 -> Candidatar (reach) | C26: ='Dados completos'!Y193 -> 3.1 | D26: ='Dados completos'!AF193 -> 72.6 | E26: ='Dados completos'!AH193 -> 0.101696 | F26: ='Dados completos'!AI193 -> Boa | G26: ='Dados completos'!B193 -> Euronext | H26: ='Dados completos'!C193 -> Outsourcing Analyst (VIE, Porto) | I26: ='Dados completos'!E193 -> Serviços financeiros | J26: ='Dados completos'!F193 -> Portugal | K26: ='Dados completos'!G193 -> Porto | L26: ='Dados completos'!H193 -> Não indicado (provável presencial) | M26: ='Dados completos'!I193 -> Não indicado | N26: ='Dados completos'!O193 -> Não indicado | O26: ='Dados completos'!V193 -> Média-alta | P26: =IF('Dados completos'!R193="","n/d",IF('Dados completos'!R193='Dados completos'!S193,TEXT('Dados completos'!R193,"#,##0"),TEXT('Dados completos'!R193,"#,##0")&", "&TEXT('Dados completos'!S193,"#,##0"))) -> 1,300, 1,800 | Q26: ='Dados completos'!M193 -> Inglês (ver oferta) | R26: ='Dados completos'!AJ193 -> Língua-chave FR (exigência 0.4); não exige experiência prévia em finanças; aceita recém-licenciadas. | S26: ='Dados completos'!AK193 -> Por confirmar | T26: ='Dados completos'!AP193 -> Parcial (agregador/título) | U26: ='Dados completos'!AO193 -> Anúncio em plataforma | V26: =HYPERLINK('Dados completos'!AN193,"Abrir") -> Abrir
A27: ='Dados completos'!A198 -> 195 | B27: ='Dados completos'!AL198 -> Reserva | C27: ='Dados completos'!Y198 -> 2.7 | D27: ='Dados completos'!AF198 -> 88.3 | E27: ='Dados completos'!AH198 -> 0.175152 | F27: ='Dados completos'!AI198 -> Boa | G27: ='Dados completos'!B198 -> Empresa por confirmar | H27: ='Dados completos'!C198 -> AML Analyst, Academy Program (Lisboa) | I27: ='Dados completos'!E198 -> Serviços financeiros | J27: ='Dados completos'!F198 -> Portugal | K27: ='Dados completos'!G198 -> Lisboa | L27: ='Dados completos'!H198 -> Não indicado (provável presencial) | M27: ='Dados completos'!I198 -> Não indicado | N27: ='Dados completos'!O198 -> Não indicado | O27: ='Dados completos'!V198 -> Média | P27: =IF('Dados completos'!R198="","n/d",IF('Dados completos'!R198='Dados completos'!S198,TEXT('Dados completos'!R198,"#,##0"),TEXT('Dados completos'!R198,"#,##0")&", "&TEXT('Dados completos'!S198,"#,##0"))) -> 1,000, 1,400 | Q27: ='Dados completos'!M198 -> Inglês (ver oferta) | R27: ='Dados completos'!AJ198 -> Língua-chave EN (exigência 0.8); não exige experiência prévia em finanças; aceita recém-licenciadas. | S27: ='Dados completos'!AK198 -> Por confirmar | T27: ='Dados completos'!AP198 -> Parcial (agregador/título) | U27: ='Dados completos'!AO198 -> Anúncio em plataforma | V27: =HYPERLINK('Dados completos'!AN198,"Abrir") -> Abrir
A28: ='Dados completos'!A199 -> 196 | B28: ='Dados completos'!AL199 -> Reserva | C28: ='Dados completos'!Y199 -> 2.7 | D28: ='Dados completos'!AF199 -> 88.3 | E28: ='Dados completos'!AH199 -> 0.175152 | F28: ='Dados completos'!AI199 -> Boa | G28: ='Dados completos'!B199 -> Empresa por confirmar | H28: ='Dados completos'!C199 -> Business Continuity Analyst Trainee (Lisboa) | I28: ='Dados completos'!E199 -> Serviços financeiros | J28: ='Dados completos'!F199 -> Portugal | K28: ='Dados completos'!G199 -> Lisboa | L28: ='Dados completos'!H199 -> Não indicado (provável presencial) | M28: ='Dados completos'!I199 -> Não indicado | N28: ='Dados completos'!O199 -> Não indicado | O28: ='Dados completos'!V199 -> Média | P28: =IF('Dados completos'!R199="","n/d",IF('Dados completos'!R199='Dados completos'!S199,TEXT('Dados completos'!R199,"#,##0"),TEXT('Dados completos'!R199,"#,##0")&", "&TEXT('Dados completos'!S199,"#,##0"))) -> 1,000, 1,400 | Q28: ='Dados completos'!M199 -> Inglês (ver oferta) | R28: ='Dados completos'!AJ199 -> Língua-chave EN (exigência 0.8); não exige experiência prévia em finanças; aceita recém-licenciadas. | S28: ='Dados completos'!AK199 -> Por confirmar | T28: ='Dados completos'!AP199 -> Parcial (agregador/título) | U28: ='Dados completos'!AO199 -> Anúncio em plataforma | V28: =HYPERLINK('Dados completos'!AN199,"Abrir") -> Abrir
A29: ='Dados completos'!A200 -> 197 | B29: ='Dados completos'!AL200 -> Reserva | C29: ='Dados completos'!Y200 -> 2.7 | D29: ='Dados completos'!AF200 -> 88.3 | E29: ='Dados completos'!AH200 -> 0.175152 | F29: ='Dados completos'!AI200 -> Boa | G29: ='Dados completos'!B200 -> Empresa por confirmar | H29: ='Dados completos'!C200 -> Data Quality Trainee (Lisboa) | I29: ='Dados completos'!E200 -> Serviços financeiros | J29: ='Dados completos'!F200 -> Portugal | K29: ='Dados completos'!G200 -> Lisboa | L29: ='Dados completos'!H200 -> Não indicado (provável presencial) | M29: ='Dados completos'!I200 -> Não indicado | N29: ='Dados completos'!O200 -> Não indicado | O29: ='Dados completos'!V200 -> Média | P29: =IF('Dados completos'!R200="","n/d",IF('Dados completos'!R200='Dados completos'!S200,TEXT('Dados completos'!R200,"#,##0"),TEXT('Dados completos'!R200,"#,##0")&", "&TEXT('Dados completos'!S200,"#,##0"))) -> 1,000, 1,400 | Q29: ='Dados completos'!M200 -> Inglês (ver oferta) | R29: ='Dados completos'!AJ200 -> Língua-chave EN (exigência 0.8); não exige experiência prévia em finanças; aceita recém-licenciadas. | S29: ='Dados completos'!AK200 -> Por confirmar | T29: ='Dados completos'!AP200 -> Parcial (agregador/título) | U29: ='Dados completos'!AO200 -> Anúncio em plataforma | V29: =HYPERLINK('Dados completos'!AN200,"Abrir") -> Abrir
A30: ='Dados completos'!A39 -> 36 | B30: ='Dados completos'!AL39 -> Reserva | C30: ='Dados completos'!Y39 -> 2.8 | D30: ='Dados completos'!AF39 -> 88 | E30: ='Dados completos'!AH39 -> 0.17472 | F30: ='Dados completos'!AI39 -> Boa | G30: ='Dados completos'!B39 -> Banco Santander Totta | H30: ='Dados completos'!C39 -> Estágio, Área de Fomento à Construção (Lisboa) | I30: ='Dados completos'!E39 -> Banca comercial | J30: ='Dados completos'!F39 -> Portugal | K30: ='Dados completos'!G39 -> Lisboa | L30: ='Dados completos'!H39 -> Não indicado (provável presencial) | M30: ='Dados completos'!I39 -> Não indicado | N30: ='Dados completos'!O39 -> Não indicado | O30: ='Dados completos'!V39 -> Média | P30: =IF('Dados completos'!R39="","n/d",IF('Dados completos'!R39='Dados completos'!S39,TEXT('Dados completos'!R39,"#,##0"),TEXT('Dados completos'!R39,"#,##0")&", "&TEXT('Dados completos'!S39,"#,##0"))) -> 1,000, 1,300 | Q30: ='Dados completos'!M39 -> Português | R30: ='Dados completos'!AJ39 -> Língua-chave PT (exigência 1); não exige experiência prévia em finanças; aceita recém-licenciadas. | S30: ='Dados completos'!AK39 -> Por confirmar | T30: ='Dados completos'!AP39 -> Parcial (agregador/título) | U30: ='Dados completos'!AO39 -> Página de carreiras (procurar a vaga) | V30: =HYPERLINK('Dados completos'!AN39,"Abrir") -> Abrir
A31: ='Dados completos'!A196 -> 193 | B31: ='Dados completos'!AL196 -> Candidatar (reach) | C31: ='Dados completos'!Y196 -> 3.3 | D31: ='Dados completos'!AF196 -> 87.55 | E31: ='Dados completos'!AH196 -> 0.116048 | F31: ='Dados completos'!AI196 -> Boa | G31: ='Dados completos'!B196 -> Empresa por confirmar | H31: ='Dados completos'!C196 -> Data Analyst Trainee (Lisboa) | I31: ='Dados completos'!E196 -> Serviços financeiros | J31: ='Dados completos'!F196 -> Portugal | K31: ='Dados completos'!G196 -> Lisboa | L31: ='Dados completos'!H196 -> Não indicado (provável presencial) | M31: ='Dados completos'!I196 -> Não indicado | N31: ='Dados completos'!O196 -> Não indicado | O31: ='Dados completos'!V196 -> Média-alta | P31: =IF('Dados completos'!R196="","n/d",IF('Dados completos'!R196='Dados completos'!S196,TEXT('Dados completos'!R196,"#,##0"),TEXT('Dados completos'!R196,"#,##0")&", "&TEXT('Dados completos'!S196,"#,##0"))) -> 1,100, 1,500 | Q31: ='Dados completos'!M196 -> Inglês (ver oferta) | R31: ='Dados completos'!AJ196 -> Língua-chave EN (exigência 0.8); não exige experiência prévia em finanças; aceita recém-licenciadas. | S31: ='Dados completos'!AK196 -> Por confirmar | T31: ='Dados completos'!AP196 -> Parcial (agregador/título) | U31: ='Dados completos'!AO196 -> Anúncio em plataforma | V31: =HYPERLINK('Dados completos'!AN196,"Abrir") -> Abrir
A32: ='Dados completos'!A189 -> 186 | B32: ='Dados completos'!AL189 -> Candidatar (reach) | C32: ='Dados completos'!Y189 -> 3.2 | D32: ='Dados completos'!AF189 -> 85.3 | E32: ='Dados completos'!AH189 -> 0.113888 | F32: ='Dados completos'!AI189 -> Boa | G32: ='Dados completos'!B189 -> Marsh | H32: ='Dados completos'!C189 -> Junior Analyst (estágio de 6 meses, Lisboa) | I32: ='Dados completos'!E189 -> Big 4 / consultoria | J32: ='Dados completos'!F189 -> Portugal | K32: ='Dados completos'!G189 -> Lisboa | L32: ='Dados completos'!H189 -> Não indicado (provável presencial) | M32: ='Dados completos'!I189 -> Não indicado | N32: ='Dados completos'!O189 -> Não indicado | O32: ='Dados completos'!V189 -> Média-alta | P32: =IF('Dados completos'!R189="","n/d",IF('Dados completos'!R189='Dados completos'!S189,TEXT('Dados completos'!R189,"#,##0"),TEXT('Dados completos'!R189,"#,##0")&", "&TEXT('Dados completos'!S189,"#,##0"))) -> 1,000, 1,400 | Q32: ='Dados completos'!M189 -> Inglês (ver oferta) | R32: ='Dados completos'!AJ189 -> Língua-chave EN (exigência 0.8); não exige experiência prévia em finanças; aceita recém-licenciadas. | S32: ='Dados completos'!AK189 -> Por confirmar | T32: ='Dados completos'!AP189 -> Parcial (agregador/título) | U32: ='Dados completos'!AO189 -> Anúncio em plataforma | V32: =HYPERLINK('Dados completos'!AN189,"Abrir") -> Abrir
A33: ='Dados completos'!A190 -> 187 | B33: ='Dados completos'!AL190 -> Candidatar (reach) | C33: ='Dados completos'!Y190 -> 3.2 | D33: ='Dados completos'!AF190 -> 85.15 | E33: ='Dados completos'!AH190 -> 0.113744 | F33: ='Dados completos'!AI190 -> Boa | G33: ='Dados completos'!B190 -> Marsh | H33: ='Dados completos'!C190 -> Insured Consulting Analyst, Ireland (estágio, Lisboa) | I33: ='Dados completos'!E190 -> Big 4 / consultoria | J33: ='Dados completos'!F190 -> Portugal | K33: ='Dados completos'!G190 -> Lisboa | L33: ='Dados completos'!H190 -> Não indicado (provável presencial) | M33: ='Dados completos'!I190 -> Não indicado | N33: ='Dados completos'!O190 -> Não indicado | O33: ='Dados completos'!V190 -> Média-alta | P33: =IF('Dados completos'!R190="","n/d",IF('Dados completos'!R190='Dados completos'!S190,TEXT('Dados completos'!R190,"#,##0"),TEXT('Dados completos'!R190,"#,##0")&", "&TEXT('Dados completos'!S190,"#,##0"))) -> 1,000, 1,400 | Q33: ='Dados completos'!M190 -> Inglês (ver oferta) | R33: ='Dados completos'!AJ190 -> Língua-chave EN (exigência 0.9); não exige experiência prévia em finanças; aceita recém-licenciadas. | S33: ='Dados completos'!AK190 -> Por confirmar | T33: ='Dados completos'!AP190 -> Parcial (agregador/título) | U33: ='Dados completos'!AO190 -> Anúncio em plataforma | V33: =HYPERLINK('Dados completos'!AN190,"Abrir") -> Abrir
A34: ='Dados completos'!A203 -> 200 | B34: ='Dados completos'!AL203 -> Candidatar (reach) | C34: ='Dados completos'!Y203 -> 3 | D34: ='Dados completos'!AF203 -> 77.75 | E34: ='Dados completos'!AH203 -> 0.10664 | F34: ='Dados completos'!AI203 -> Boa | G34: ='Dados completos'!B203 -> UNICRE | H34: ='Dados completos'!C203 -> Unlocker Junior Controller (Planeamento e Controlo de Gestão) | I34: ='Dados completos'!E203 -> Serviços financeiros | J34: ='Dados completos'!F203 -> Portugal | K34: ='Dados completos'!G203 -> Lisboa | L34: ='Dados completos'!H203 -> Não indicado (provável presencial) | M34: ='Dados completos'!I203 -> Não indicado | N34: ='Dados completos'!O203 -> 46314 | O34: ='Dados completos'!V203 -> Média-alta | P34: =IF('Dados completos'!R203="","n/d",IF('Dados completos'!R203='Dados completos'!S203,TEXT('Dados completos'!R203,"#,##0"),TEXT('Dados completos'!R203,"#,##0")&", "&TEXT('Dados completos'!S203,"#,##0"))) -> 1,200, 1,600 | Q34: ='Dados completos'!M203 -> Português e inglês | R34: ='Dados completos'!AJ203 -> Língua-chave PT (exigência 0.3); experiência prévia em finanças valorizada, CV tem pouca. | S34: ='Dados completos'!AK203 -> Aberta, prazo definido | T34: ='Dados completos'!AP203 -> Verificada na página | U34: ='Dados completos'!AO203 -> Anúncio em plataforma | V34: =HYPERLINK('Dados completos'!AN203,"Abrir") -> Abrir
A35: ='Dados completos'!A194 -> 191 | B35: ='Dados completos'!AL194 -> Reserva | C35: ='Dados completos'!Y194 -> 2.8 | D35: ='Dados completos'!AF194 -> 72.6 | E35: ='Dados completos'!AH194 -> 0.101696 | F35: ='Dados completos'!AI194 -> Boa | G35: ='Dados completos'!B194 -> Empresa por confirmar (VIE) | H35: ='Dados completos'!C194 -> ESG Data Analyst (VIE, Lisboa) | I35: ='Dados completos'!E194 -> Serviços financeiros | J35: ='Dados completos'!F194 -> Portugal | K35: ='Dados completos'!G194 -> Lisboa | L35: ='Dados completos'!H194 -> Não indicado (provável presencial) | M35: ='Dados completos'!I194 -> Não indicado | N35: ='Dados completos'!O194 -> Não indicado | O35: ='Dados completos'!V194 -> Média-alta | P35: =IF('Dados completos'!R194="","n/d",IF('Dados completos'!R194='Dados completos'!S194,TEXT('Dados completos'!R194,"#,##0"),TEXT('Dados completos'!R194,"#,##0")&", "&TEXT('Dados completos'!S194,"#,##0"))) -> 1,300, 1,800 | Q35: ='Dados completos'!M194 -> Inglês (ver oferta) | R35: ='Dados completos'!AJ194 -> Língua-chave FR (exigência 0.4); não exige experiência prévia em finanças; aceita recém-licenciadas. | S35: ='Dados completos'!AK194 -> Por confirmar | T35: ='Dados completos'!AP194 -> Parcial (agregador/título) | U35: ='Dados completos'!AO194 -> Anúncio em plataforma | V35: =HYPERLINK('Dados completos'!AN194,"Abrir") -> Abrir
A36: ='Dados completos'!A197 -> 194 | B36: ='Dados completos'!AL197 -> Candidatar (reach) | C36: ='Dados completos'!Y197 -> 3 | D36: ='Dados completos'!AF197 -> 87.55 | E36: ='Dados completos'!AH197 -> 0.116048 | F36: ='Dados completos'!AI197 -> Boa | G36: ='Dados completos'!B197 -> Empresa por confirmar | H36: ='Dados completos'!C197 -> Operational Risk Data Analyst Trainee (Lisboa) | I36: ='Dados completos'!E197 -> Serviços financeiros | J36: ='Dados completos'!F197 -> Portugal | K36: ='Dados completos'!G197 -> Lisboa | L36: ='Dados completos'!H197 -> Não indicado (provável presencial) | M36: ='Dados completos'!I197 -> Não indicado | N36: ='Dados completos'!O197 -> Não indicado | O36: ='Dados completos'!V197 -> Média-alta | P36: =IF('Dados completos'!R197="","n/d",IF('Dados completos'!R197='Dados completos'!S197,TEXT('Dados completos'!R197,"#,##0"),TEXT('Dados completos'!R197,"#,##0")&", "&TEXT('Dados completos'!S197,"#,##0"))) -> 1,100, 1,500 | Q36: ='Dados completos'!M197 -> Inglês (ver oferta) | R36: ='Dados completos'!AJ197 -> Língua-chave EN (exigência 0.8); não exige experiência prévia em finanças; aceita recém-licenciadas. | S36: ='Dados completos'!AK197 -> Por confirmar | T36: ='Dados completos'!AP197 -> Parcial (agregador/título) | U36: ='Dados completos'!AO197 -> Anúncio em plataforma | V36: =HYPERLINK('Dados completos'!AN197,"Abrir") -> Abrir
A37: ='Dados completos'!A219 -> 216 | B37: ='Dados completos'!AL219 -> Reserva | C37: ='Dados completos'!Y219 -> 2.9 | D37: ='Dados completos'!AF219 -> 87 | E37: ='Dados completos'!AH219 -> 0.11552 | F37: ='Dados completos'!AI219 -> Boa | G37: ='Dados completos'!B219 -> BNP Paribas Personal Finance | H37: ='Dados completos'!C219 -> Rising Talents (programa de 12 meses) | I37: ='Dados completos'!E219 -> Serviços financeiros | J37: ='Dados completos'!F219 -> Portugal | K37: ='Dados completos'!G219 -> Lisboa | L37: ='Dados completos'!H219 -> Não indicado (provável presencial) | M37: ='Dados completos'!I219 -> Não indicado | N37: ='Dados completos'!O219 -> Não indicado | O37: ='Dados completos'!V219 -> Média-alta | P37: =IF('Dados completos'!R219="","n/d",IF('Dados completos'!R219='Dados completos'!S219,TEXT('Dados completos'!R219,"#,##0"),TEXT('Dados completos'!R219,"#,##0")&", "&TEXT('Dados completos'!S219,"#,##0"))) -> 1,100, 1,500 | Q37: ='Dados completos'!M219 -> Inglês (ver oferta) | R37: ='Dados completos'!AJ219 -> Língua-chave PT (exigência 0.3); não exige experiência prévia em finanças; aceita recém-licenciadas. | S37: ='Dados completos'!AK219 -> Por confirmar | T37: ='Dados completos'!AP219 -> Parcial (agregador/título) | U37: ='Dados completos'!AO219 -> Anúncio em plataforma | V37: =HYPERLINK('Dados completos'!AN219,"Abrir") -> Abrir
A38: ='Dados completos'!A202 -> 199 | B38: ='Dados completos'!AL202 -> Reserva | C38: ='Dados completos'!Y202 -> 2 | D38: ='Dados completos'!AF202 -> 63.85 | E38: ='Dados completos'!AH202 -> 0.139944 | F38: ='Dados completos'!AI202 -> Boa | G38: ='Dados completos'!B202 -> Empresa por confirmar | H38: ='Dados completos'!C202 -> Customer Finance Intern, falante de francês (Lisboa) | I38: ='Dados completos'!E202 -> Serviços financeiros | J38: ='Dados completos'!F202 -> Portugal | K38: ='Dados completos'!G202 -> Lisboa | L38: ='Dados completos'!H202 -> Não indicado (provável presencial) | M38: ='Dados completos'!I202 -> Não indicado | N38: ='Dados completos'!O202 -> Não indicado | O38: ='Dados completos'!V202 -> Média | P38: =IF('Dados completos'!R202="","n/d",IF('Dados completos'!R202='Dados completos'!S202,TEXT('Dados completos'!R202,"#,##0"),TEXT('Dados completos'!R202,"#,##0")&", "&TEXT('Dados completos'!S202,"#,##0"))) -> 1,000, 1,300 | Q38: ='Dados completos'!M202 -> Francês e inglês (ver oferta) | R38: ='Dados completos'!AJ202 -> Língua-chave FR (exigência 0.9); não exige experiência prévia em finanças; aceita recém-licenciadas. | S38: ='Dados completos'!AK202 -> Por confirmar | T38: ='Dados completos'!AP202 -> Parcial (agregador/título) | U38: ='Dados completos'!AO202 -> Anúncio em plataforma | V38: =HYPERLINK('Dados completos'!AN202,"Abrir") -> Abrir
A39: ='Dados completos'!A164 -> 161 | B39: ='Dados completos'!AL164 -> Reserva | C39: ='Dados completos'!Y164 -> 2.6 | D39: ='Dados completos'!AF164 -> 92.5 | E39: ='Dados completos'!AH164 -> 0.1812 | F39: ='Dados completos'!AI164 -> Boa | G39: ='Dados completos'!B164 -> EY | H39: ='Dados completos'!C164 -> New Graduates January 2027, Assurance (Lisboa & Porto) | I39: ='Dados completos'!E164 -> Big 4 / consultoria | J39: ='Dados completos'!F164 -> Portugal | K39: ='Dados completos'!G164 -> Lisboa | L39: ='Dados completos'!H164 -> Não indicado (provável presencial) | M39: ='Dados completos'!I164 -> Jan 2027 | N39: ='Dados completos'!O164 -> Não indicado | O39: ='Dados completos'!V164 -> Média | P39: =IF('Dados completos'!R164="","n/d",IF('Dados completos'!R164='Dados completos'!S164,TEXT('Dados completos'!R164,"#,##0"),TEXT('Dados completos'!R164,"#,##0")&", "&TEXT('Dados completos'!S164,"#,##0"))) -> 1,000, 1,400 | Q39: ='Dados completos'!M164 -> Português e inglês (ver oferta) | R39: ='Dados completos'!AJ164 -> Língua-chave PT (exigência 1); não exige experiência prévia em finanças; aceita recém-licenciadas. | S39: ='Dados completos'!AK164 -> Por confirmar | T39: ='Dados completos'!AP164 -> Parcial (agregador/título) | U39: ='Dados completos'!AO164 -> Página de carreiras (procurar a vaga) | V39: =HYPERLINK('Dados completos'!AN164,"Abrir") -> Abrir
A40: ='Dados completos'!A170 -> 167 | B40: ='Dados completos'!AL170 -> Reserva | C40: ='Dados completos'!Y170 -> 2.6 | D40: ='Dados completos'!AF170 -> 92.5 | E40: ='Dados completos'!AH170 -> 0.1812 | F40: ='Dados completos'!AI170 -> Boa | G40: ='Dados completos'!B170 -> Auchan Retail Portugal | H40: ='Dados completos'!C170 -> Empower Trainee Program (estágio profissional, Grande Lisboa) | I40: ='Dados completos'!E170 -> Big corporate | J40: ='Dados completos'!F170 -> Portugal | K40: ='Dados completos'!G170 -> Lisboa | L40: ='Dados completos'!H170 -> Não indicado (provável presencial) | M40: ='Dados completos'!I170 -> Não indicado | N40: ='Dados completos'!O170 -> Não indicado | O40: ='Dados completos'!V170 -> Média | P40: =IF('Dados completos'!R170="","n/d",IF('Dados completos'!R170='Dados completos'!S170,TEXT('Dados completos'!R170,"#,##0"),TEXT('Dados completos'!R170,"#,##0")&", "&TEXT('Dados completos'!S170,"#,##0"))) -> 1,000, 1,250 | Q40: ='Dados completos'!M170 -> Inglês (ver oferta) | R40: ='Dados completos'!AJ170 -> Língua-chave PT (exigência 0.3); não exige experiência prévia em finanças; aceita recém-licenciadas. | S40: ='Dados completos'!AK170 -> Por confirmar | T40: ='Dados completos'!AP170 -> Parcial (agregador/título) | U40: ='Dados completos'!AO170 -> Direto (site/ATS da empresa) | V40: =HYPERLINK('Dados completos'!AN170,"Abrir") -> Abrir
A41: ='Dados completos'!A177 -> 174 | B41: ='Dados completos'!AL177 -> Reserva | C41: ='Dados completos'!Y177 -> 2.6 | D41: ='Dados completos'!AF177 -> 92.5 | E41: ='Dados completos'!AH177 -> 0.1812 | F41: ='Dados completos'!AI177 -> Boa | G41: ='Dados completos'!B177 -> Santander Portugal | H41: ='Dados completos'!C177 -> Estágio, Comunicação e Brand Management | I41: ='Dados completos'!E177 -> Banca comercial | J41: ='Dados completos'!F177 -> Portugal | K41: ='Dados completos'!G177 -> Lisboa | L41: ='Dados completos'!H177 -> Não indicado (provável presencial) | M41: ='Dados completos'!I177 -> Não indicado | N41: ='Dados completos'!O177 -> Não indicado | O41: ='Dados completos'!V177 -> Média | P41: =IF('Dados completos'!R177="","n/d",IF('Dados completos'!R177='Dados completos'!S177,TEXT('Dados completos'!R177,"#,##0"),TEXT('Dados completos'!R177,"#,##0")&", "&TEXT('Dados completos'!S177,"#,##0"))) -> 1,000, 1,300 | Q41: ='Dados completos'!M177 -> Inglês (ver oferta) | R41: ='Dados completos'!AJ177 -> Língua-chave PT (exigência 0.3); não exige experiência prévia em finanças; aceita recém-licenciadas. | S41: ='Dados completos'!AK177 -> Por confirmar | T41: ='Dados completos'!AP177 -> Parcial (agregador/título) | U41: ='Dados completos'!AO177 -> Direto (site/ATS da empresa) | V41: =HYPERLINK('Dados completos'!AN177,"Abrir") -> Abrir
A42: ='Dados completos'!A201 -> 198 | B42: ='Dados completos'!AL201 -> Reserva | C42: ='Dados completos'!Y201 -> 2.5 | D42: ='Dados completos'!AF201 -> 91.3 | E42: ='Dados completos'!AH201 -> 0.179472 | F42: ='Dados completos'!AI201 -> Boa | G42: ='Dados completos'!B201 -> Empresa por confirmar | H42: ='Dados completos'!C201 -> Account Payable Trainee, English Speaker (Lisboa) | I42: ='Dados completos'!E201 -> Serviços financeiros | J42: ='Dados completos'!F201 -> Portugal | K42: ='Dados completos'!G201 -> Lisboa | L42: ='Dados completos'!H201 -> Não indicado (provável presencial) | M42: ='Dados completos'!I201 -> Não indicado | N42: ='Dados completos'!O201 -> Não indicado | O42: ='Dados completos'!V201 -> Média | P42: =IF('Dados completos'!R201="","n/d",IF('Dados completos'!R201='Dados completos'!S201,TEXT('Dados completos'!R201,"#,##0"),TEXT('Dados completos'!R201,"#,##0")&", "&TEXT('Dados completos'!S201,"#,##0"))) -> 1,000, 1,300 | Q42: ='Dados completos'!M201 -> Inglês (ver oferta) | R42: ='Dados completos'!AJ201 -> Língua-chave EN (exigência 0.8); não exige experiência prévia em finanças; aceita recém-licenciadas. | S42: ='Dados completos'!AK201 -> Por confirmar | T42: ='Dados completos'!AP201 -> Parcial (agregador/título) | U42: ='Dados completos'!AO201 -> Anúncio em plataforma | V42: =HYPERLINK('Dados completos'!AN201,"Abrir") -> Abrir
A43: ='Dados completos'!A168 -> 165 | B43: ='Dados completos'!AL168 -> Reserva | C43: ='Dados completos'!Y168 -> 2.5 | D43: ='Dados completos'!AF168 -> 90 | E43: ='Dados completos'!AH168 -> 0.1776 | F43: ='Dados completos'!AI168 -> Boa | G43: ='Dados completos'!B168 -> CP, Comboios de Portugal | H43: ='Dados completos'!C168 -> CPTrainUP, 2.ª edição (trainees, início janeiro 2027) | I43: ='Dados completos'!E168 -> Big corporate | J43: ='Dados completos'!F168 -> Portugal | K43: ='Dados completos'!G168 -> Lisboa | L43: ='Dados completos'!H168 -> Não indicado (provável presencial) | M43: ='Dados completos'!I168 -> Jan 2027 | N43: ='Dados completos'!O168 -> Não indicado | O43: ='Dados completos'!V168 -> Média | P43: =IF('Dados completos'!R168="","n/d",IF('Dados completos'!R168='Dados completos'!S168,TEXT('Dados completos'!R168,"#,##0"),TEXT('Dados completos'!R168,"#,##0")&", "&TEXT('Dados completos'!S168,"#,##0"))) -> 1,100, 1,400 | Q43: ='Dados completos'!M168 -> Português | R43: ='Dados completos'!AJ168 -> Língua-chave PT (exigência 0.3); não exige experiência prévia em finanças; aceita recém-licenciadas. | S43: ='Dados completos'!AK168 -> Aberta (prazo não indicado) | T43: ='Dados completos'!AP168 -> Parcial (agregador/título) | U43: ='Dados completos'!AO168 -> Direto (site/ATS da empresa) | V43: =HYPERLINK('Dados completos'!AN168,"Abrir") -> Abrir
A44: ='Dados completos'!A68 -> 65 | B44: ='Dados completos'!AL68 -> Reserva | C44: ='Dados completos'!Y68 -> 2.4 | D44: ='Dados completos'!AF68 -> 51.25 | E44: ='Dados completos'!AH68 -> 0.0812 | F44: ='Dados completos'!AI68 -> Boa | G44: ='Dados completos'!B68 -> Rothschild & Co | H44: ='Dados completos'!C68 -> Administrative & Finance Intern, Five Arrows (Luxemburgo), Março 2027 | I44: ='Dados completos'!E68 -> Banca de investimento / boutique | J44: ='Dados completos'!F68 -> Luxemburgo | K44: ='Dados completos'!G68 -> Luxemburgo | L44: ='Dados completos'!H68 -> Não indicado (provável presencial) | M44: ='Dados completos'!I68 -> Mar 2027 (não é janeiro) | N44: ='Dados completos'!O68 -> Não indicado | O44: ='Dados completos'!V68 -> Média-alta | P44: =IF('Dados completos'!R68="","n/d",IF('Dados completos'!R68='Dados completos'!S68,TEXT('Dados completos'!R68,"#,##0"),TEXT('Dados completos'!R68,"#,##0")&", "&TEXT('Dados completos'!S68,"#,##0"))) -> 1,800, 2,500 | Q44: ='Dados completos'!M68 -> Francês e inglês (ver oferta) | R44: ='Dados completos'!AJ68 -> Língua-chave FR (exigência 0.5); experiência prévia em finanças valorizada, CV tem pouca; exige mestrado em curso ou convenção de estágio, risco. | S44: ='Dados completos'!AK68 -> Por confirmar | T44: ='Dados completos'!AP68 -> Parcial (agregador/título) | U44: ='Dados completos'!AO68 -> Direto (site/ATS da empresa) | V44: =HYPERLINK('Dados completos'!AN68,"Abrir") -> Abrir
A45: ='Dados completos'!A167 -> 164 | B45: ='Dados completos'!AL167 -> Reserva | C45: ='Dados completos'!Y167 -> 2.8 | D45: ='Dados completos'!AF167 -> 91 | E45: ='Dados completos'!AH167 -> 0.11936 | F45: ='Dados completos'!AI167 -> Boa | G45: ='Dados completos'!B167 -> Coca-Cola Europacific Partners | H45: ='Dados completos'!C167 -> Programa Graduates, Desenvolvimento Comercial (Lisboa) | I45: ='Dados completos'!E167 -> Big corporate | J45: ='Dados completos'!F167 -> Portugal | K45: ='Dados completos'!G167 -> Lisboa | L45: ='Dados completos'!H167 -> Não indicado (provável presencial) | M45: ='Dados completos'!I167 -> Não indicado | N45: ='Dados completos'!O167 -> Não indicado | O45: ='Dados completos'!V167 -> Média-alta | P45: =IF('Dados completos'!R167="","n/d",IF('Dados completos'!R167='Dados completos'!S167,TEXT('Dados completos'!R167,"#,##0"),TEXT('Dados completos'!R167,"#,##0")&", "&TEXT('Dados completos'!S167,"#,##0"))) -> 1,200, 1,600 | Q45: ='Dados completos'!M167 -> Inglês C1 (obrigatório); espanhol B2 (preferido) | R45: ='Dados completos'!AJ167 -> Língua-chave PT (exigência 0.3); não exige experiência prévia em finanças; aceita recém-licenciadas. | S45: ='Dados completos'!AK167 -> Aberta (prazo não indicado) | T45: ='Dados completos'!AP167 -> Parcial (agregador/título) | U45: ='Dados completos'!AO167 -> Direto (site/ATS da empresa) | V45: =HYPERLINK('Dados completos'!AN167,"Abrir") -> Abrir
A46: ='Dados completos'!A171 -> 168 | B46: ='Dados completos'!AL171 -> Reserva | C46: ='Dados completos'!Y171 -> 2.6 | D46: ='Dados completos'!AF171 -> 92.5 | E46: ='Dados completos'!AH171 -> 0.1208 | F46: ='Dados completos'!AI171 -> Boa | G46: ='Dados completos'!B171 -> AstraZeneca Portugal | H46: ='Dados completos'!C171 -> Life Changers, 3.ª edição (trainees, 11 meses) | I46: ='Dados completos'!E171 -> Big corporate | J46: ='Dados completos'!F171 -> Portugal | K46: ='Dados completos'!G171 -> Lisboa | L46: ='Dados completos'!H171 -> Não indicado (provável presencial) | M46: ='Dados completos'!I171 -> Não indicado | N46: ='Dados completos'!O171 -> Não indicado | O46: ='Dados completos'!V171 -> Média-alta | P46: =IF('Dados completos'!R171="","n/d",IF('Dados completos'!R171='Dados completos'!S171,TEXT('Dados completos'!R171,"#,##0"),TEXT('Dados completos'!R171,"#,##0")&", "&TEXT('Dados completos'!S171,"#,##0"))) -> 1,200, 1,600 | Q46: ='Dados completos'!M171 -> Inglês (ver oferta) | R46: ='Dados completos'!AJ171 -> Língua-chave PT (exigência 0.3); não exige experiência prévia em finanças; aceita recém-licenciadas. | S46: ='Dados completos'!AK171 -> Por confirmar | T46: ='Dados completos'!AP171 -> Parcial (agregador/título) | U46: ='Dados completos'!AO171 -> Direto (site/ATS da empresa) | V46: =HYPERLINK('Dados completos'!AN171,"Abrir") -> Abrir
A47: ='Dados completos'!A173 -> 170 | B47: ='Dados completos'!AL173 -> Reserva | C47: ='Dados completos'!Y173 -> 2.5 | D47: ='Dados completos'!AF173 -> 89.5 | E47: ='Dados completos'!AH173 -> 0.11792 | F47: ='Dados completos'!AI173 -> Boa | G47: ='Dados completos'!B173 -> Mondelēz International | H47: ='Dados completos'!C173 -> Taste the Future, Order to Cash Trainee | I47: ='Dados completos'!E173 -> Big corporate | J47: ='Dados completos'!F173 -> Portugal | K47: ='Dados completos'!G173 -> Lisboa | L47: ='Dados completos'!H173 -> Não indicado (provável presencial) | M47: ='Dados completos'!I173 -> Não indicado | N47: ='Dados completos'!O173 -> Não indicado | O47: ='Dados completos'!V173 -> Média-alta | P47: =IF('Dados completos'!R173="","n/d",IF('Dados completos'!R173='Dados completos'!S173,TEXT('Dados completos'!R173,"#,##0"),TEXT('Dados completos'!R173,"#,##0")&", "&TEXT('Dados completos'!S173,"#,##0"))) -> 1,000, 1,300 | Q47: ='Dados completos'!M173 -> Inglês (ver oferta) | R47: ='Dados completos'!AJ173 -> Língua-chave PT (exigência 0.3); não exige experiência prévia em finanças; aceita recém-licenciadas. | S47: ='Dados completos'!AK173 -> Por confirmar | T47: ='Dados completos'!AP173 -> Parcial (agregador/título) | U47: ='Dados completos'!AO173 -> Anúncio em plataforma | V47: =HYPERLINK('Dados completos'!AN173,"Abrir") -> Abrir
A48: ='Dados completos'!A158 -> 155 | B48: ='Dados completos'!AL158 -> Prioridade | C48: ='Dados completos'!Y158 -> 3.6 | D48: ='Dados completos'!AF158 -> 58 | E48: ='Dados completos'!AH158 -> 0.03288 | F48: ='Dados completos'!AI158 -> Média | G48: ='Dados completos'!B158 -> Eurazeo | H48: ='Dados completos'!C158 -> Internship, Growth (Paris, S1 2027) | I48: ='Dados completos'!E158 -> VC / private equity | J48: ='Dados completos'!F158 -> França | K48: ='Dados completos'!G158 -> Paris | L48: ='Dados completos'!H158 -> Não indicado (provável presencial) | M48: ='Dados completos'!I158 -> Jan 2027 (S1) | N48: ='Dados completos'!O158 -> Não indicado | O48: ='Dados completos'!V158 -> Alta | P48: =IF('Dados completos'!R158="","n/d",IF('Dados completos'!R158='Dados completos'!S158,TEXT('Dados completos'!R158,"#,##0"),TEXT('Dados completos'!R158,"#,##0")&", "&TEXT('Dados completos'!S158,"#,##0"))) -> 1,500, 2,500 | Q48: ='Dados completos'!M158 -> Inglês (ver oferta) | R48: ='Dados completos'!AJ158 -> Língua-chave EN (exigência 1); experiência prévia em finanças valorizada, CV tem pouca; exige mestrado em curso ou convenção de estágio, risco. | S48: ='Dados completos'!AK158 -> Por confirmar | T48: ='Dados completos'!AP158 -> Parcial (agregador/título) | U48: ='Dados completos'!AO158 -> Anúncio em plataforma | V48: =HYPERLINK('Dados completos'!AN158,"Abrir") -> Abrir
A49: ='Dados completos'!A224 -> 221 | B49: ='Dados completos'!AL224 -> Prioridade | C49: ='Dados completos'!Y224 -> 3.5 | D49: ='Dados completos'!AF224 -> 65 | E49: ='Dados completos'!AH224 -> 0.0354 | F49: ='Dados completos'!AI224 -> Média | G49: ='Dados completos'!B224 -> Portugal Ventures | H49: ='Dados completos'!C224 -> Candidatura espontânea (venture capital, Lisboa/Porto) | I49: ='Dados completos'!E224 -> VC / private equity | J49: ='Dados completos'!F224 -> Portugal | K49: ='Dados completos'!G224 -> Lisboa | L49: ='Dados completos'!H224 -> Não indicado (provável presencial) | M49: ='Dados completos'!I224 -> Não indicado | N49: ='Dados completos'!O224 -> Não indicado | O49: ='Dados completos'!V224 -> Alta | P49: =IF('Dados completos'!R224="","n/d",IF('Dados completos'!R224='Dados completos'!S224,TEXT('Dados completos'!R224,"#,##0"),TEXT('Dados completos'!R224,"#,##0")&", "&TEXT('Dados completos'!S224,"#,##0"))) -> 1,000, 1,300 | Q49: ='Dados completos'!M224 -> Inglês (ver oferta) | R49: ='Dados completos'!AJ224 -> Língua-chave PT (exigência 0.3); pede experiência prévia em IB/PE/consultoria, o CV mostrado não tem. | S49: ='Dados completos'!AK224 -> Via a explorar | T49: ='Dados completos'!AP224 -> Por confirmar | U49: ='Dados completos'!AO224 -> Página de carreiras (procurar a vaga) | V49: =HYPERLINK('Dados completos'!AN224,"Abrir") -> Abrir
A50: ='Dados completos'!A225 -> 222 | B50: ='Dados completos'!AL225 -> Prioridade | C50: ='Dados completos'!Y225 -> 3.5 | D50: ='Dados completos'!AF225 -> 65 | E50: ='Dados completos'!AH225 -> 0.0354 | F50: ='Dados completos'!AI225 -> Média | G50: ='Dados completos'!B225 -> Armilar Venture Partners | H50: ='Dados completos'!C225 -> Candidatura espontânea (venture capital, Lisboa) | I50: ='Dados completos'!E225 -> VC / private equity | J50: ='Dados completos'!F225 -> Portugal | K50: ='Dados completos'!G225 -> Lisboa | L50: ='Dados completos'!H225 -> Não indicado (provável presencial) | M50: ='Dados completos'!I225 -> Não indicado | N50: ='Dados completos'!O225 -> Não indicado | O50: ='Dados completos'!V225 -> Alta | P50: =IF('Dados completos'!R225="","n/d",IF('Dados completos'!R225='Dados completos'!S225,TEXT('Dados completos'!R225,"#,##0"),TEXT('Dados completos'!R225,"#,##0")&", "&TEXT('Dados completos'!S225,"#,##0"))) -> 1,000, 1,300 | Q50: ='Dados completos'!M225 -> Inglês (ver oferta) | R50: ='Dados completos'!AJ225 -> Língua-chave PT (exigência 0.3); pede experiência prévia em IB/PE/consultoria, o CV mostrado não tem. | S50: ='Dados completos'!AK225 -> Via a explorar | T50: ='Dados completos'!AP225 -> Por confirmar | U50: ='Dados completos'!AO225 -> Página de carreiras (procurar a vaga) | V50: =HYPERLINK('Dados completos'!AN225,"Abrir") -> Abrir
A51: ='Dados completos'!A226 -> 223 | B51: ='Dados completos'!AL226 -> Prioridade | C51: ='Dados completos'!Y226 -> 3.5 | D51: ='Dados completos'!AF226 -> 65 | E51: ='Dados completos'!AH226 -> 0.0354 | F51: ='Dados completos'!AI226 -> Média | G51: ='Dados completos'!B226 -> Indico Capital Partners | H51: ='Dados completos'!C226 -> Candidatura espontânea (venture capital, Lisboa) | I51: ='Dados completos'!E226 -> VC / private equity | J51: ='Dados completos'!F226 -> Portugal | K51: ='Dados completos'!G226 -> Lisboa | L51: ='Dados completos'!H226 -> Não indicado (provável presencial) | M51: ='Dados completos'!I226 -> Não indicado | N51: ='Dados completos'!O226 -> Não indicado | O51: ='Dados completos'!V226 -> Alta | P51: =IF('Dados completos'!R226="","n/d",IF('Dados completos'!R226='Dados completos'!S226,TEXT('Dados completos'!R226,"#,##0"),TEXT('Dados completos'!R226,"#,##0")&", "&TEXT('Dados completos'!S226,"#,##0"))) -> 1,000, 1,300 | Q51: ='Dados completos'!M226 -> Inglês (ver oferta) | R51: ='Dados completos'!AJ226 -> Língua-chave PT (exigência 0.3); pede experiência prévia em IB/PE/consultoria, o CV mostrado não tem. | S51: ='Dados completos'!AK226 -> Via a explorar | T51: ='Dados completos'!AP226 -> Por confirmar | U51: ='Dados completos'!AO226 -> Página de carreiras (procurar a vaga) | V51: =HYPERLINK('Dados completos'!AN226,"Abrir") -> Abrir
A52: ='Dados completos'!A69 -> 66 | B52: ='Dados completos'!AL69 -> Reserva | C52: ='Dados completos'!Y69 -> 1.8 | D52: ='Dados completos'!AF69 -> 45.55 | E52: ='Dados completos'!AH69 -> 0.075728 | F52: ='Dados completos'!AI69 -> Média | G52: ='Dados completos'!B69 -> Rothschild & Co | H52: ='Dados completos'!C69 -> Stage Fund Controlling (6 meses), Janvier 2027 (Luxemburgo) | I52: ='Dados completos'!E69 -> Banca de investimento / boutique | J52: ='Dados completos'!F69 -> Luxemburgo | K52: ='Dados completos'!G69 -> Luxemburgo | L52: ='Dados completos'!H69 -> Não indicado (provável presencial) | M52: ='Dados completos'!I69 -> Jan 2027 | N52: ='Dados completos'!O69 -> Não indicado | O52: ='Dados completos'!V69 -> Média-alta | P52: =IF('Dados completos'!R69="","n/d",IF('Dados completos'!R69='Dados completos'!S69,TEXT('Dados completos'!R69,"#,##0"),TEXT('Dados completos'!R69,"#,##0")&", "&TEXT('Dados completos'!S69,"#,##0"))) -> 1,800, 2,500 | Q52: ='Dados completos'!M69 -> Francês e inglês (ver oferta) | R52: ='Dados completos'!AJ69 -> Língua-chave FR (exigência 0.7); experiência prévia em finanças valorizada, CV tem pouca; exige mestrado em curso ou convenção de estágio, risco. | S52: ='Dados completos'!AK69 -> Por confirmar | T52: ='Dados completos'!AP69 -> Parcial (agregador/título) | U52: ='Dados completos'!AO69 -> Anúncio em plataforma | V52: =HYPERLINK('Dados completos'!AN69,"Abrir") -> Abrir
A53: ='Dados completos'!A70 -> 67 | B53: ='Dados completos'!AL70 -> Reserva | C53: ='Dados completos'!Y70 -> 1.8 | D53: ='Dados completos'!AF70 -> 45.55 | E53: ='Dados completos'!AH70 -> 0.075728 | F53: ='Dados completos'!AI70 -> Média | G53: ='Dados completos'!B70 -> Rothschild & Co | H53: ='Dados completos'!C70 -> Stage Comptabilité et Reporting (6 meses), Janvier 2027 (Luxemburgo) | I53: ='Dados completos'!E70 -> Banca de investimento / boutique | J53: ='Dados completos'!F70 -> Luxemburgo | K53: ='Dados completos'!G70 -> Luxemburgo | L53: ='Dados completos'!H70 -> Não indicado (provável presencial) | M53: ='Dados completos'!I70 -> Jan 2027 | N53: ='Dados completos'!O70 -> Não indicado | O53: ='Dados completos'!V70 -> Média-alta | P53: =IF('Dados completos'!R70="","n/d",IF('Dados completos'!R70='Dados completos'!S70,TEXT('Dados completos'!R70,"#,##0"),TEXT('Dados completos'!R70,"#,##0")&", "&TEXT('Dados completos'!S70,"#,##0"))) -> 1,800, 2,500 | Q53: ='Dados completos'!M70 -> Francês e inglês (ver oferta) | R53: ='Dados completos'!AJ70 -> Língua-chave FR (exigência 0.7); experiência prévia em finanças valorizada, CV tem pouca; exige mestrado em curso ou convenção de estágio, risco. | S53: ='Dados completos'!AK70 -> Por confirmar | T53: ='Dados completos'!AP70 -> Parcial (agregador/título) | U53: ='Dados completos'!AO70 -> Direto (site/ATS da empresa) | V53: =HYPERLINK('Dados completos'!AN70,"Abrir") -> Abrir
A54: ='Dados completos'!A23 -> 20 | B54: ='Dados completos'!AL23 -> Candidatar (reach) | C54: ='Dados completos'!Y23 -> 3.4 | D54: ='Dados completos'!AF23 -> 71 | E54: ='Dados completos'!AH23 -> 0.03756 | F54: ='Dados completos'!AI23 -> Média | G54: ='Dados completos'!B23 -> Eurazeo | H54: ='Dados completos'!C23 -> Internship, Strategy and M&A (Paris, S1 2027) | I54: ='Dados completos'!E23 -> VC / private equity | J54: ='Dados completos'!F23 -> França | K54: ='Dados completos'!G23 -> Paris | L54: ='Dados completos'!H23 -> Não indicado (provável presencial) | M54: ='Dados completos'!I23 -> Jan 2027 (ou ASAP) | N54: ='Dados completos'!O23 -> Aberta até a oferta sair | O54: ='Dados completos'!V23 -> Alta | P54: =IF('Dados completos'!R23="","n/d",IF('Dados completos'!R23='Dados completos'!S23,TEXT('Dados completos'!R23,"#,##0"),TEXT('Dados completos'!R23,"#,##0")&", "&TEXT('Dados completos'!S23,"#,##0"))) -> 1,500, 2,200 | Q54: ='Dados completos'!M23 -> Inglês (nível alto) | R54: ='Dados completos'!AJ23 -> Língua-chave EN (exigência 1); não exige experiência prévia em finanças; exige mestrado em curso ou convenção de estágio, risco. | S54: ='Dados completos'!AK23 -> Aberta (rolling) | T54: ='Dados completos'!AP23 -> Verificada na página | U54: ='Dados completos'!AO23 -> Anúncio em plataforma | V54: =HYPERLINK('Dados completos'!AN23,"Abrir") -> Abrir
A55: ='Dados completos'!A227 -> 224 | B55: ='Dados completos'!AL227 -> Candidatar (reach) | C55: ='Dados completos'!Y227 -> 3.2 | D55: ='Dados completos'!AF227 -> 65.5 | E55: ='Dados completos'!AH227 -> 0.03558 | F55: ='Dados completos'!AI227 -> Média | G55: ='Dados completos'!B227 -> Banco Português de Fomento | H55: ='Dados completos'!C227 -> Bolsa de emprego (investimento, fundos e fomento) | I55: ='Dados completos'!E227 -> Setor público / instituição | J55: ='Dados completos'!F227 -> Portugal | K55: ='Dados completos'!G227 -> Lisboa | L55: ='Dados completos'!H227 -> Não indicado (provável presencial) | M55: ='Dados completos'!I227 -> Não indicado | N55: ='Dados completos'!O227 -> Não indicado | O55: ='Dados completos'!V227 -> Alta | P55: =IF('Dados completos'!R227="","n/d",IF('Dados completos'!R227='Dados completos'!S227,TEXT('Dados completos'!R227,"#,##0"),TEXT('Dados completos'!R227,"#,##0")&", "&TEXT('Dados completos'!S227,"#,##0"))) -> 1,100, 1,500 | Q55: ='Dados completos'!M227 -> Inglês (ver oferta) | R55: ='Dados completos'!AJ227 -> Língua-chave PT (exigência 0.3); pede experiência prévia em IB/PE/consultoria, o CV mostrado não tem. | S55: ='Dados completos'!AK227 -> Via a explorar | T55: ='Dados completos'!AP227 -> Por confirmar | U55: ='Dados completos'!AO227 -> Página de carreiras (procurar a vaga) | V55: =HYPERLINK('Dados completos'!AN227,"Abrir") -> Abrir
A56: ='Dados completos'!A24 -> 21 | B56: ='Dados completos'!AL24 -> Candidatar (reach) | C56: ='Dados completos'!Y24 -> 3.4 | D56: ='Dados completos'!AF24 -> 62.5 | E56: ='Dados completos'!AH24 -> 0.0345 | F56: ='Dados completos'!AI24 -> Média | G56: ='Dados completos'!B24 -> Eurazeo | H56: ='Dados completos'!C24 -> Internship, Private Debt Direct Lending (Paris, S1 2027) | I56: ='Dados completos'!E24 -> VC / private equity | J56: ='Dados completos'!F24 -> França | K56: ='Dados completos'!G24 -> Paris | L56: ='Dados completos'!H24 -> Não indicado (provável presencial) | M56: ='Dados completos'!I24 -> Jan 2027 (ou Mar) | N56: ='Dados completos'!O24 -> Aberta até a oferta sair | O56: ='Dados completos'!V24 -> Alta | P56: =IF('Dados completos'!R24="","n/d",IF('Dados completos'!R24='Dados completos'!S24,TEXT('Dados completos'!R24,"#,##0"),TEXT('Dados completos'!R24,"#,##0")&", "&TEXT('Dados completos'!S24,"#,##0"))) -> 1,500, 2,200 | Q56: ='Dados completos'!M24 -> Inglês (fluente, obrigatório) | R56: ='Dados completos'!AJ24 -> Língua-chave EN (exigência 1); experiência prévia em finanças valorizada, CV tem pouca; exige mestrado em curso ou convenção de estágio, risco. | S56: ='Dados completos'!AK24 -> Aberta (rolling) | T56: ='Dados completos'!AP24 -> Verificada na página | U56: ='Dados completos'!AO24 -> Anúncio em plataforma | V56: =HYPERLINK('Dados completos'!AN24,"Abrir") -> Abrir
A57: ='Dados completos'!A130 -> 127 | B57: ='Dados completos'!AL130 -> Candidatar (reach) | C57: ='Dados completos'!Y130 -> 3.1 | D57: ='Dados completos'!AF130 -> 60.5 | E57: ='Dados completos'!AH130 -> 0.03378 | F57: ='Dados completos'!AI130 -> Média | G57: ='Dados completos'!B130 -> Carlsquare | H57: ='Dados completos'!C130 -> M&A Internship, Q1 2027 (Londres) | I57: ='Dados completos'!E130 -> Banca de investimento / boutique | J57: ='Dados completos'!F130 -> Reino Unido | K57: ='Dados completos'!G130 -> Londres | L57: ='Dados completos'!H130 -> Não indicado (provável presencial) | M57: ='Dados completos'!I130 -> Q1 2027 | N57: ='Dados completos'!O130 -> Não indicado | O57: ='Dados completos'!V130 -> Alta | P57: =IF('Dados completos'!R130="","n/d",IF('Dados completos'!R130='Dados completos'!S130,TEXT('Dados completos'!R130,"#,##0"),TEXT('Dados completos'!R130,"#,##0")&", "&TEXT('Dados completos'!S130,"#,##0"))) -> 2,800, 4,000 | Q57: ='Dados completos'!M130 -> Inglês (ver oferta) | R57: ='Dados completos'!AJ130 -> Língua-chave EN (exigência 1); experiência prévia em finanças valorizada, CV tem pouca; exige mestrado em curso ou convenção de estágio, risco. | S57: ='Dados completos'!AK130 -> Por confirmar | T57: ='Dados completos'!AP130 -> Parcial (agregador/título) | U57: ='Dados completos'!AO130 -> Direto (site/ATS da empresa) | V57: =HYPERLINK('Dados completos'!AN130,"Abrir") -> Abrir
A58: ='Dados completos'!A131 -> 128 | B58: ='Dados completos'!AL131 -> Candidatar (reach) | C58: ='Dados completos'!Y131 -> 3.1 | D58: ='Dados completos'!AF131 -> 60.5 | E58: ='Dados completos'!AH131 -> 0.03378 | F58: ='Dados completos'!AI131 -> Média | G58: ='Dados completos'!B131 -> Mizuho | H58: ='Dados completos'!C131 -> Off-Cycle Internship, Investment Banking (Londres) | I58: ='Dados completos'!E131 -> Banca de investimento | J58: ='Dados completos'!F131 -> Reino Unido | K58: ='Dados completos'!G131 -> Londres | L58: ='Dados completos'!H131 -> Não indicado (provável presencial) | M58: ='Dados completos'!I131 -> Por confirmar | N58: ='Dados completos'!O131 -> Não indicado | O58: ='Dados completos'!V131 -> Alta | P58: =IF('Dados completos'!R131="","n/d",IF('Dados completos'!R131='Dados completos'!S131,TEXT('Dados completos'!R131,"#,##0"),TEXT('Dados completos'!R131,"#,##0")&", "&TEXT('Dados completos'!S131,"#,##0"))) -> 2,800, 4,000 | Q58: ='Dados completos'!M131 -> Inglês (ver oferta) | R58: ='Dados completos'!AJ131 -> Língua-chave EN (exigência 1); experiência prévia em finanças valorizada, CV tem pouca; exige mestrado em curso ou convenção de estágio, risco. | S58: ='Dados completos'!AK131 -> Por confirmar | T58: ='Dados completos'!AP131 -> Parcial (agregador/título) | U58: ='Dados completos'!AO131 -> Página de carreiras (procurar a vaga) | V58: =HYPERLINK('Dados completos'!AN131,"Abrir") -> Abrir
A59: ='Dados completos'!A157 -> 154 | B59: ='Dados completos'!AL157 -> Candidatar (reach) | C59: ='Dados completos'!Y157 -> 3 | D59: ='Dados completos'!AF157 -> 58 | E59: ='Dados completos'!AH157 -> 0.03288 | F59: ='Dados completos'!AI157 -> Média | G59: ='Dados completos'!B157 -> Eurazeo | H59: ='Dados completos'!C157 -> Internship, Infrastructure (Paris, S1 2027) | I59: ='Dados completos'!E157 -> VC / private equity | J59: ='Dados completos'!F157 -> França | K59: ='Dados completos'!G157 -> Paris | L59: ='Dados completos'!H157 -> Não indicado (provável presencial) | M59: ='Dados completos'!I157 -> Jan 2027 (S1) | N59: ='Dados completos'!O157 -> Não indicado | O59: ='Dados completos'!V157 -> Alta | P59: =IF('Dados completos'!R157="","n/d",IF('Dados completos'!R157='Dados completos'!S157,TEXT('Dados completos'!R157,"#,##0"),TEXT('Dados completos'!R157,"#,##0")&", "&TEXT('Dados completos'!S157,"#,##0"))) -> 1,500, 2,500 | Q59: ='Dados completos'!M157 -> Inglês (ver oferta) | R59: ='Dados completos'!AJ157 -> Língua-chave EN (exigência 1); experiência prévia em finanças valorizada, CV tem pouca; exige mestrado em curso ou convenção de estágio, risco. | S59: ='Dados completos'!AK157 -> Por confirmar | T59: ='Dados completos'!AP157 -> Parcial (agregador/título) | U59: ='Dados completos'!AO157 -> Anúncio em plataforma | V59: =HYPERLINK('Dados completos'!AN157,"Abrir") -> Abrir
A60: ='Dados completos'!A160 -> 157 | B60: ='Dados completos'!AL160 -> Candidatar (reach) | C60: ='Dados completos'!Y160 -> 3 | D60: ='Dados completos'!AF160 -> 58 | E60: ='Dados completos'!AH160 -> 0.03288 | F60: ='Dados completos'!AI160 -> Média | G60: ='Dados completos'!B160 -> Eurazeo | H60: ='Dados completos'!C160 -> Stage, Real Estate (Paris, S1 2027) | I60: ='Dados completos'!E160 -> VC / private equity | J60: ='Dados completos'!F160 -> França | K60: ='Dados completos'!G160 -> Paris | L60: ='Dados completos'!H160 -> Não indicado (provável presencial) | M60: ='Dados completos'!I160 -> Jan 2027 (S1) | N60: ='Dados completos'!O160 -> Não indicado | O60: ='Dados completos'!V160 -> Alta | P60: =IF('Dados completos'!R160="","n/d",IF('Dados completos'!R160='Dados completos'!S160,TEXT('Dados completos'!R160,"#,##0"),TEXT('Dados completos'!R160,"#,##0")&", "&TEXT('Dados completos'!S160,"#,##0"))) -> 1,500, 2,500 | Q60: ='Dados completos'!M160 -> Inglês (ver oferta) | R60: ='Dados completos'!AJ160 -> Língua-chave EN (exigência 1); experiência prévia em finanças valorizada, CV tem pouca; exige mestrado em curso ou convenção de estágio, risco. | S60: ='Dados completos'!AK160 -> Por confirmar | T60: ='Dados completos'!AP160 -> Parcial (agregador/título) | U60: ='Dados completos'!AO160 -> Anúncio em plataforma | V60: =HYPERLINK('Dados completos'!AN160,"Abrir") -> Abrir
A61: ='Dados completos'!A165 -> 162 | B61: ='Dados completos'!AL165 -> Candidatar (reach) | C61: ='Dados completos'!Y165 -> 3 | D61: ='Dados completos'!AF165 -> 86.5 | E61: ='Dados completos'!AH165 -> 0.04314 | F61: ='Dados completos'!AI165 -> Média | G61: ='Dados completos'!B165 -> Mastercard | H61: ='Dados completos'!C165 -> Global Markets, Graduate Launch Program 2027 (Lisboa) | I61: ='Dados completos'!E165 -> Big corporate | J61: ='Dados completos'!F165 -> Portugal | K61: ='Dados completos'!G165 -> Lisboa | L61: ='Dados completos'!H165 -> Não indicado (provável presencial) | M61: ='Dados completos'!I165 -> 2027 | N61: ='Dados completos'!O165 -> 46320 | O61: ='Dados completos'!V165 -> Alta | P61: =IF('Dados completos'!R165="","n/d",IF('Dados completos'!R165='Dados completos'!S165,TEXT('Dados completos'!R165,"#,##0"),TEXT('Dados completos'!R165,"#,##0")&", "&TEXT('Dados completos'!S165,"#,##0"))) -> 1,000, 1,400 | Q61: ='Dados completos'!M165 -> Inglês (ver oferta) | R61: ='Dados completos'!AJ165 -> Língua-chave EN (exigência 1); não exige experiência prévia em finanças; aceita recém-licenciadas. | S61: ='Dados completos'!AK165 -> Aberta, prazo definido | T61: ='Dados completos'!AP165 -> Parcial (agregador/título) | U61: ='Dados completos'!AO165 -> Direto (site/ATS da empresa) | V61: =HYPERLINK('Dados completos'!AN165,"Abrir") -> Abrir
A62: ='Dados completos'!A5 -> 2 | B62: ='Dados completos'!AL5 -> Candidatar (reach) | C62: ='Dados completos'!Y5 -> 3.2 | D62: ='Dados completos'!AF5 -> 54.5 | E62: ='Dados completos'!AH5 -> 0.03162 | F62: ='Dados completos'!AI5 -> Média | G62: ='Dados completos'!B5 -> Rothschild & Co | H62: ='Dados completos'!C5 -> Global Advisory Spain, Madrid Long Term Internship | I62: ='Dados completos'!E5 -> Banca de investimento / boutique | J62: ='Dados completos'!F5 -> Espanha | K62: ='Dados completos'!G5 -> Madrid | L62: ='Dados completos'!H5 -> Não indicado (provável presencial) | M62: ='Dados completos'!I5 -> Jan ou Jul 2027 (a indicar na candidatura) | N62: ='Dados completos'!O5 -> Não indicado | O62: ='Dados completos'!V5 -> Alta | P62: =IF('Dados completos'!R5="","n/d",IF('Dados completos'!R5='Dados completos'!S5,TEXT('Dados completos'!R5,"#,##0"),TEXT('Dados completos'!R5,"#,##0")&", "&TEXT('Dados completos'!S5,"#,##0"))) -> 1,000, 1,800 | Q62: ='Dados completos'!M5 -> Espanhol e inglês (nível alto) | R62: ='Dados completos'!AJ5 -> Língua-chave ES (exigência 1); experiência prévia em finanças valorizada, CV tem pouca. | S62: ='Dados completos'!AK5 -> Aberta (prazo não indicado) | T62: ='Dados completos'!AP5 -> Verificada na página | U62: ='Dados completos'!AO5 -> Direto (site/ATS da empresa) | V62: =HYPERLINK('Dados completos'!AN5,"Abrir") -> Abrir
A63: ='Dados completos'!A92 -> 89 | B63: ='Dados completos'!AL92 -> Candidatar (reach) | C63: ='Dados completos'!Y92 -> 3 | D63: ='Dados completos'!AF92 -> 53.6 | E63: ='Dados completos'!AH92 -> 0.031296 | F63: ='Dados completos'!AI92 -> Média | G63: ='Dados completos'!B92 -> PGIM Private Capital | H63: ='Dados completos'!C92 -> Intern, Real Estate Private Equity Portfolio Management (Q1 2027, Frankfurt) | I63: ='Dados completos'!E92 -> VC / private equity | J63: ='Dados completos'!F92 -> Alemanha | K63: ='Dados completos'!G92 -> Frankfurt | L63: ='Dados completos'!H92 -> Não indicado (provável presencial) | M63: ='Dados completos'!I92 -> Q1 2027 | N63: ='Dados completos'!O92 -> Não indicado | O63: ='Dados completos'!V92 -> Alta | P63: =IF('Dados completos'!R92="","n/d",IF('Dados completos'!R92='Dados completos'!S92,TEXT('Dados completos'!R92,"#,##0"),TEXT('Dados completos'!R92,"#,##0")&", "&TEXT('Dados completos'!S92,"#,##0"))) -> 1,800, 2,800 | Q63: ='Dados completos'!M92 -> Inglês (ver oferta) | R63: ='Dados completos'!AJ92 -> Língua-chave DE (exigência 0.4); experiência prévia em finanças valorizada, CV tem pouca; exige mestrado em curso ou convenção de estágio, risco. | S63: ='Dados completos'!AK92 -> Por confirmar | T63: ='Dados completos'!AP92 -> Parcial (agregador/título) | U63: ='Dados completos'!AO92 -> Direto (site/ATS da empresa) | V63: =HYPERLINK('Dados completos'!AN92,"Abrir") -> Abrir
A64: ='Dados completos'!A25 -> 22 | B64: ='Dados completos'!AL25 -> Reserva | C64: ='Dados completos'!Y25 -> 2.8 | D64: ='Dados completos'!AF25 -> 82.5 | E64: ='Dados completos'!AH25 -> 0.0417 | F64: ='Dados completos'!AI25 -> Média | G64: ='Dados completos'!B25 -> European Investment Bank (EIB) | H64: ='Dados completos'!C25 -> Traineeship Programme (sessão março-abril 2027) | I64: ='Dados completos'!E25 -> Setor público / instituição | J64: ='Dados completos'!F25 -> Luxemburgo | K64: ='Dados completos'!G25 -> Luxemburgo | L64: ='Dados completos'!H25 -> Não indicado (provável presencial) | M64: ='Dados completos'!I25 -> Mar-Abr 2027 (não é janeiro) | N64: ='Dados completos'!O25 -> Vagas anunciadas ~4 meses antes (novembro) | O64: ='Dados completos'!V25 -> Alta | P64: =IF('Dados completos'!R25="","n/d",IF('Dados completos'!R25='Dados completos'!S25,TEXT('Dados completos'!R25,"#,##0"),TEXT('Dados completos'!R25,"#,##0")&", "&TEXT('Dados completos'!S25,"#,##0"))) -> 1,500 | Q64: ='Dados completos'!M25 -> Inglês e/ou francês | R64: ='Dados completos'!AJ25 -> Língua-chave EN (exigência 1); não exige experiência prévia em finanças; aceita recém-licenciadas. | S64: ='Dados completos'!AK25 -> Por confirmar | T64: ='Dados completos'!AP25 -> Verificada na página | U64: ='Dados completos'!AO25 -> Página de carreiras (procurar a vaga) | V64: =HYPERLINK('Dados completos'!AN25,"Abrir") -> Abrir
A65: ='Dados completos'!A155 -> 152 | B65: ='Dados completos'!AL155 -> Candidatar (reach) | C65: ='Dados completos'!Y155 -> 3 | D65: ='Dados completos'!AF155 -> 52.75 | E65: ='Dados completos'!AH155 -> 0.03099 | F65: ='Dados completos'!AI155 -> Média | G65: ='Dados completos'!B155 -> Alantra | H65: ='Dados completos'!C155 -> IB Q1 2027 M&A Intern (Frankfurt) | I65: ='Dados completos'!E155 -> Banca de investimento / boutique | J65: ='Dados completos'!F155 -> Alemanha | K65: ='Dados completos'!G155 -> Frankfurt | L65: ='Dados completos'!H155 -> Não indicado (provável presencial) | M65: ='Dados completos'!I155 -> Q1 2027 | N65: ='Dados completos'!O155 -> Não indicado | O65: ='Dados completos'!V155 -> Alta | P65: =IF('Dados completos'!R155="","n/d",IF('Dados completos'!R155='Dados completos'!S155,TEXT('Dados completos'!R155,"#,##0"),TEXT('Dados completos'!R155,"#,##0")&", "&TEXT('Dados completos'!S155,"#,##0"))) -> 1,800, 2,800 | Q65: ='Dados completos'!M155 -> Alemão e inglês (ver oferta) | R65: ='Dados completos'!AJ155 -> Língua-chave DE (exigência 0.5); experiência prévia em finanças valorizada, CV tem pouca. | S65: ='Dados completos'!AK155 -> Por confirmar | T65: ='Dados completos'!AP155 -> Parcial (agregador/título) | U65: ='Dados completos'!AO155 -> Direto (site/ATS da empresa) | V65: =HYPERLINK('Dados completos'!AN155,"Abrir") -> Abrir
A66: ='Dados completos'!A11 -> 8 | B66: ='Dados completos'!AL11 -> Candidatar (reach) | C66: ='Dados completos'!Y11 -> 3.2 | D66: ='Dados completos'!AF11 -> 52 | E66: ='Dados completos'!AH11 -> 0.03072 | F66: ='Dados completos'!AI11 -> Média | G66: ='Dados completos'!B11 -> Alantra | H66: ='Dados completos'!C11 -> Investment Banking Off-Cycle Internship Programme, January 2027 | I66: ='Dados completos'!E11 -> Banca de investimento / boutique | J66: ='Dados completos'!F11 -> Espanha | K66: ='Dados completos'!G11 -> Madrid | L66: ='Dados completos'!H11 -> Não indicado (provável presencial) | M66: ='Dados completos'!I11 -> Jan 2027 | N66: ='Dados completos'!O11 -> Não indicado | O66: ='Dados completos'!V11 -> Alta | P66: =IF('Dados completos'!R11="","n/d",IF('Dados completos'!R11='Dados completos'!S11,TEXT('Dados completos'!R11,"#,##0"),TEXT('Dados completos'!R11,"#,##0")&", "&TEXT('Dados completos'!S11,"#,##0"))) -> 1,000, 1,800 | Q66: ='Dados completos'!M11 -> Inglês e espanhol (bilingue/quase nativo) | R66: ='Dados completos'!AJ11 -> Língua-chave ES (exigência 1); pede experiência prévia em IB/PE/consultoria, o CV mostrado não tem; aceita recém-licenciadas. | S66: ='Dados completos'!AK11 -> Aberta (prazo não indicado) | T66: ='Dados completos'!AP11 -> Verificada na página | U66: ='Dados completos'!AO11 -> Direto (site/ATS da empresa) | V66: =HYPERLINK('Dados completos'!AN11,"Abrir") -> Abrir
A67: ='Dados completos'!A175 -> 172 | B67: ='Dados completos'!AL175 -> Reserva | C67: ='Dados completos'!Y175 -> 2.8 | D67: ='Dados completos'!AF175 -> 63.5 | E67: ='Dados completos'!AH175 -> 0.03486 | F67: ='Dados completos'!AI175 -> Média | G67: ='Dados completos'!B175 -> Bankinter Portugal | H67: ='Dados completos'!C175 -> Analista Financeiro, Desenvolvimento de Negócio, Banca Digital e Meios de Pagamento | I67: ='Dados completos'!E175 -> Banca comercial | J67: ='Dados completos'!F175 -> Portugal | K67: ='Dados completos'!G175 -> Lisboa | L67: ='Dados completos'!H175 -> Não indicado (provável presencial) | M67: ='Dados completos'!I175 -> Não indicado | N67: ='Dados completos'!O175 -> Não indicado | O67: ='Dados completos'!V175 -> Alta | P67: =IF('Dados completos'!R175="","n/d",IF('Dados completos'!R175='Dados completos'!S175,TEXT('Dados completos'!R175,"#,##0"),TEXT('Dados completos'!R175,"#,##0")&", "&TEXT('Dados completos'!S175,"#,##0"))) -> 1,500, 2,000 | Q67: ='Dados completos'!M175 -> Inglês (ver oferta) | R67: ='Dados completos'!AJ175 -> Língua-chave PT (exigência 0.3); experiência prévia em finanças valorizada, CV tem pouca; exige mestrado em curso ou convenção de estágio, risco. | S67: ='Dados completos'!AK175 -> Aberta (prazo não indicado) | T67: ='Dados completos'!AP175 -> Parcial (agregador/título) | U67: ='Dados completos'!AO175 -> Anúncio em plataforma | V67: =HYPERLINK('Dados completos'!AN175,"Abrir") -> Abrir
A68: ='Dados completos'!A67 -> 64 | B68: ='Dados completos'!AL67 -> Reserva | C68: ='Dados completos'!Y67 -> 2.8 | D68: ='Dados completos'!AF67 -> 61.25 | E68: ='Dados completos'!AH67 -> 0.03405 | F68: ='Dados completos'!AI67 -> Média | G68: ='Dados completos'!B67 -> Rothschild & Co | H68: ='Dados completos'!C67 -> Global Advisory Internship, Poland 2027 | I68: ='Dados completos'!E67 -> Banca de investimento / boutique | J68: ='Dados completos'!F67 -> Polónia | K68: ='Dados completos'!G67 -> Varsóvia | L68: ='Dados completos'!H67 -> Não indicado (provável presencial) | M68: ='Dados completos'!I67 -> 2027 (mês por confirmar) | N68: ='Dados completos'!O67 -> Não indicado | O68: ='Dados completos'!V67 -> Alta | P68: =IF('Dados completos'!R67="","n/d",IF('Dados completos'!R67='Dados completos'!S67,TEXT('Dados completos'!R67,"#,##0"),TEXT('Dados completos'!R67,"#,##0")&", "&TEXT('Dados completos'!S67,"#,##0"))) -> 800, 1,400 | Q68: ='Dados completos'!M67 -> Inglês (ver oferta) | R68: ='Dados completos'!AJ67 -> Língua-chave EN (exigência 0.5); experiência prévia em finanças valorizada, CV tem pouca; exige mestrado em curso ou convenção de estágio, risco. | S68: ='Dados completos'!AK67 -> Por confirmar | T68: ='Dados completos'!AP67 -> Parcial (agregador/título) | U68: ='Dados completos'!AO67 -> Direto (site/ATS da empresa) | V68: =HYPERLINK('Dados completos'!AN67,"Abrir") -> Abrir
A69: ='Dados completos'!A90 -> 87 | B69: ='Dados completos'!AL90 -> Candidatar (reach) | C69: ='Dados completos'!Y90 -> 3 | D69: ='Dados completos'!AF90 -> 49.4 | E69: ='Dados completos'!AH90 -> 0.029784 | F69: ='Dados completos'!AI90 -> Baixa | G69: ='Dados completos'!B90 -> Tikehau Capital | H69: ='Dados completos'!C90 -> Internship, Private Debt Milan, January 2027 | I69: ='Dados completos'!E90 -> VC / private equity | J69: ='Dados completos'!F90 -> Itália | K69: ='Dados completos'!G90 -> Milão | L69: ='Dados completos'!H90 -> Não indicado (provável presencial) | M69: ='Dados completos'!I90 -> Jan 2027 | N69: ='Dados completos'!O90 -> Não indicado | O69: ='Dados completos'!V90 -> Alta | P69: =IF('Dados completos'!R90="","n/d",IF('Dados completos'!R90='Dados completos'!S90,TEXT('Dados completos'!R90,"#,##0"),TEXT('Dados completos'!R90,"#,##0")&", "&TEXT('Dados completos'!S90,"#,##0"))) -> 800, 1,500 | Q69: ='Dados completos'!M90 -> Italiano e inglês (ver oferta) | R69: ='Dados completos'!AJ90 -> Língua-chave IT (exigência 0.6); experiência prévia em finanças valorizada, CV tem pouca; exige mestrado em curso ou convenção de estágio, risco. | S69: ='Dados completos'!AK90 -> Por confirmar | T69: ='Dados completos'!AP90 -> Parcial (agregador/título) | U69: ='Dados completos'!AO90 -> Direto (site/ATS da empresa) | V69: =HYPERLINK('Dados completos'!AN90,"Abrir") -> Abrir
A70: ='Dados completos'!A135 -> 132 | B70: ='Dados completos'!AL135 -> Reserva | C70: ='Dados completos'!Y135 -> 2.8 | D70: ='Dados completos'!AF135 -> 60.5 | E70: ='Dados completos'!AH135 -> 0.03378 | F70: ='Dados completos'!AI135 -> Média | G70: ='Dados completos'!B135 -> Wells Fargo | H70: ='Dados completos'!C135 -> Off-Cycle Internship, Corporate & Investment Banking (Londres) | I70: ='Dados completos'!E135 -> Banca de investimento | J70: ='Dados completos'!F135 -> Reino Unido | K70: ='Dados completos'!G135 -> Londres | L70: ='Dados completos'!H135 -> Não indicado (provável presencial) | M70: ='Dados completos'!I135 -> Por confirmar | N70: ='Dados completos'!O135 -> Não indicado | O70: ='Dados completos'!V135 -> Alta | P70: =IF('Dados completos'!R135="","n/d",IF('Dados completos'!R135='Dados completos'!S135,TEXT('Dados completos'!R135,"#,##0"),TEXT('Dados completos'!R135,"#,##0")&", "&TEXT('Dados completos'!S135,"#,##0"))) -> 2,800, 4,000 | Q70: ='Dados completos'!M135 -> Inglês (ver oferta) | R70: ='Dados completos'!AJ135 -> Língua-chave EN (exigência 1); experiência prévia em finanças valorizada, CV tem pouca; exige mestrado em curso ou convenção de estágio, risco. | S70: ='Dados completos'!AK135 -> Por confirmar | T70: ='Dados completos'!AP135 -> Parcial (agregador/título) | U70: ='Dados completos'!AO135 -> Página de carreiras (procurar a vaga) | V70: =HYPERLINK('Dados completos'!AN135,"Abrir") -> Abrir
A71: ='Dados completos'!A129 -> 126 | B71: ='Dados completos'!AL129 -> Reserva | C71: ='Dados completos'!Y129 -> 2.9 | D71: ='Dados completos'!AF129 -> 47.75 | E71: ='Dados completos'!AH129 -> 0.02919 | F71: ='Dados completos'!AI129 -> Baixa | G71: ='Dados completos'!B129 -> Carlsquare | H71: ='Dados completos'!C129 -> M&A Internship (m/f/d), January 2027 (Paris) | I71: ='Dados completos'!E129 -> Banca de investimento / boutique | J71: ='Dados completos'!F129 -> França | K71: ='Dados completos'!G129 -> Paris | L71: ='Dados completos'!H129 -> Não indicado (provável presencial) | M71: ='Dados completos'!I129 -> Jan 2027 | N71: ='Dados completos'!O129 -> Não indicado | O71: ='Dados completos'!V129 -> Alta | P71: =IF('Dados completos'!R129="","n/d",IF('Dados completos'!R129='Dados completos'!S129,TEXT('Dados completos'!R129,"#,##0"),TEXT('Dados completos'!R129,"#,##0")&", "&TEXT('Dados completos'!S129,"#,##0"))) -> 1,500, 2,500 | Q71: ='Dados completos'!M129 -> Francês e inglês (ver oferta) | R71: ='Dados completos'!AJ129 -> Língua-chave FR (exigência 0.5); experiência prévia em finanças valorizada, CV tem pouca; exige mestrado em curso ou convenção de estágio, risco. | S71: ='Dados completos'!AK129 -> Por confirmar | T71: ='Dados completos'!AP129 -> Parcial (agregador/título) | U71: ='Dados completos'!AO129 -> Direto (site/ATS da empresa) | V71: =HYPERLINK('Dados completos'!AN129,"Abrir") -> Abrir
A72: ='Dados completos'!A145 -> 142 | B72: ='Dados completos'!AL145 -> Reserva | C72: ='Dados completos'!Y145 -> 2.9 | D72: ='Dados completos'!AF145 -> 47.75 | E72: ='Dados completos'!AH145 -> 0.02919 | F72: ='Dados completos'!AI145 -> Baixa | G72: ='Dados completos'!B145 -> Lincoln International | H72: ='Dados completos'!C145 -> M&A Internship, Janeiro 2027 | I72: ='Dados completos'!E145 -> Banca de investimento / boutique | J72: ='Dados completos'!F145 -> França | K72: ='Dados completos'!G145 -> Paris | L72: ='Dados completos'!H145 -> Não indicado (provável presencial) | M72: ='Dados completos'!I145 -> Jan 2027 | N72: ='Dados completos'!O145 -> Não indicado | O72: ='Dados completos'!V145 -> Alta | P72: =IF('Dados completos'!R145="","n/d",IF('Dados completos'!R145='Dados completos'!S145,TEXT('Dados completos'!R145,"#,##0"),TEXT('Dados completos'!R145,"#,##0")&", "&TEXT('Dados completos'!S145,"#,##0"))) -> 1,500, 2,500 | Q72: ='Dados completos'!M145 -> Francês e inglês (ver oferta) | R72: ='Dados completos'!AJ145 -> Língua-chave FR (exigência 0.5); experiência prévia em finanças valorizada, CV tem pouca; exige mestrado em curso ou convenção de estágio, risco. | S72: ='Dados completos'!AK145 -> Por confirmar | T72: ='Dados completos'!AP145 -> Parcial (agregador/título) | U72: ='Dados completos'!AO145 -> Direto (site/ATS da empresa) | V72: =HYPERLINK('Dados completos'!AN145,"Abrir") -> Abrir
A73: ='Dados completos'!A138 -> 135 | B73: ='Dados completos'!AL138 -> Reserva | C73: ='Dados completos'!Y138 -> 2.9 | D73: ='Dados completos'!AF138 -> 45.2 | E73: ='Dados completos'!AH138 -> 0.028272 | F73: ='Dados completos'!AI138 -> Baixa | G73: ='Dados completos'!B138 -> Mediobanca | H73: ='Dados completos'!C138 -> Spain Off-Cycle Internship, Investment Banking (M&A) | I73: ='Dados completos'!E138 -> Banca de investimento / boutique | J73: ='Dados completos'!F138 -> Espanha | K73: ='Dados completos'!G138 -> Madrid | L73: ='Dados completos'!H138 -> Não indicado (provável presencial) | M73: ='Dados completos'!I138 -> Por confirmar | N73: ='Dados completos'!O138 -> Não indicado | O73: ='Dados completos'!V138 -> Alta | P73: =IF('Dados completos'!R138="","n/d",IF('Dados completos'!R138='Dados completos'!S138,TEXT('Dados completos'!R138,"#,##0"),TEXT('Dados completos'!R138,"#,##0")&", "&TEXT('Dados completos'!S138,"#,##0"))) -> 1,000, 1,800 | Q73: ='Dados completos'!M138 -> Espanhol e inglês (ver oferta) | R73: ='Dados completos'!AJ138 -> Língua-chave ES (exigência 0.8); experiência prévia em finanças valorizada, CV tem pouca; exige mestrado em curso ou convenção de estágio, risco. | S73: ='Dados completos'!AK138 -> Por confirmar | T73: ='Dados completos'!AP138 -> Parcial (agregador/título) | U73: ='Dados completos'!AO138 -> Direto (site/ATS da empresa) | V73: =HYPERLINK('Dados completos'!AN138,"Abrir") -> Abrir
A74: ='Dados completos'!A37 -> 34 | B74: ='Dados completos'!AL37 -> Candidatar (reach) | C74: ='Dados completos'!Y37 -> 3.2 | D74: ='Dados completos'!AF37 -> 45.05 | E74: ='Dados completos'!AH37 -> 0.028218 | F74: ='Dados completos'!AI37 -> Baixa | G74: ='Dados completos'!B37 -> Neuplaner | H74: ='Dados completos'!C37 -> Praktikant, M&A Investment Team (Berlim) | I74: ='Dados completos'!E37 -> Banca de investimento / boutique | J74: ='Dados completos'!F37 -> Alemanha | K74: ='Dados completos'!G37 -> Berlim | L74: ='Dados completos'!H37 -> Não indicado (provável presencial) | M74: ='Dados completos'!I37 -> Q1 ou Q2 2027 | N74: ='Dados completos'!O37 -> Não indicado | O74: ='Dados completos'!V37 -> Alta | P74: =IF('Dados completos'!R37="","n/d",IF('Dados completos'!R37='Dados completos'!S37,TEXT('Dados completos'!R37,"#,##0"),TEXT('Dados completos'!R37,"#,##0")&", "&TEXT('Dados completos'!S37,"#,##0"))) -> 1,200, 2,000 | Q74: ='Dados completos'!M37 -> Alemão provável | R74: ='Dados completos'!AJ37 -> Língua-chave DE (exigência 0.7); experiência prévia em finanças valorizada, CV tem pouca; exige mestrado em curso ou convenção de estágio, risco. | S74: ='Dados completos'!AK37 -> Por confirmar | T74: ='Dados completos'!AP37 -> Parcial (agregador/título) | U74: ='Dados completos'!AO37 -> Anúncio em plataforma | V74: =HYPERLINK('Dados completos'!AN37,"Abrir") -> Abrir
A75: ='Dados completos'!A77 -> 74 | B75: ='Dados completos'!AL77 -> Reserva | C75: ='Dados completos'!Y77 -> 2.6 | D75: ='Dados completos'!AF77 -> 68 | E75: ='Dados completos'!AH77 -> 0.03648 | F75: ='Dados completos'!AI77 -> Média | G75: ='Dados completos'!B77 -> PAI Partners | H75: ='Dados completos'!C77 -> DealCloud internship (6 meses, Londres) | I75: ='Dados completos'!E77 -> VC / private equity | J75: ='Dados completos'!F77 -> Reino Unido | K75: ='Dados completos'!G77 -> Londres | L75: ='Dados completos'!H77 -> Não indicado (provável presencial) | M75: ='Dados completos'!I77 -> Por confirmar | N75: ='Dados completos'!O77 -> Não indicado | O75: ='Dados completos'!V77 -> Alta | P75: =IF('Dados completos'!R77="","n/d",IF('Dados completos'!R77='Dados completos'!S77,TEXT('Dados completos'!R77,"#,##0"),TEXT('Dados completos'!R77,"#,##0")&", "&TEXT('Dados completos'!S77,"#,##0"))) -> 2,800, 4,000 | Q75: ='Dados completos'!M77 -> Inglês (ver oferta) | R75: ='Dados completos'!AJ77 -> Língua-chave EN (exigência 1); experiência prévia em finanças valorizada, CV tem pouca; exige mestrado em curso ou convenção de estágio, risco. | S75: ='Dados completos'!AK77 -> Por confirmar | T75: ='Dados completos'!AP77 -> Parcial (agregador/título) | U75: ='Dados completos'!AO77 -> Direto (site/ATS da empresa) | V75: =HYPERLINK('Dados completos'!AN77,"Abrir") -> Abrir
A76: ='Dados completos'!A223 -> 220 | B76: ='Dados completos'!AL223 -> Reserva | C76: ='Dados completos'!Y223 -> 2.6 | D76: ='Dados completos'!AF223 -> 67.5 | E76: ='Dados completos'!AH223 -> 0.0363 | F76: ='Dados completos'!AI223 -> Média | G76: ='Dados completos'!B223 -> Feedzai | H76: ='Dados completos'!C223 -> Customer Strategy and Value Associate (Lisboa) | I76: ='Dados completos'!E223 -> Startup / scale-up | J76: ='Dados completos'!F223 -> Portugal | K76: ='Dados completos'!G223 -> Lisboa | L76: ='Dados completos'!H223 -> Não indicado (provável presencial) | M76: ='Dados completos'!I223 -> Não indicado | N76: ='Dados completos'!O223 -> Não indicado | O76: ='Dados completos'!V223 -> Alta | P76: =IF('Dados completos'!R223="","n/d",IF('Dados completos'!R223='Dados completos'!S223,TEXT('Dados completos'!R223,"#,##0"),TEXT('Dados completos'!R223,"#,##0")&", "&TEXT('Dados completos'!S223,"#,##0"))) -> 1,400, 2,000 | Q76: ='Dados completos'!M223 -> Inglês (ver oferta) | R76: ='Dados completos'!AJ223 -> Língua-chave EN (exigência 1); experiência prévia em finanças valorizada, CV tem pouca. | S76: ='Dados completos'!AK223 -> Aberta (prazo não indicado) | T76: ='Dados completos'!AP223 -> Parcial (agregador/título) | U76: ='Dados completos'!AO223 -> Direto (site/ATS da empresa) | V76: =HYPERLINK('Dados completos'!AN223,"Abrir") -> Abrir
A77: ='Dados completos'!A149 -> 146 | B77: ='Dados completos'!AL149 -> Reserva | C77: ='Dados completos'!Y149 -> 2.9 | D77: ='Dados completos'!AF149 -> 42.05 | E77: ='Dados completos'!AH149 -> 0.027138 | F77: ='Dados completos'!AI149 -> Baixa | G77: ='Dados completos'!B149 -> Natixis CIB | H77: ='Dados completos'!C149 -> Off-Cycle Internship, Corporate & Investment Banking (Paris) | I77: ='Dados completos'!E149 -> Banca de investimento | J77: ='Dados completos'!F149 -> França | K77: ='Dados completos'!G149 -> Paris | L77: ='Dados completos'!H149 -> Não indicado (provável presencial) | M77: ='Dados completos'!I149 -> Por confirmar | N77: ='Dados completos'!O149 -> Não indicado | O77: ='Dados completos'!V149 -> Alta | P77: =IF('Dados completos'!R149="","n/d",IF('Dados completos'!R149='Dados completos'!S149,TEXT('Dados completos'!R149,"#,##0"),TEXT('Dados completos'!R149,"#,##0")&", "&TEXT('Dados completos'!S149,"#,##0"))) -> 1,500, 2,500 | Q77: ='Dados completos'!M149 -> Francês e inglês (ver oferta) | R77: ='Dados completos'!AJ149 -> Língua-chave FR (exigência 0.7); experiência prévia em finanças valorizada, CV tem pouca; exige mestrado em curso ou convenção de estágio, risco. | S77: ='Dados completos'!AK149 -> Por confirmar | T77: ='Dados completos'!AP149 -> Parcial (agregador/título) | U77: ='Dados completos'!AO149 -> Página de carreiras (procurar a vaga) | V77: =HYPERLINK('Dados completos'!AN149,"Abrir") -> Abrir
A78: ='Dados completos'!A94 -> 91 | B78: ='Dados completos'!AL94 -> Reserva | C78: ='Dados completos'!Y94 -> 2.9 | D78: ='Dados completos'!AF94 -> 41.2 | E78: ='Dados completos'!AH94 -> 0.026832 | F78: ='Dados completos'!AI94 -> Baixa | G78: ='Dados completos'!B94 -> INDEFI Group | H78: ='Dados completos'!C94 -> Strategy Consultant Internship, Private Equity, Janvier 2027 | I78: ='Dados completos'!E94 -> Banca de investimento / boutique | J78: ='Dados completos'!F94 -> França | K78: ='Dados completos'!G94 -> Paris | L78: ='Dados completos'!H94 -> Não indicado (provável presencial) | M78: ='Dados completos'!I94 -> Jan 2027 | N78: ='Dados completos'!O94 -> Não indicado | O78: ='Dados completos'!V94 -> Alta | P78: =IF('Dados completos'!R94="","n/d",IF('Dados completos'!R94='Dados completos'!S94,TEXT('Dados completos'!R94,"#,##0"),TEXT('Dados completos'!R94,"#,##0")&", "&TEXT('Dados completos'!S94,"#,##0"))) -> 1,500, 2,500 | Q78: ='Dados completos'!M94 -> Francês e inglês (ver oferta) | R78: ='Dados completos'!AJ94 -> Língua-chave FR (exigência 0.8); experiência prévia em finanças valorizada, CV tem pouca; exige mestrado em curso ou convenção de estágio, risco. | S78: ='Dados completos'!AK94 -> Por confirmar | T78: ='Dados completos'!AP94 -> Parcial (agregador/título) | U78: ='Dados completos'!AO94 -> Anúncio em plataforma | V78: =HYPERLINK('Dados completos'!AN94,"Abrir") -> Abrir
A79: ='Dados completos'!A52 -> 49 | B79: ='Dados completos'!AL52 -> Reserva | C79: ='Dados completos'!Y52 -> 2.7 | D79: ='Dados completos'!AF52 -> 51.25 | E79: ='Dados completos'!AH52 -> 0.03045 | F79: ='Dados completos'!AI52 -> Média | G79: ='Dados completos'!B52 -> Ardian | H79: ='Dados completos'!C52 -> Corporate Finance Intern, January 2027 | I79: ='Dados completos'!E52 -> VC / private equity | J79: ='Dados completos'!F52 -> Luxemburgo | K79: ='Dados completos'!G52 -> Luxemburgo | L79: ='Dados completos'!H52 -> Não indicado (provável presencial) | M79: ='Dados completos'!I52 -> Jan 2027 | N79: ='Dados completos'!O52 -> Não indicado | O79: ='Dados completos'!V52 -> Alta | P79: =IF('Dados completos'!R52="","n/d",IF('Dados completos'!R52='Dados completos'!S52,TEXT('Dados completos'!R52,"#,##0"),TEXT('Dados completos'!R52,"#,##0")&", "&TEXT('Dados completos'!S52,"#,##0"))) -> 1,800, 2,500 | Q79: ='Dados completos'!M52 -> Francês e inglês (ver oferta) | R79: ='Dados completos'!AJ52 -> Língua-chave FR (exigência 0.5); experiência prévia em finanças valorizada, CV tem pouca; exige mestrado em curso ou convenção de estágio, risco. | S79: ='Dados completos'!AK52 -> Por confirmar | T79: ='Dados completos'!AP52 -> Parcial (agregador/título) | U79: ='Dados completos'!AO52 -> Direto (site/ATS da empresa) | V79: =HYPERLINK('Dados completos'!AN52,"Abrir") -> Abrir
A80: ='Dados completos'!A72 -> 69 | B80: ='Dados completos'!AL72 -> Reserva | C80: ='Dados completos'!Y72 -> 2.7 | D80: ='Dados completos'!AF72 -> 50.75 | E80: ='Dados completos'!AH72 -> 0.03027 | F80: ='Dados completos'!AI72 -> Média | G80: ='Dados completos'!B72 -> Revaia | H80: ='Dados completos'!C72 -> Finance & Operations Intern, Growth Equity Fund (6 meses desde janeiro 2027) | I80: ='Dados completos'!E72 -> VC / private equity | J80: ='Dados completos'!F72 -> França | K80: ='Dados completos'!G72 -> Paris | L80: ='Dados completos'!H72 -> Não indicado (provável presencial) | M80: ='Dados completos'!I72 -> Jan 2027 | N80: ='Dados completos'!O72 -> Não indicado | O80: ='Dados completos'!V72 -> Alta | P80: =IF('Dados completos'!R72="","n/d",IF('Dados completos'!R72='Dados completos'!S72,TEXT('Dados completos'!R72,"#,##0"),TEXT('Dados completos'!R72,"#,##0")&", "&TEXT('Dados completos'!S72,"#,##0"))) -> 1,500, 2,500 | Q80: ='Dados completos'!M72 -> Francês e inglês (ver oferta) | R80: ='Dados completos'!AJ72 -> Língua-chave FR (exigência 0.5); experiência prévia em finanças valorizada, CV tem pouca; exige mestrado em curso ou convenção de estágio, risco. | S80: ='Dados completos'!AK72 -> Por confirmar | T80: ='Dados completos'!AP72 -> Parcial (agregador/título) | U80: ='Dados completos'!AO72 -> Direto (site/ATS da empresa) | V80: =HYPERLINK('Dados completos'!AN72,"Abrir") -> Abrir
A81: ='Dados completos'!A89 -> 86 | B81: ='Dados completos'!AL89 -> Reserva | C81: ='Dados completos'!Y89 -> 2.9 | D81: ='Dados completos'!AF89 -> 39.2 | E81: ='Dados completos'!AH89 -> 0.026112 | F81: ='Dados completos'!AI89 -> Baixa | G81: ='Dados completos'!B89 -> Tikehau Capital | H81: ='Dados completos'!C89 -> Internship, Financial Analyst (Paris), Mar 2027 | I81: ='Dados completos'!E89 -> VC / private equity | J81: ='Dados completos'!F89 -> França | K81: ='Dados completos'!G89 -> Paris | L81: ='Dados completos'!H89 -> Não indicado (provável presencial) | M81: ='Dados completos'!I89 -> Mar 2027 (não é janeiro) | N81: ='Dados completos'!O89 -> Não indicado | O81: ='Dados completos'!V89 -> Alta | P81: =IF('Dados completos'!R89="","n/d",IF('Dados completos'!R89='Dados completos'!S89,TEXT('Dados completos'!R89,"#,##0"),TEXT('Dados completos'!R89,"#,##0")&", "&TEXT('Dados completos'!S89,"#,##0"))) -> 1,500, 2,500 | Q81: ='Dados completos'!M89 -> Francês e inglês (ver oferta) | R81: ='Dados completos'!AJ89 -> Língua-chave FR (exigência 0.8); experiência prévia em finanças valorizada, CV tem pouca; exige mestrado em curso ou convenção de estágio, risco. | S81: ='Dados completos'!AK89 -> Por confirmar | T81: ='Dados completos'!AP89 -> Parcial (agregador/título) | U81: ='Dados completos'!AO89 -> Direto (site/ATS da empresa) | V81: =HYPERLINK('Dados completos'!AN89,"Abrir") -> Abrir
A82: ='Dados completos'!A146 -> 143 | B82: ='Dados completos'!AL146 -> Reserva | C82: ='Dados completos'!Y146 -> 2.6 | D82: ='Dados completos'!AF146 -> 47.75 | E82: ='Dados completos'!AH146 -> 0.02919 | F82: ='Dados completos'!AI146 -> Baixa | G82: ='Dados completos'!B146 -> Lincoln International | H82: ='Dados completos'!C146 -> Debt Advisory Internship, Março 2027 | I82: ='Dados completos'!E146 -> Banca de investimento / boutique | J82: ='Dados completos'!F146 -> França | K82: ='Dados completos'!G146 -> Paris | L82: ='Dados completos'!H146 -> Não indicado (provável presencial) | M82: ='Dados completos'!I146 -> Mar 2027 (não é janeiro) | N82: ='Dados completos'!O146 -> Não indicado | O82: ='Dados completos'!V146 -> Alta | P82: =IF('Dados completos'!R146="","n/d",IF('Dados completos'!R146='Dados completos'!S146,TEXT('Dados completos'!R146,"#,##0"),TEXT('Dados completos'!R146,"#,##0")&", "&TEXT('Dados completos'!S146,"#,##0"))) -> 1,500, 2,500 | Q82: ='Dados completos'!M146 -> Francês e inglês (ver oferta) | R82: ='Dados completos'!AJ146 -> Língua-chave FR (exigência 0.5); experiência prévia em finanças valorizada, CV tem pouca; exige mestrado em curso ou convenção de estágio, risco. | S82: ='Dados completos'!AK146 -> Por confirmar | T82: ='Dados completos'!AP146 -> Parcial (agregador/título) | U82: ='Dados completos'!AO146 -> Direto (site/ATS da empresa) | V82: =HYPERLINK('Dados completos'!AN146,"Abrir") -> Abrir
A83: ='Dados completos'!A151 -> 148 | B83: ='Dados completos'!AL151 -> Reserva | C83: ='Dados completos'!Y151 -> 2.5 | D83: ='Dados completos'!AF151 -> 61.25 | E83: ='Dados completos'!AH151 -> 0.03405 | F83: ='Dados completos'!AI151 -> Média | G83: ='Dados completos'!B151 -> Citi | H83: ='Dados completos'!C151 -> Banking, Corporate Banking Placement Analyst 2027, Jan-Jun (Amesterdão) | I83: ='Dados completos'!E151 -> Banca de investimento | J83: ='Dados completos'!F151 -> Países Baixos | K83: ='Dados completos'!G151 -> Amesterdão | L83: ='Dados completos'!H151 -> Não indicado (provável presencial) | M83: ='Dados completos'!I151 -> Jan-Jun 2027 | N83: ='Dados completos'!O151 -> Não indicado | O83: ='Dados completos'!V151 -> Alta | P83: =IF('Dados completos'!R151="","n/d",IF('Dados completos'!R151='Dados completos'!S151,TEXT('Dados completos'!R151,"#,##0"),TEXT('Dados completos'!R151,"#,##0")&", "&TEXT('Dados completos'!S151,"#,##0"))) -> 1,800, 2,500 | Q83: ='Dados completos'!M151 -> Inglês (ver oferta) | R83: ='Dados completos'!AJ151 -> Língua-chave EN (exigência 0.5); experiência prévia em finanças valorizada, CV tem pouca; exige mestrado em curso ou convenção de estágio, risco. | S83: ='Dados completos'!AK151 -> Por confirmar | T83: ='Dados completos'!AP151 -> Parcial (agregador/título) | U83: ='Dados completos'!AO151 -> Direto (site/ATS da empresa) | V83: =HYPERLINK('Dados completos'!AN151,"Abrir") -> Abrir
A84: ='Dados completos'!A159 -> 156 | B84: ='Dados completos'!AL159 -> Reserva | C84: ='Dados completos'!Y159 -> 2.5 | D84: ='Dados completos'!AF159 -> 61 | E84: ='Dados completos'!AH159 -> 0.03396 | F84: ='Dados completos'!AI159 -> Média | G84: ='Dados completos'!B159 -> Eurazeo | H84: ='Dados completos'!C159 -> Internship, Investor Relations, Direct Transactions (Paris, S1 2027) | I84: ='Dados completos'!E159 -> VC / private equity | J84: ='Dados completos'!F159 -> França | K84: ='Dados completos'!G159 -> Paris | L84: ='Dados completos'!H159 -> Não indicado (provável presencial) | M84: ='Dados completos'!I159 -> Jan 2027 (S1) | N84: ='Dados completos'!O159 -> Não indicado | O84: ='Dados completos'!V159 -> Alta | P84: =IF('Dados completos'!R159="","n/d",IF('Dados completos'!R159='Dados completos'!S159,TEXT('Dados completos'!R159,"#,##0"),TEXT('Dados completos'!R159,"#,##0")&", "&TEXT('Dados completos'!S159,"#,##0"))) -> 1,500, 2,500 | Q84: ='Dados completos'!M159 -> Inglês (ver oferta) | R84: ='Dados completos'!AJ159 -> Língua-chave EN (exigência 1); experiência prévia em finanças valorizada, CV tem pouca; exige mestrado em curso ou convenção de estágio, risco. | S84: ='Dados completos'!AK159 -> Por confirmar | T84: ='Dados completos'!AP159 -> Parcial (agregador/título) | U84: ='Dados completos'!AO159 -> Anúncio em plataforma | V84: =HYPERLINK('Dados completos'!AN159,"Abrir") -> Abrir
A85: ='Dados completos'!A60 -> 57 | B85: ='Dados completos'!AL60 -> Candidatar (reach) | C85: ='Dados completos'!Y60 -> 3.1 | D85: ='Dados completos'!AF60 -> 28.5 | E85: ='Dados completos'!AH60 -> 0.02226 | F85: ='Dados completos'!AI60 -> Baixa | G85: ='Dados completos'!B60 -> Rothschild & Co | H85: ='Dados completos'!C60 -> Stage Private Equity Banque Privée, Janvier 2027 | I85: ='Dados completos'!E60 -> Banca de investimento / boutique | J85: ='Dados completos'!F60 -> França | K85: ='Dados completos'!G60 -> Paris | L85: ='Dados completos'!H60 -> Não indicado (provável presencial) | M85: ='Dados completos'!I60 -> Jan 2027 | N85: ='Dados completos'!O60 -> Não indicado | O85: ='Dados completos'!V60 -> Alta | P85: =IF('Dados completos'!R60="","n/d",IF('Dados completos'!R60='Dados completos'!S60,TEXT('Dados completos'!R60,"#,##0"),TEXT('Dados completos'!R60,"#,##0")&", "&TEXT('Dados completos'!S60,"#,##0"))) -> 1,500, 2,500 | Q85: ='Dados completos'!M60 -> Francês e inglês (ver oferta) | R85: ='Dados completos'!AJ60 -> Língua-chave FR (exigência 1); experiência prévia em finanças valorizada, CV tem pouca; exige mestrado em curso ou convenção de estágio, risco. | S85: ='Dados completos'!AK60 -> Por confirmar | T85: ='Dados completos'!AP60 -> Parcial (agregador/título) | U85: ='Dados completos'!AO60 -> Direto (site/ATS da empresa) | V85: =HYPERLINK('Dados completos'!AN60,"Abrir") -> Abrir
A86: ='Dados completos'!A61 -> 58 | B86: ='Dados completos'!AL61 -> Candidatar (reach) | C86: ='Dados completos'!Y61 -> 3.1 | D86: ='Dados completos'!AF61 -> 28.5 | E86: ='Dados completos'!AH61 -> 0.02226 | F86: ='Dados completos'!AI61 -> Baixa | G86: ='Dados completos'!B61 -> Rothschild & Co | H86: ='Dados completos'!C61 -> Stage Mandat Private Equity Banque Privée, Janvier 2027 | I86: ='Dados completos'!E61 -> Banca de investimento / boutique | J86: ='Dados completos'!F61 -> França | K86: ='Dados completos'!G61 -> Paris | L86: ='Dados completos'!H61 -> Não indicado (provável presencial) | M86: ='Dados completos'!I61 -> Jan 2027 | N86: ='Dados completos'!O61 -> Não indicado | O86: ='Dados completos'!V61 -> Alta | P86: =IF('Dados completos'!R61="","n/d",IF('Dados completos'!R61='Dados completos'!S61,TEXT('Dados completos'!R61,"#,##0"),TEXT('Dados completos'!R61,"#,##0")&", "&TEXT('Dados completos'!S61,"#,##0"))) -> 1,500, 2,500 | Q86: ='Dados completos'!M61 -> Francês e inglês (ver oferta) | R86: ='Dados completos'!AJ61 -> Língua-chave FR (exigência 1); experiência prévia em finanças valorizada, CV tem pouca; exige mestrado em curso ou convenção de estágio, risco. | S86: ='Dados completos'!AK61 -> Por confirmar | T86: ='Dados completos'!AP61 -> Parcial (agregador/título) | U86: ='Dados completos'!AO61 -> Direto (site/ATS da empresa) | V86: =HYPERLINK('Dados completos'!AN61,"Abrir") -> Abrir
A87: ='Dados completos'!A50 -> 47 | B87: ='Dados completos'!AL50 -> Reserva | C87: ='Dados completos'!Y50 -> 2.4 | D87: ='Dados completos'!AF50 -> 56.95 | E87: ='Dados completos'!AH50 -> 0.032502 | F87: ='Dados completos'!AI50 -> Média | G87: ='Dados completos'!B50 -> Ardian | H87: ='Dados completos'!C50 -> Fund Finance, Secondaries & Primaries Intern, February 2027 | I87: ='Dados completos'!E50 -> VC / private equity | J87: ='Dados completos'!F50 -> Suíça | K87: ='Dados completos'!G50 -> Zurique | L87: ='Dados completos'!H50 -> Não indicado (provável presencial) | M87: ='Dados completos'!I50 -> Fev 2027 | N87: ='Dados completos'!O50 -> Não indicado | O87: ='Dados completos'!V50 -> Alta | P87: =IF('Dados completos'!R50="","n/d",IF('Dados completos'!R50='Dados completos'!S50,TEXT('Dados completos'!R50,"#,##0"),TEXT('Dados completos'!R50,"#,##0")&", "&TEXT('Dados completos'!S50,"#,##0"))) -> 3,000, 4,500 | Q87: ='Dados completos'!M50 -> Inglês (ver oferta) | R87: ='Dados completos'!AJ50 -> Língua-chave DE (exigência 0.3); experiência prévia em finanças valorizada, CV tem pouca; exige mestrado em curso ou convenção de estágio, risco. | S87: ='Dados completos'!AK50 -> Por confirmar | T87: ='Dados completos'!AP50 -> Parcial (agregador/título) | U87: ='Dados completos'!AO50 -> Direto (site/ATS da empresa) | V87: =HYPERLINK('Dados completos'!AN50,"Abrir") -> Abrir
A88: ='Dados completos'!A95 -> 92 | B88: ='Dados completos'!AL95 -> Reserva | C88: ='Dados completos'!Y95 -> 2.8 | D88: ='Dados completos'!AF95 -> 34.35 | E88: ='Dados completos'!AH95 -> 0.024366 | F88: ='Dados completos'!AI95 -> Baixa | G88: ='Dados completos'!B95 -> Oddo BHF | H88: ='Dados completos'!C95 -> Stage Corporate Development / M&A, Janvier 2027 | I88: ='Dados completos'!E95 -> Banca de investimento / boutique | J88: ='Dados completos'!F95 -> França | K88: ='Dados completos'!G95 -> Paris | L88: ='Dados completos'!H95 -> Não indicado (provável presencial) | M88: ='Dados completos'!I95 -> Jan 2027 | N88: ='Dados completos'!O95 -> Não indicado | O88: ='Dados completos'!V95 -> Alta | P88: =IF('Dados completos'!R95="","n/d",IF('Dados completos'!R95='Dados completos'!S95,TEXT('Dados completos'!R95,"#,##0"),TEXT('Dados completos'!R95,"#,##0")&", "&TEXT('Dados completos'!S95,"#,##0"))) -> 1,500, 2,500 | Q88: ='Dados completos'!M95 -> Francês e inglês (ver oferta) | R88: ='Dados completos'!AJ95 -> Língua-chave FR (exigência 0.9); experiência prévia em finanças valorizada, CV tem pouca; exige mestrado em curso ou convenção de estágio, risco. | S88: ='Dados completos'!AK95 -> Por confirmar | T88: ='Dados completos'!AP95 -> Parcial (agregador/título) | U88: ='Dados completos'!AO95 -> Anúncio em plataforma | V88: =HYPERLINK('Dados completos'!AN95,"Abrir") -> Abrir
A89: ='Dados completos'!A103 -> 100 | B89: ='Dados completos'!AL103 -> Reserva | C89: ='Dados completos'!Y103 -> 2.4 | D89: ='Dados completos'!AF103 -> 53.6 | E89: ='Dados completos'!AH103 -> 0.031296 | F89: ='Dados completos'!AI103 -> Média | G89: ='Dados completos'!B103 -> Barclays | H89: ='Dados completos'!C103 -> International Corporate Banking Off-Cycle Internship 2027 (Frankfurt) | I89: ='Dados completos'!E103 -> Banca de investimento | J89: ='Dados completos'!F103 -> Alemanha | K89: ='Dados completos'!G103 -> Frankfurt | L89: ='Dados completos'!H103 -> Não indicado (provável presencial) | M89: ='Dados completos'!I103 -> 2027 (mês por confirmar) | N89: ='Dados completos'!O103 -> Não indicado | O89: ='Dados completos'!V103 -> Alta | P89: =IF('Dados completos'!R103="","n/d",IF('Dados completos'!R103='Dados completos'!S103,TEXT('Dados completos'!R103,"#,##0"),TEXT('Dados completos'!R103,"#,##0")&", "&TEXT('Dados completos'!S103,"#,##0"))) -> 1,800, 2,800 | Q89: ='Dados completos'!M103 -> Inglês (ver oferta) | R89: ='Dados completos'!AJ103 -> Língua-chave DE (exigência 0.4); experiência prévia em finanças valorizada, CV tem pouca; exige mestrado em curso ou convenção de estágio, risco. | S89: ='Dados completos'!AK103 -> Por confirmar | T89: ='Dados completos'!AP103 -> Parcial (agregador/título) | U89: ='Dados completos'!AO103 -> Direto (site/ATS da empresa) | V89: =HYPERLINK('Dados completos'!AN103,"Abrir") -> Abrir
A90: ='Dados completos'!A169 -> 166 | B90: ='Dados completos'!AL169 -> Reserva | C90: ='Dados completos'!Y169 -> 2.6 | D90: ='Dados completos'!AF169 -> 92.5 | E90: ='Dados completos'!AH169 -> 0.0453 | F90: ='Dados completos'!AI169 -> Média | G90: ='Dados completos'!B169 -> TAP Air Portugal | H90: ='Dados completos'!C169 -> First Flight, estágio profissional (vertente corporativa) | I90: ='Dados completos'!E169 -> Big corporate | J90: ='Dados completos'!F169 -> Portugal | K90: ='Dados completos'!G169 -> Lisboa | L90: ='Dados completos'!H169 -> Não indicado (provável presencial) | M90: ='Dados completos'!I169 -> Não indicado | N90: ='Dados completos'!O169 -> Não indicado | O90: ='Dados completos'!V169 -> Alta | P90: =IF('Dados completos'!R169="","n/d",IF('Dados completos'!R169='Dados completos'!S169,TEXT('Dados completos'!R169,"#,##0"),TEXT('Dados completos'!R169,"#,##0")&", "&TEXT('Dados completos'!S169,"#,##0"))) -> 1,100, 1,500 | Q90: ='Dados completos'!M169 -> Inglês (ver oferta) | R90: ='Dados completos'!AJ169 -> Língua-chave PT (exigência 0.3); não exige experiência prévia em finanças; aceita recém-licenciadas. | S90: ='Dados completos'!AK169 -> Por confirmar | T90: ='Dados completos'!AP169 -> Parcial (agregador/título) | U90: ='Dados completos'!AO169 -> Página de carreiras (procurar a vaga) | V90: =HYPERLINK('Dados completos'!AN169,"Abrir") -> Abrir
A91: ='Dados completos'!A148 -> 145 | B91: ='Dados completos'!AL148 -> Reserva | C91: ='Dados completos'!Y148 -> 2.2 | D91: ='Dados completos'!AF148 -> 63.95 | E91: ='Dados completos'!AH148 -> 0.035022 | F91: ='Dados completos'!AI148 -> Média | G91: ='Dados completos'!B148 -> MUFG | H91: ='Dados completos'!C148 -> 2027 6-Month Internship, Japanese Corporate Banking Division (Amesterdão) | I91: ='Dados completos'!E148 -> Banca de investimento | J91: ='Dados completos'!F148 -> Países Baixos | K91: ='Dados completos'!G148 -> Amesterdão | L91: ='Dados completos'!H148 -> Não indicado (provável presencial) | M91: ='Dados completos'!I148 -> 2027 (mês por confirmar) | N91: ='Dados completos'!O148 -> 46341 | O91: ='Dados completos'!V148 -> Alta | P91: =IF('Dados completos'!R148="","n/d",IF('Dados completos'!R148='Dados completos'!S148,TEXT('Dados completos'!R148,"#,##0"),TEXT('Dados completos'!R148,"#,##0")&", "&TEXT('Dados completos'!S148,"#,##0"))) -> 1,800, 2,500 | Q91: ='Dados completos'!M148 -> Inglês (ver oferta) | R91: ='Dados completos'!AJ148 -> Língua-chave EN (exigência 0.7); experiência prévia em finanças valorizada, CV tem pouca; exige mestrado em curso ou convenção de estágio, risco. | S91: ='Dados completos'!AK148 -> Aberta, prazo definido | T91: ='Dados completos'!AP148 -> Parcial (agregador/título) | U91: ='Dados completos'!AO148 -> Direto (site/ATS da empresa) | V91: =HYPERLINK('Dados completos'!AN148,"Abrir") -> Abrir
A92: ='Dados completos'!A139 -> 136 | B92: ='Dados completos'!AL139 -> Reserva | C92: ='Dados completos'!Y139 -> 2.3 | D92: ='Dados completos'!AF139 -> 47.3 | E92: ='Dados completos'!AH139 -> 0.029028 | F92: ='Dados completos'!AI139 -> Baixa | G92: ='Dados completos'!B139 -> Mediobanca | H92: ='Dados completos'!C139 -> Off-cycle Internship DCM & Financing (Milão) | I92: ='Dados completos'!E139 -> Banca de investimento / boutique | J92: ='Dados completos'!F139 -> Itália | K92: ='Dados completos'!G139 -> Milão | L92: ='Dados completos'!H139 -> Não indicado (provável presencial) | M92: ='Dados completos'!I139 -> Por confirmar | N92: ='Dados completos'!O139 -> Não indicado | O92: ='Dados completos'!V139 -> Alta | P92: =IF('Dados completos'!R139="","n/d",IF('Dados completos'!R139='Dados completos'!S139,TEXT('Dados completos'!R139,"#,##0"),TEXT('Dados completos'!R139,"#,##0")&", "&TEXT('Dados completos'!S139,"#,##0"))) -> 800, 1,500 | Q92: ='Dados completos'!M139 -> Italiano e inglês (ver oferta) | R92: ='Dados completos'!AJ139 -> Língua-chave IT (exigência 0.7); experiência prévia em finanças valorizada, CV tem pouca; exige mestrado em curso ou convenção de estágio, risco. | S92: ='Dados completos'!AK139 -> Por confirmar | T92: ='Dados completos'!AP139 -> Parcial (agregador/título) | U92: ='Dados completos'!AO139 -> Direto (site/ATS da empresa) | V92: =HYPERLINK('Dados completos'!AN139,"Abrir") -> Abrir
A93: ='Dados completos'!A147 -> 144 | B93: ='Dados completos'!AL147 -> Reserva | C93: ='Dados completos'!Y147 -> 2.3 | D93: ='Dados completos'!AF147 -> 44.9 | E93: ='Dados completos'!AH147 -> 0.028164 | F93: ='Dados completos'!AI147 -> Baixa | G93: ='Dados completos'!B147 -> MUFG | H93: ='Dados completos'!C147 -> 6-month Internship, Debt Capital Markets Bonds & Loans, January 2027 (Paris) | I93: ='Dados completos'!E147 -> Banca de investimento | J93: ='Dados completos'!F147 -> França | K93: ='Dados completos'!G147 -> Paris | L93: ='Dados completos'!H147 -> Não indicado (provável presencial) | M93: ='Dados completos'!I147 -> Jan 2027 | N93: ='Dados completos'!O147 -> Não indicado | O93: ='Dados completos'!V147 -> Alta | P93: =IF('Dados completos'!R147="","n/d",IF('Dados completos'!R147='Dados completos'!S147,TEXT('Dados completos'!R147,"#,##0"),TEXT('Dados completos'!R147,"#,##0")&", "&TEXT('Dados completos'!S147,"#,##0"))) -> 1,500, 2,500 | Q93: ='Dados completos'!M147 -> Francês e inglês (ver oferta) | R93: ='Dados completos'!AJ147 -> Língua-chave FR (exigência 0.6); experiência prévia em finanças valorizada, CV tem pouca; exige mestrado em curso ou convenção de estágio, risco. | S93: ='Dados completos'!AK147 -> Por confirmar | T93: ='Dados completos'!AP147 -> Parcial (agregador/título) | U93: ='Dados completos'!AO147 -> Direto (site/ATS da empresa) | V93: =HYPERLINK('Dados completos'!AN147,"Abrir") -> Abrir
A94: ='Dados completos'!A150 -> 147 | B94: ='Dados completos'!AL150 -> Reserva | C94: ='Dados completos'!Y150 -> 2.3 | D94: ='Dados completos'!AF150 -> 44.2 | E94: ='Dados completos'!AH150 -> 0.027912 | F94: ='Dados completos'!AI150 -> Baixa | G94: ='Dados completos'!B150 -> BCG | H94: ='Dados completos'!C150 -> Internship, Junior Financial Analyst, Janvier 2027 (Paris) | I94: ='Dados completos'!E150 -> Big 4 / consultoria | J94: ='Dados completos'!F150 -> França | K94: ='Dados completos'!G150 -> Paris | L94: ='Dados completos'!H150 -> Não indicado (provável presencial) | M94: ='Dados completos'!I150 -> Jan 2027 | N94: ='Dados completos'!O150 -> Não indicado | O94: ='Dados completos'!V150 -> Alta | P94: =IF('Dados completos'!R150="","n/d",IF('Dados completos'!R150='Dados completos'!S150,TEXT('Dados completos'!R150,"#,##0"),TEXT('Dados completos'!R150,"#,##0")&", "&TEXT('Dados completos'!S150,"#,##0"))) -> 1,500, 2,500 | Q94: ='Dados completos'!M150 -> Francês e inglês (ver oferta) | R94: ='Dados completos'!AJ150 -> Língua-chave FR (exigência 0.8); experiência prévia em finanças valorizada, CV tem pouca; exige mestrado em curso ou convenção de estágio, risco. | S94: ='Dados completos'!AK150 -> Por confirmar | T94: ='Dados completos'!AP150 -> Parcial (agregador/título) | U94: ='Dados completos'!AO150 -> Anúncio em plataforma | V94: =HYPERLINK('Dados completos'!AN150,"Abrir") -> Abrir
A95: ='Dados completos'!A166 -> 163 | B95: ='Dados completos'!AL166 -> Reserva | C95: ='Dados completos'!Y166 -> 2.3 | D95: ='Dados completos'!AF166 -> 82 | E95: ='Dados completos'!AH166 -> 0.04152 | F95: ='Dados completos'!AI166 -> Média | G95: ='Dados completos'!B166 -> Jerónimo Martins | H95: ='Dados completos'!C166 -> Programa de Trainees 2027 (recém-mestres de gestão, economia e STEM) | I95: ='Dados completos'!E166 -> Big corporate | J95: ='Dados completos'!F166 -> Portugal | K95: ='Dados completos'!G166 -> Lisboa | L95: ='Dados completos'!H166 -> Não indicado (provável presencial) | M95: ='Dados completos'!I166 -> Não indicado | N95: ='Dados completos'!O166 -> Não indicado | O95: ='Dados completos'!V166 -> Alta | P95: =IF('Dados completos'!R166="","n/d",IF('Dados completos'!R166='Dados completos'!S166,TEXT('Dados completos'!R166,"#,##0"),TEXT('Dados completos'!R166,"#,##0")&", "&TEXT('Dados completos'!S166,"#,##0"))) -> 1,200, 1,600 | Q95: ='Dados completos'!M166 -> Português e inglês fluentes | R95: ='Dados completos'!AJ166 -> Língua-chave PT (exigência 0.3); não exige experiência prévia em finanças. | S95: ='Dados completos'!AK166 -> Aberta (prazo não indicado) | T95: ='Dados completos'!AP166 -> Parcial (agregador/título) | U95: ='Dados completos'!AO166 -> Direto (site/ATS da empresa) | V95: =HYPERLINK('Dados completos'!AN166,"Abrir") -> Abrir
A96: ='Dados completos'!A51 -> 48 | B96: ='Dados completos'!AL51 -> Reserva | C96: ='Dados completos'!Y51 -> 2.1 | D96: ='Dados completos'!AF51 -> 56.95 | E96: ='Dados completos'!AH51 -> 0.032502 | F96: ='Dados completos'!AI51 -> Média | G96: ='Dados completos'!B51 -> Ardian | H96: ='Dados completos'!C51 -> Investor Relations Intern, January 2027 | I96: ='Dados completos'!E51 -> VC / private equity | J96: ='Dados completos'!F51 -> Suíça | K96: ='Dados completos'!G51 -> Zurique | L96: ='Dados completos'!H51 -> Não indicado (provável presencial) | M96: ='Dados completos'!I51 -> Jan 2027 | N96: ='Dados completos'!O51 -> Não indicado | O96: ='Dados completos'!V51 -> Alta | P96: =IF('Dados completos'!R51="","n/d",IF('Dados completos'!R51='Dados completos'!S51,TEXT('Dados completos'!R51,"#,##0"),TEXT('Dados completos'!R51,"#,##0")&", "&TEXT('Dados completos'!S51,"#,##0"))) -> 3,000, 4,500 | Q96: ='Dados completos'!M51 -> Inglês (ver oferta) | R96: ='Dados completos'!AJ51 -> Língua-chave DE (exigência 0.3); experiência prévia em finanças valorizada, CV tem pouca; exige mestrado em curso ou convenção de estágio, risco. | S96: ='Dados completos'!AK51 -> Por confirmar | T96: ='Dados completos'!AP51 -> Parcial (agregador/título) | U96: ='Dados completos'!AO51 -> Direto (site/ATS da empresa) | V96: =HYPERLINK('Dados completos'!AN51,"Abrir") -> Abrir
A97: ='Dados completos'!A125 -> 122 | B97: ='Dados completos'!AL125 -> Reserva | C97: ='Dados completos'!Y125 -> 2.5 | D97: ='Dados completos'!AF125 -> 31 | E97: ='Dados completos'!AH125 -> 0.02316 | F97: ='Dados completos'!AI125 -> Baixa | G97: ='Dados completos'!B125 -> Houlihan Lokey | H97: ='Dados completos'!C125 -> 6-month Internship, Sovereign Advisory, Financial Restructuring (Paris) | I97: ='Dados completos'!E125 -> Banca de investimento / boutique | J97: ='Dados completos'!F125 -> França | K97: ='Dados completos'!G125 -> Paris | L97: ='Dados completos'!H125 -> Não indicado (provável presencial) | M97: ='Dados completos'!I125 -> Jan 2027 | N97: ='Dados completos'!O125 -> Não indicado | O97: ='Dados completos'!V125 -> Alta | P97: =IF('Dados completos'!R125="","n/d",IF('Dados completos'!R125='Dados completos'!S125,TEXT('Dados completos'!R125,"#,##0"),TEXT('Dados completos'!R125,"#,##0")&", "&TEXT('Dados completos'!S125,"#,##0"))) -> 1,500, 2,500 | Q97: ='Dados completos'!M125 -> Francês e inglês (ver oferta) | R97: ='Dados completos'!AJ125 -> Língua-chave FR (exigência 1); experiência prévia em finanças valorizada, CV tem pouca; exige mestrado em curso ou convenção de estágio, risco. | S97: ='Dados completos'!AK125 -> Por confirmar | T97: ='Dados completos'!AP125 -> Parcial (agregador/título) | U97: ='Dados completos'!AO125 -> Direto (site/ATS da empresa) | V97: =HYPERLINK('Dados completos'!AN125,"Abrir") -> Abrir
A98: ='Dados completos'!A9 -> 6 | B98: ='Dados completos'!AL9 -> Reserva | C98: ='Dados completos'!Y9 -> 2.8 | D98: ='Dados completos'!AF9 -> 22.5 | E98: ='Dados completos'!AH9 -> 0.0201 | F98: ='Dados completos'!AI9 -> Baixa | G98: ='Dados completos'!B9 -> Houlihan Lokey | H98: ='Dados completos'!C9 -> 6-Month Off-Cycle Intern, Capital Solutions, Secondary Advisory | I98: ='Dados completos'!E9 -> Banca de investimento / boutique | J98: ='Dados completos'!F9 -> França | K98: ='Dados completos'!G9 -> Paris | L98: ='Dados completos'!H9 -> Não indicado (provável presencial) | M98: ='Dados completos'!I9 -> Jan 2027 | N98: ='Dados completos'!O9 -> Não indicado | O98: ='Dados completos'!V9 -> Alta | P98: =IF('Dados completos'!R9="","n/d",IF('Dados completos'!R9='Dados completos'!S9,TEXT('Dados completos'!R9,"#,##0"),TEXT('Dados completos'!R9,"#,##0")&", "&TEXT('Dados completos'!S9,"#,##0"))) -> 1,500, 2,500 | Q98: ='Dados completos'!M9 -> Francês e inglês (fluentes) | R98: ='Dados completos'!AJ9 -> Língua-chave FR (exigência 1); pede experiência prévia em IB/PE/consultoria, o CV mostrado não tem; exige mestrado em curso ou convenção de estágio, risco. | S98: ='Dados completos'!AK9 -> Aberta (prazo não indicado) | T98: ='Dados completos'!AP9 -> Verificada na página | U98: ='Dados completos'!AO9 -> Direto (site/ATS da empresa) | V98: =HYPERLINK('Dados completos'!AN9,"Abrir") -> Abrir
A99: ='Dados completos'!A47 -> 44 | B99: ='Dados completos'!AL47 -> Reserva | C99: ='Dados completos'!Y47 -> 2.2 | D99: ='Dados completos'!AF47 -> 34.5 | E99: ='Dados completos'!AH47 -> 0.02442 | F99: ='Dados completos'!AI47 -> Baixa | G99: ='Dados completos'!B47 -> Ardian | H99: ='Dados completos'!C47 -> Fund Finance, Secondaries & Primaries Stage, Janvier 2027 | I99: ='Dados completos'!E47 -> VC / private equity | J99: ='Dados completos'!F47 -> França | K99: ='Dados completos'!G47 -> Paris | L99: ='Dados completos'!H47 -> Não indicado (provável presencial) | M99: ='Dados completos'!I47 -> Jan 2027 | N99: ='Dados completos'!O47 -> Não indicado | O99: ='Dados completos'!V47 -> Alta | P99: =IF('Dados completos'!R47="","n/d",IF('Dados completos'!R47='Dados completos'!S47,TEXT('Dados completos'!R47,"#,##0"),TEXT('Dados completos'!R47,"#,##0")&", "&TEXT('Dados completos'!S47,"#,##0"))) -> 1,500, 2,500 | Q99: ='Dados completos'!M47 -> Francês e inglês (ver oferta) | R99: ='Dados completos'!AJ47 -> Língua-chave FR (exigência 1); experiência prévia em finanças valorizada, CV tem pouca; exige mestrado em curso ou convenção de estágio, risco. | S99: ='Dados completos'!AK47 -> Por confirmar | T99: ='Dados completos'!AP47 -> Parcial (agregador/título) | U99: ='Dados completos'!AO47 -> Direto (site/ATS da empresa) | V99: =HYPERLINK('Dados completos'!AN47,"Abrir") -> Abrir
A100: ='Dados completos'!A87 -> 84 | B100: ='Dados completos'!AL87 -> Reserva | C100: ='Dados completos'!Y87 -> 2.1 | D100: ='Dados completos'!AF87 -> 47.9 | E100: ='Dados completos'!AH87 -> 0.029244 | F100: ='Dados completos'!AI87 -> Baixa | G100: ='Dados completos'!B87 -> Tikehau Capital | H100: ='Dados completos'!C87 -> Internship, ESG Analyst for Private Equity (Paris) | I100: ='Dados completos'!E87 -> VC / private equity | J100: ='Dados completos'!F87 -> França | K100: ='Dados completos'!G87 -> Paris | L100: ='Dados completos'!H87 -> Não indicado (provável presencial) | M100: ='Dados completos'!I87 -> Jan 2027 | N100: ='Dados completos'!O87 -> Não indicado | O100: ='Dados completos'!V87 -> Alta | P100: =IF('Dados completos'!R87="","n/d",IF('Dados completos'!R87='Dados completos'!S87,TEXT('Dados completos'!R87,"#,##0"),TEXT('Dados completos'!R87,"#,##0")&", "&TEXT('Dados completos'!S87,"#,##0"))) -> 1,500, 2,500 | Q100: ='Dados completos'!M87 -> Francês e inglês (ver oferta) | R100: ='Dados completos'!AJ87 -> Língua-chave FR (exigência 0.6); experiência prévia em finanças valorizada, CV tem pouca; exige mestrado em curso ou convenção de estágio, risco. | S100: ='Dados completos'!AK87 -> Por confirmar | T100: ='Dados completos'!AP87 -> Parcial (agregador/título) | U100: ='Dados completos'!AO87 -> Direto (site/ATS da empresa) | V100: =HYPERLINK('Dados completos'!AN87,"Abrir") -> Abrir
A101: ='Dados completos'!A8 -> 5 | B101: ='Dados completos'!AL8 -> Candidatar (reach) | C101: ='Dados completos'!Y8 -> 3.4 | D101: ='Dados completos'!AF8 -> 77.5 | E101: ='Dados completos'!AH8 -> 0.0133 | F101: ='Dados completos'!AI8 -> Baixa | G101: ='Dados completos'!B8 -> Blackstone | H101: ='Dados completos'!C8 -> 2027 Private Equity Off-Cycle Internship | I101: ='Dados completos'!E8 -> VC / private equity | J101: ='Dados completos'!F8 -> Reino Unido | K101: ='Dados completos'!G8 -> Londres (conforme agregador) | L101: ='Dados completos'!H8 -> Não indicado (provável presencial) | M101: ='Dados completos'!I8 -> Jan ou Jul 2027 | N101: ='Dados completos'!O8 -> Rolling (sem prazo) | O101: ='Dados completos'!V8 -> Muito alta | P101: =IF('Dados completos'!R8="","n/d",IF('Dados completos'!R8='Dados completos'!S8,TEXT('Dados completos'!R8,"#,##0"),TEXT('Dados completos'!R8,"#,##0")&", "&TEXT('Dados completos'!S8,"#,##0"))) -> 2,800, 4,000 | Q101: ='Dados completos'!M8 -> Inglês | R101: ='Dados completos'!AJ8 -> Língua-chave EN (exigência 1); experiência prévia em finanças valorizada, CV tem pouca; aceita recém-licenciadas. | S101: ='Dados completos'!AK8 -> Aberta (rolling) | T101: ='Dados completos'!AP8 -> Verificada na página | U101: ='Dados completos'!AO8 -> Direto (site/ATS da empresa) | V101: =HYPERLINK('Dados completos'!AN8,"Abrir") -> Abrir
...

Sheet Dados completos
A1: Estágios 6 meses, entrada janeiro 2027, dados completos
A2: Azul: valores que introduzi ou estimei (editáveis). Preto: fórmulas. Todos os salários estimados são valores BRUTOS mensais (antes de impostos e descontos). São estimativas de mercado, exceto os do EIB e do IEFP, que são oficiais. Passa o rato por cima do cabeçalho das colunas principais para ver o que significam. Pesquisa de 17-10-2026.
A3: ID | B3: Empresa | C3: Role | D3: Tipo / área | E3: Tipo de empresa | F3: País | G3: Cidade | H3: Modalidade | I3: Início | J3: Duração | K3: Descrição (o que vais fazer) | L3: Requirements | M3: Idiomas | N3: Elegibilidade (estudante / recém-licenciada) | O3: Deadline | P3: Dias até deadline | Q3: Salário indicado na oferta (como indicado) | R3: Salário bruto est. mín (€/mês) | S3: Salário bruto est. máx (€/mês) | T3: Salário bruto est. médio (€/mês) | U3: Fonte / confiança do salário bruto | V3: Dificuldade de ser aceite | W3: Fit com PE/Finance (1-5) | X3: Facilidade (1-5) | Y3: Score (60% fit + 40% facilidade) | Z3: Língua-chave | AA3: Exigência da língua (0-1) | AB3: Idioma (0-1) | AC3: Experiência (0-1) | AD3: Elegibilidade (0-1) | AE3: Perfil / skills (0-1) | AF3: Match com o CV (0-100) | AG3: Prob. base (dificuldade) | AH3: Prob. estimada de aceitação | AI3: Chance | AJ3: Porquê (CV) | AK3: Estado | AL3: Veredicto | AM3: Notas / riscos | AN3: Link | AO3: Tipo de link | AP3: Qualidade da informação | AQ3: Ativa | AR3: P efetiva | AS3: Índice (P × interesse) | AT3: Chave de rank | AU3: Rank | AV3: Match (ativas) | AW3: P (ativas)
A4: 1 | B4: Rothschild & Co (Five Arrows) | C4: 2027 Five Arrows Private Equity Long Term Internship | D4: Private Equity | E4: Banca de investimento / boutique | F4: Reino Unido | G4: Londres | H4: Não indicado (provável presencial) | I4: Jan 2027 | J4: 6 meses | K4: Pesquisa setorial e avaliação de oportunidades, memos de comité de investimento, modelos financeiros, apoio à execução de deals e monitorização de participadas. | L4: 2:1 ou superior; estágio anterior em IB (M&A/LevFin/ECM), PE ou consultoria estratégica top; fundamentos de corporate finance e LBO; Excel/PowerPoint avançados. | M4: Inglês | N4: Não indica se exige ser estudante | O4: Não indicado | P4: =IF(ISNUMBER(O4),O4-TODAY(),"") | Q4: Não indicado | R4: 2800 | S4: 4000 | T4: =IF(R4="","",AVERAGE(R4,S4)) -> 3400 | U4: Estimativa (Londres, off-cycle PE/IB), valor bruto | V4: Muito alta | W4: 5 | X4: 1 | Y4: =ROUND(0.6*W4+0.4*X4,1) -> 3.4 | Z4: EN | AA4: 1 | AB4: =1-AA4*(1-INDEX('Perfil e pressupostos'!$C$14:$C$20,MATCH(Z4,'Perfil e pressupostos'!$A$14:$A$20,0))) -> 0.95 | AC4: 0.1 | AD4: 0.8 | AE4: 0.7 | AF4: =100*('Perfil e pressupostos'!$F$14*AB4+'Perfil e pressupostos'!$F$15*AC4+'Perfil e pressupostos'!$F$16*AD4+'Perfil e pressupostos'!$F$17*AE4)/'Perfil e pressupostos'!$F$18 -> 62 | AG4: =INDEX('Perfil e pressupostos'!$B$25:$B$28,MATCH(V4,'Perfil e pressupostos'!$A$25:$A$28,0)) -> 0.01 | AH4: =MIN('Perfil e pressupostos'!$F$29,AG4*('Perfil e pressupostos'!$F$25+'Perfil e pressupostos'!$F$26*AF4/100)*IF(AD4<='Perfil e pressupostos'!$F$28,'Perfil e pressupostos'!$F$27,1)) -> 0.01144 | AI4: =IF(AQ4=0,"—",IF(AH4>='Perfil e pressupostos'!$F$30,"Boa",IF(AH4>='Perfil e pressupostos'!$F$31,"Média","Baixa"))) -> Baixa | AJ4: Língua-chave EN (exigência 1); pede experiência prévia em IB/PE/consultoria, o CV mostrado não tem. | AK4: Aberta (prazo não indicado) | AL4: =IF(AK4="Prazo expirado","Prazo passado",IF(LEFT(AK4,11)="Monitorizar","Monitorizar",IF(Y4>=3.5,"Prioridade",IF(Y4>=3,"Candidatar (reach)","Reserva")))) -> Candidatar (reach) | AM4: Exige experiência prévia em IB/PE/consultoria; ideal para quem já tem 1 estágio relevante. | AN4: https://www.rothschildandco.com/en/careers/students-and-graduates/opportunities/2027-five-arrows-private-equity-long-term-internship/ | AO4: Direto (site/ATS da empresa) | AP4: Verificada na página | AQ4: =IF(OR(AK4="Prazo expirado",LEFT(AK4,11)="Monitorizar"),0,1) -> 1 | AR4: =IF(AQ4=0,0,AH4) -> 0.01144 | AS4: =AR4*W4/5 -> 0.01144 | AT4: =AS4+W4/1000000+(1000-ROW())/1000000000 -> 0.011445996 | AU4: =RANK(AT4,$AT$4:$AT$227) -> 101 | AV4: =IF(AQ4=0,"",AF4) -> 62 | AW4: =IF(AQ4=0,"",AH4) -> 0.01144
A5: 2 | B5: Rothschild & Co | C5: Global Advisory Spain, Madrid Long Term Internship | D5: IB / M&A | E5: Banca de investimento / boutique | F5: Espanha | G5: Madrid | H5: Não indicado (provável presencial) | I5: Jan ou Jul 2027 (a indicar na candidatura) | J5: 6 meses | K5: Pesquisa setorial e pitch books, modelos financeiros (DCF, comps, precedentes, LBO), coordenação de workstreams da transação. | L5: Liderança, análise, trabalho em equipa, atenção ao detalhe; experiência prévia de M&A considerada. | M5: Espanhol e inglês (nível alto) | N5: Não indica | O5: Não indicado | P5: =IF(ISNUMBER(O5),O5-TODAY(),"") | Q5: Não indicado | R5: 1000 | S5: 1800 | T5: =IF(R5="","",AVERAGE(R5,S5)) -> 1400 | U5: Estimativa (Madrid, estágio IB), valor bruto | V5: Alta | W5: 4 | X5: 2 | Y5: =ROUND(0.6*W5+0.4*X5,1) -> 3.2 | Z5: ES | AA5: 1 | AB5: =1-AA5*(1-INDEX('Perfil e pressupostos'!$C$14:$C$20,MATCH(Z5,'Perfil e pressupostos'!$A$14:$A$20,0))) -> 0.3 | AC5: 0.5 | AD5: 0.8 | AE5: 0.7 | AF5: =100*('Perfil e pressupostos'!$F$14*AB5+'Perfil e pressupostos'!$F$15*AC5+'Perfil e pressupostos'!$F$16*AD5+'Perfil e pressupostos'!$F$17*AE5)/'Perfil e pressupostos'!$F$18 -> 54.5 | AG5: =INDEX('Perfil e pressupostos'!$B$25:$B$28,MATCH(V5,'Perfil e pressupostos'!$A$25:$A$28,0)) -> 0.03 | AH5: =MIN('Perfil e pressupostos'!$F$29,AG5*('Perfil e pressupostos'!$F$25+'Perfil e pressupostos'!$F$26*AF5/100)*IF(AD5<='Perfil e pressupostos'!$F$28,'Perfil e pressupostos'!$F$27,1)) -> 0.03162 | AI5: =IF(AQ5=0,"—",IF(AH5>='Perfil e pressupostos'!$F$30,"Boa",IF(AH5>='Perfil e pressupostos'!$F$31,"Média","Baixa"))) -> Média | AJ5: Língua-chave ES (exigência 1); experiência prévia em finanças valorizada, CV tem pouca. | AK5: Aberta (prazo não indicado) | AL5: =IF(AK5="Prazo expirado","Prazo passado",IF(LEFT(AK5,11)="Monitorizar","Monitorizar",IF(Y5>=3.5,"Prioridade",IF(Y5>=3,"Candidatar (reach)","Reserva")))) -> Candidatar (reach) | AM5: Espanhol de nível alto é a principal barreira. Link do portal de candidatura menciona 'July-2026', confirmar. | AN5: https://www.rothschildandco.com/en/careers/students-and-graduates/opportunities/global-advisory-spain-madrid-long-term-internship-6-months-starting-january-or-july-2027/ | AO5: Direto (site/ATS da empresa) | AP5: Verificada na página | AQ5: =IF(OR(AK5="Prazo expirado",LEFT(AK5,11)="Monitorizar"),0,1) -> 1 | AR5: =IF(AQ5=0,0,AH5) -> 0.03162 | AS5: =AR5*W5/5 -> 0.025296 | AT5: =AS5+W5/1000000+(1000-ROW())/1000000000 -> 0.025300995 | AU5: =RANK(AT5,$AT$4:$AT$227) -> 58 | AV5: =IF(AQ5=0,"",AF5) -> 54.5 | AW5: =IF(AQ5=0,"",AH5) -> 0.03162
A6: 3 | B6: Rothschild & Co | C6: Stage, Transaction R&Co, Global Advisory (Paris) | D6: IB / M&A | E6: Banca de investimento / boutique | F6: França | G6: Paris | H6: Não indicado (provável presencial) | I6: Jan/Mar 2027 | J6: Não indicada | K6: Estágio em Global Advisory (M&A) em Paris. | L6: Detalhes não obtidos; normalmente exige estudante com convention de stage. | M6: Francês provável | N6: Provável estudante (convention de stage) | O6: Não indicado | P6: =IF(ISNUMBER(O6),O6-TODAY(),"") | Q6: Não indicado | R6: 1500 | S6: 2500 | T6: =IF(R6="","",AVERAGE(R6,S6)) -> 2000 | U6: Estimativa (Paris, stage IB), valor bruto | V6: Muito alta | W6: 4 | X6: 1 | Y6: =ROUND(0.6*W6+0.4*X6,1) -> 2.8 | Z6: FR | AA6: 0.6 | AB6: =1-AA6*(1-INDEX('Perfil e pressupostos'!$C$14:$C$20,MATCH(Z6,'Perfil e pressupostos'!$A$14:$A$20,0))) -> 0.43 | AC6: 0.4 | AD6: 0.3 | AE6: 0.7 | AF6: =100*('Perfil e pressupostos'!$F$14*AB6+'Perfil e pressupostos'!$F$15*AC6+'Perfil e pressupostos'!$F$16*AD6+'Perfil e pressupostos'!$F$17*AE6)/'Perfil e pressupostos'!$F$18 -> 42.9 | AG6: =INDEX('Perfil e pressupostos'!$B$25:$B$28,MATCH(V6,'Perfil e pressupostos'!$A$25:$A$28,0)) -> 0.01 | AH6: =MIN('Perfil e pressupostos'!$F$29,AG6*('Perfil e pressupostos'!$F$25+'Perfil e pressupostos'!$F$26*AF6/100)*IF(AD6<='Perfil e pressupostos'!$F$28,'Perfil e pressupostos'!$F$27,1)) -> 0.009148 | AI6: =IF(AQ6=0,"—",IF(AH6>='Perfil e pressupostos'!$F$30,"Boa",IF(AH6>='Perfil e pressupostos'!$F$31,"Média","Baixa"))) -> Baixa | AJ6: Língua-chave FR (exigência 0.6); experiência prévia em finanças valorizada, CV tem pouca; exige mestrado em curso ou convenção de estágio, risco. | AK6: Por confirmar | AL6: =IF(AK6="Prazo expirado","Prazo passado",IF(LEFT(AK6,11)="Monitorizar","Monitorizar",IF(Y6>=3.5,"Prioridade",IF(Y6>=3,"Candidatar (reach)","Reserva")))) -> Reserva | AM6: Estágios franceses exigem normalmente convenção da escola, difícil para recém-licenciada. | AN6: https://www.rothschildandco.com/en/careers/students-and-graduates/opportunities/ga-stage-transaction-r-co-global-advisory-janviermars-2027/ | AO6: Direto (site/ATS da empresa) | AP6: Parcial (agregador/título) | AQ6: =IF(OR(AK6="Prazo expirado",LEFT(AK6,11)="Monitorizar"),0,1) -> 1 | AR6: =IF(AQ6=0,0,AH6) -> 0.009148 | AS6: =AR6*W6/5 -> 0.0073184 | AT6: =AS6+W6/1000000+(1000-ROW())/1000000000 -> 0.007323394 | AU6: =RANK(AT6,$AT$4:$AT$227) -> 177 | AV6: =IF(AQ6=0,"",AF6) -> 42.9 | AW6: =IF(AQ6=0,"",AH6) -> 0.009148
A7: 4 | B7: Rothschild & Co (Five Arrows) | C7: Stage, Private Equity Investment Analyst, FAPI | D7: Private Equity | E7: Banca de investimento / boutique | F7: França | G7: Paris | H7: Não indicado (provável presencial) | I7: Mar 2027 (não é janeiro) | J7: Não indicada | K7: Analista de investimento em private equity (Five Arrows / FAPI). | L7: Detalhes não obtidos. | M7: Francês provável | N7: Provável estudante | O7: Não indicado | P7: =IF(ISNUMBER(O7),O7-TODAY(),"") | Q7: Não indicado | R7: 1500 | S7: 2500 | T7: =IF(R7="","",AVERAGE(R7,S7)) -> 2000 | U7: Estimativa (Paris, stage PE), valor bruto | V7: Muito alta | W7: 5 | X7: 1 | Y7: =ROUND(0.6*W7+0.4*X7,1) -> 3.4 | Z7: FR | AA7: 0.6 | AB7: =1-AA7*(1-INDEX('Perfil e pressupostos'!$C$14:$C$20,MATCH(Z7,'Perfil e pressupostos'!$A$14:$A$20,0))) -> 0.43 | AC7: 0.1 | AD7: 0.3 | AE7: 0.7 | AF7: =100*('Perfil e pressupostos'!$F$14*AB7+'Perfil e pressupostos'!$F$15*AC7+'Perfil e pressupostos'!$F$16*AD7+'Perfil e pressupostos'!$F$17*AE7)/'Perfil e pressupostos'!$F$18 -> 33.9 | AG7: =INDEX('Perfil e pressupostos'!$B$25:$B$28,MATCH(V7,'Perfil e pressupostos'!$A$25:$A$28,0)) -> 0.01 | AH7: =MIN('Perfil e pressupostos'!$F$29,AG7*('Perfil e pressupostos'!$F$25+'Perfil e pressupostos'!$F$26*AF7/100)*IF(AD7<='Perfil e pressupostos'!$F$28,'Perfil e pressupostos'!$F$27,1)) -> 0.008068 | AI7: =IF(AQ7=0,"—",IF(AH7>='Perfil e pressupostos'!$F$30,"Boa",IF(AH7>='Perfil e pressupostos'!$F$31,"Média","Baixa"))) -> Baixa | AJ7: Língua-chave FR (exigência 0.6); pede experiência prévia em IB/PE/consultoria, o CV mostrado não tem; exige mestrado em curso ou convenção de estágio, risco. | AK7: Por confirmar | AL7: =IF(AK7="Prazo expirado","Prazo passado",IF(LEFT(AK7,11)="Monitorizar","Monitorizar",IF(Y7>=3.5,"Prioridade",IF(Y7>=3,"Candidatar (reach)","Reserva")))) -> Candidatar (reach) | AM7: Início em março, só serve se aceitares atrasar 2 meses. | AN7: https://rothschildandco.tal.net/vx/lang-en-GB/mobile-0/appcentre-1/brand-4/candidate/so/pm/1/pl/2/opp/969-Stage-Private-Equity-Investment-Analyst-FAPI-Janvier-Mars-2027/en-GB | AO7: Direto (site/ATS da empresa) | AP7: Parcial (agregador/título) | AQ7: =IF(OR(AK7="Prazo expirado",LEFT(AK7,11)="Monitorizar"),0,1) -> 1 | AR7: =IF(AQ7=0,0,AH7) -> 0.008068 | AS7: =AR7*W7/5 -> 0.008068 | AT7: =AS7+W7/1000000+(1000-ROW())/1000000000 -> 0.008073993 | AU7: =RANK(AT7,$AT$4:$AT$227) -> 143 | AV7: =IF(AQ7=0,"",AF7) -> 33.9 | AW7: =IF(AQ7=0,"",AH7) -> 0.008068
A8: 5 | B8: Blackstone | C8: 2027 Private Equity Off-Cycle Internship | D8: Private Equity | E8: VC / private equity | F8: Reino Unido | G8: Londres (conforme agregador) | H8: Não indicado (provável presencial) | I8: Jan ou Jul 2027 | J8: ~6 meses | K8: Modelação e análise financeira, investigação de investimentos, apoio à execução, memorandos, contacto com gestão de participadas, reuniões de due diligence. | L8: Estudante de licenciatura/mestrado com graduação prevista em 2026 ou 2027; CV com mês/ano de graduação e média, em PDF; competências analíticas e quantitativas. | M8: Inglês | N8: Estudante com graduação 2026/2027, encaixa | O8: Rolling (sem prazo) | P8: =IF(ISNUMBER(O8),O8-TODAY(),"") | Q8: Não indicado | R8: 2800 | S8: 4000 | T8: =IF(R8="","",AVERAGE(R8,S8)) -> 3400 | U8: Estimativa (Londres, PE), valor bruto | V8: Muito alta | W8: 5 | X8: 1 | Y8: =ROUND(0.6*W8+0.4*X8,1) -> 3.4 | Z8: EN | AA8: 1 | AB8: =1-AA8*(1-INDEX('Perfil e pressupostos'!$C$14:$C$20,MATCH(Z8,'Perfil e pressupostos'!$A$14:$A$20,0))) -> 0.95 | AC8: 0.4 | AD8: 1 | AE8: 0.8 | AF8: =100*('Perfil e pressupostos'!$F$14*AB8+'Perfil e pressupostos'!$F$15*AC8+'Perfil e pressupostos'!$F$16*AD8+'Perfil e pressupostos'!$F$17*AE8)/'Perfil e pressupostos'!$F$18 -> 77.5 | AG8: =INDEX('Perfil e pressupostos'!$B$25:$B$28,MATCH(V8,'Perfil e pressupostos'!$A$25:$A$28,0)) -> 0.01 | AH8: =MIN('Perfil e pressupostos'!$F$29,AG8*('Perfil e pressupostos'!$F$25+'Perfil e pressupostos'!$F$26*AF8/100)*IF(AD8<='Perfil e pressupostos'!$F$28,'Perfil e pressupostos'!$F$27,1)) -> 0.0133 | AI8: =IF(AQ8=0,"—",IF(AH8>='Perfil e pressupostos'!$F$30,"Boa",IF(AH8>='Perfil e pressupostos'!$F$31,"Média","Baixa"))) -> Baixa | AJ8: Língua-chave EN (exigência 1); experiência prévia em finanças valorizada, CV tem pouca; aceita recém-licenciadas. | AK8: Aberta (rolling) | AL8: =IF(AK8="Prazo expirado","Prazo passado",IF(LEFT(AK8,11)="Monitorizar","Monitorizar",IF(Y8>=3.5,"Prioridade",IF(Y8>=3,"Candidatar (reach)","Reserva")))) -> Candidatar (reach) | AM8: Muito concorrida; candidatar cedo (rolling). Localização vem do agregador, confirmar. | AN8: https://blackstone.wd1.myworkdayjobs.com/Blackstone_Campus_Careers/job/London/XMLNAME-2027-Blackstone-Private-Equity-Off-Cycle-Internship_45106 | AO8: Direto (site/ATS da empresa) | AP8: Verificada na página | AQ8: =IF(OR(AK8="Prazo expirado",LEFT(AK8,11)="Monitorizar"),0,1) -> 1 | AR8: =IF(AQ8=0,0,AH8) -> 0.0133 | AS8: =AR8*W8/5 -> 0.0133 | AT8: =AS8+W8/1000000+(1000-ROW())/1000000000 -> 0.013305992 | AU8: =RANK(AT8,$AT$4:$AT$227) -> 97 | AV8: =IF(AQ8=0,"",AF8) -> 77.5 | AW8: =IF(AQ8=0,"",AH8) -> 0.0133
A9: 6 | B9: Houlihan Lokey | C9: 6-Month Off-Cycle Intern, Capital Solutions, Secondary Advisory | D9: Advisory (PE secundários) | E9: Banca de investimento / boutique | F9: França | G9: Paris | H9: Não indicado (provável presencial) | I9: Jan 2027 | J9: 6 meses | K9: Liquidez para PE: estruturar financiamento, preparar materiais de venda e diligência para transações LP-led/GP-led, gerir data rooms. | L9: Mestrado em finanças/gestão numa escola top (em curso); experiência em PE/IB; fundamentos de PE. | M9: Francês e inglês (fluentes) | N9: Exige mestrado em curso | O9: Não indicado | P9: =IF(ISNUMBER(O9),O9-TODAY(),"") | Q9: Não indicado | R9: 1500 | S9: 2500 | T9: =IF(R9="","",AVERAGE(R9,S9)) -> 2000 | U9: Estimativa (Paris, off-cycle IB), valor bruto | V9: Alta | W9: 4 | X9: 1 | Y9: =ROUND(0.6*W9+0.4*X9,1) -> 2.8 | Z9: FR | AA9: 1 | AB9: =1-AA9*(1-INDEX('Perfil e pressupostos'!$C$14:$C$20,MATCH(Z9,'Perfil e pressupostos'!$A$14:$A$20,0))) -> 0.05 | AC9: 0.1 | AD9: 0.3 | AE9: 0.7 | AF9: =100*('Perfil e pressupostos'!$F$14*AB9+'Perfil e pressupostos'!$F$15*AC9+'Perfil e pressupostos'!$F$16*AD9+'Perfil e pressupostos'!$F$17*AE9)/'Perfil e pressupostos'!$F$18 -> 22.5 | AG9: =INDEX('Perfil e pressupostos'!$B$25:$B$28,MATCH(V9,'Perfil e pressupostos'!$A$25:$A$28,0)) -> 0.03 | AH9: =MIN('Perfil e pressupostos'!$F$29,AG9*('Perfil e pressupostos'!$F$25+'Perfil e pressupostos'!$F$26*AF9/100)*IF(AD9<='Perfil e pressupostos'!$F$28,'Perfil e pressupostos'!$F$27,1)) -> 0.0201 | AI9: =IF(AQ9=0,"—",IF(AH9>='Perfil e pressupostos'!$F$30,"Boa",IF(AH9>='Perfil e pressupostos'!$F$31,"Média","Baixa"))) -> Baixa | AJ9: Língua-chave FR (exigência 1); pede experiência prévia em IB/PE/consultoria, o CV mostrado não tem; exige mestrado em curso ou convenção de estágio, risco. | AK9: Aberta (prazo não indicado) | AL9: =IF(AK9="Prazo expirado","Prazo passado",IF(LEFT(AK9,11)="Monitorizar","Monitorizar",IF(Y9>=3.5,"Prioridade",IF(Y9>=3,"Candidatar (reach)","Reserva")))) -> Reserva | AM9: Francês fluente e mestrado em curso são eliminatórios. | AN9: https://hl.wd1.myworkdayjobs.com/Campus/job/Paris-France/XMLNAME-6-Month-Off-Cycle-Intern---Capital-Solutions--Secondary-Advisory--January-2027-_R3617 | AO9: Direto (site/ATS da empresa) | AP9: Verificada na página | AQ9: =IF(OR(AK9="Prazo expirado",LEFT(AK9,11)="Monitorizar"),0,1) -> 1 | AR9: =IF(AQ9=0,0,AH9) -> 0.0201 | AS9: =AR9*W9/5 -> 0.01608 | AT9: =AS9+W9/1000000+(1000-ROW())/1000000000 -> 0.016084991 | AU9: =RANK(AT9,$AT$4:$AT$227) -> 94 | AV9: =IF(AQ9=0,"",AF9) -> 22.5 | AW9: =IF(AQ9=0,"",AH9) -> 0.0201
A10: 7 | B10: Houlihan Lokey | C10: Off-Cycle Internship, Primary Capital Advisory (PE Fundraising) | D10: Advisory (PE fundraising) | E10: Banca de investimento / boutique | F10: França | G10: Paris | H10: Não indicado (provável presencial) | I10: Jan 2027 | J10: Não indicada | K10: Posicionar gestores de ativos alternativos, preparar materiais de fundraising, gerir processos e due diligence de investidores. | L10: Experiência em fundraising PE / IB / transaction services; preferência por mestrado top; análise e multitasking. | M10: Francês e inglês fluentes; espanhol/alemão é vantagem | N10: Preferência por mestrado em curso | O10: Não indicado | P10: =IF(ISNUMBER(O10),O10-TODAY(),"") | Q10: Não indicado | R10: 1500 | S10: 2500 | T10: =IF(R10="","",AVERAGE(R10,S10)) -> 2000 | U10: Estimativa (Paris, off-cycle IB), valor bruto | V10: Muito alta | W10: 5 | X10: 1 | Y10: =ROUND(0.6*W10+0.4*X10,1) -> 3.4 | Z10: FR | AA10: 1 | AB10: =1-AA10*(1-INDEX('Perfil e pressupostos'!$C$14:$C$20,MATCH(Z10,'Perfil e pressupostos'!$A$14:$A$20,0))) -> 0.05 | AC10: 0.05 | AD10: 0.3 | AE10: 0.6 | AF10: =100*('Perfil e pressupostos'!$F$14*AB10+'Perfil e pressupostos'!$F$15*AC10+'Perfil e pressupostos'!$F$16*AD10+'Perfil e pressupostos'!$F$17*AE10)/'Perfil e pressupostos'!$F$18 -> 19.5 | AG10: =INDEX('Perfil e pressupostos'!$B$25:$B$28,MATCH(V10,'Perfil e pressupostos'!$A$25:$A$28,0)) -> 0.01 | AH10: =MIN('Perfil e pressupostos'!$F$29,AG10*('Perfil e pressupostos'!$F$25+'Perfil e pressupostos'!$F$26*AF10/100)*IF(AD10<='Perfil e pressupostos'!$F$28,'Perfil e pressupostos'!$F$27,1)) -> 0.00634 | AI10: =IF(AQ10=0,"—",IF(AH10>='Perfil e pressupostos'!$F$30,"Boa",IF(AH10>='Perfil e pressupostos'!$F$31,"Média","Baixa"))) -> Baixa | AJ10: Língua-chave FR (exigência 1); pede experiência prévia em IB/PE/consultoria, o CV mostrado não tem; exige mestrado em curso ou convenção de estágio, risco. | AK10: Aberta (prazo não indicado) | AL10: =IF(AK10="Prazo expirado","Prazo passado",IF(LEFT(AK10,11)="Monitorizar","Monitorizar",IF(Y10>=3.5,"Prioridade",IF(Y10>=3,"Candidatar (reach)","Reserva")))) -> Candidatar (reach) | AM10: Pede experiência em fundraising/IB. | AN10: https://hl.wd1.myworkdayjobs.com/Campus/job/Paris-France/Off-Cycle-Internship---Primary-Capital-Advisory--Private-Equity-Fundraising----January-2027_R3598 | AO10: Direto (site/ATS da empresa) | AP10: Verificada na página | AQ10: =IF(OR(AK10="Prazo expirado",LEFT(AK10,11)="Monitorizar"),0,1) -> 1 | AR10: =IF(AQ10=0,0,AH10) -> 0.00634 | AS10: =AR10*W10/5 -> 0.00634 | AT10: =AS10+W10/1000000+(1000-ROW())/1000000000 -> 0.00634599 | AU10: =RANK(AT10,$AT$4:$AT$227) -> 182 | AV10: =IF(AQ10=0,"",AF10) -> 19.5 | AW10: =IF(AQ10=0,"",AH10) -> 0.00634
A11: 8 | B11: Alantra | C11: Investment Banking Off-Cycle Internship Programme, January 2027 | D11: IB / M&A | E11: Banca de investimento / boutique | F11: Espanha | G11: Madrid | H11: Não indicado (provável presencial) | I11: Jan 2027 | J11: Não indicada | K11: Apoio a M&A e corporate finance: pesquisa, valuation (comps, precedentes, DCF), modelos, pitchbooks e memorandos, due diligence e execução. | L11: Estudante ou recém-licenciado (Business, Finance, Economics, Engenharia); estágio prévio em IB/PE/consultoria; contabilidade e valuation; Excel e PowerPoint avançados. | M11: Inglês e espanhol (bilingue/quase nativo) | N11: Aceita recém-licenciados, encaixa | O11: Não indicado | P11: =IF(ISNUMBER(O11),O11-TODAY(),"") | Q11: Não indicado | R11: 1000 | S11: 1800 | T11: =IF(R11="","",AVERAGE(R11,S11)) -> 1400 | U11: Estimativa (Madrid, IB), valor bruto | V11: Alta | W11: 4 | X11: 2 | Y11: =ROUND(0.6*W11+0.4*X11,1) -> 3.2 | Z11: ES | AA11: 1 | AB11: =1-AA11*(1-INDEX('Perfil e pressupostos'!$C$14:$C$20,MATCH(Z11,'Perfil e pressupostos'!$A$14:$A$20,0))) -> 0.3 | AC11: 0.2 | AD11: 1 | AE11: 0.8 | AF11: =100*('Perfil e pressupostos'!$F$14*AB11+'Perfil e pressupostos'!$F$15*AC11+'Perfil e pressupostos'!$F$16*AD11+'Perfil e pressupostos'!$F$17*AE11)/'Perfil e pressupostos'!$F$18 -> 52 | AG11: =INDEX('Perfil e pressupostos'!$B$25:$B$28,MATCH(V11,'Perfil e pressupostos'!$A$25:$A$28,0)) -> 0.03 | AH11: =MIN('Perfil e pressupostos'!$F$29,AG11*('Perfil e pressupostos'!$F$25+'Perfil e pressupostos'!$F$26*AF11/100)*IF(AD11<='Perfil e pressupostos'!$F$28,'Perfil e pressupostos'!$F$27,1)) -> 0.03072 | AI11: =IF(AQ11=0,"—",IF(AH11>='Perfil e pressupostos'!$F$30,"Boa",IF(AH11>='Perfil e pressupostos'!$F$31,"Média","Baixa"))) -> Média | AJ11: Língua-chave ES (exigência 1); pede experiência prévia em IB/PE/consultoria, o CV mostrado não tem; aceita recém-licenciadas. | AK11: Aberta (prazo não indicado) | AL11: =IF(AK11="Prazo expirado","Prazo passado",IF(LEFT(AK11,11)="Monitorizar","Monitorizar",IF(Y11>=3.5,"Prioridade",IF(Y11>=3,"Candidatar (reach)","Reserva")))) -> Candidatar (reach) | AM11: Aceita recém-licenciados (vantagem). Espanhol quase nativo é a barreira. | AN11: https://alantra.wd3.myworkdayjobs.com/Alantra/job/Spain---Madrid/Investment-Banking-Off-Cycle-Internship-Programme---January-2027_JR498 | AO11: Direto (site/ATS da empresa) | AP11: Verificada na página | AQ11: =IF(OR(AK11="Prazo expirado",LEFT(AK11,11)="Monitorizar"),0,1) -> 1 | AR11: =IF(AQ11=0,0,AH11) -> 0.03072 | AS11: =AR11*W11/5 -> 0.024576 | AT11: =AS11+W11/1000000+(1000-ROW())/1000000000 -> 0.024580989 | AU11: =RANK(AT11,$AT$4:$AT$227) -> 62 | AV11: =IF(AQ11=0,"",AF11) -> 52 | AW11: =IF(AQ11=0,"",AH11) -> 0.03072
A12: 9 | B12: IK Partners | C12: Capital Markets Off-Cycle Analyst 2027 | D12: Private Equity | E12: VC / private equity | F12: Reino Unido | G12: Londres | H12: Presencial | I12: Jan 2027 | J12: 5 meses | K12: Análise financeira e modelação, due diligence e estruturação de financiamento de LBOs, monitorização de participadas, pesquisa de mercados de dívida. | L12: Finanças/economia/engenharia; estágio prévio (~6 meses) em PE, VC, IB, M&A ou consultoria; capital markets/leveraged finance é plus. | M12: Inglês | N12: Não indica | O12: Não indicado | P12: =IF(ISNUMBER(O12),O12-TODAY(),"") | Q12: Não indicado | R12: 2800 | S12: 4000 | T12: =IF(R12="","",AVERAGE(R12,S12)) -> 3400 | U12: Estimativa (Londres, PE), valor bruto | V12: Muito alta | W12: 5 | X12: 1 | Y12: =ROUND(0.6*W12+0.4*X12,1) -> 3.4 | Z12: EN | AA12: 1 | AB12: =1-AA12*(1-INDEX('Perfil e pressupostos'!$C$14:$C$20,MATCH(Z12,'Perfil e pressupostos'!$A$14:$A$20,0))) -> 0.95 | AC12: 0.05 | AD12: 0.8 | AE12: 0.7 | AF12: =100*('Perfil e pressupostos'!$F$14*AB12+'Perfil e pressupostos'!$F$15*AC12+'Perfil e pressupostos'!$F$16*AD12+'Perfil e pressupostos'!$F$17*AE12)/'Perfil e pressupostos'!$F$18 -> 60.5 | AG12: =INDEX('Perfil e pressupostos'!$B$25:$B$28,MATCH(V12,'Perfil e pressupostos'!$A$25:$A$28,0)) -> 0.01 | AH12: =MIN('Perfil e pressupostos'!$F$29,AG12*('Perfil e pressupostos'!$F$25+'Perfil e pressupostos'!$F$26*AF12/100)*IF(AD12<='Perfil e pressupostos'!$F$28,'Perfil e pressupostos'!$F$27,1)) -> 0.01126 | AI12: =IF(AQ12=0,"—",IF(AH12>='Perfil e pressupostos'!$F$30,"Boa",IF(AH12>='Perfil e pressupostos'!$F$31,"Média","Baixa"))) -> Baixa | AJ12: Língua-chave EN (exigência 1); pede experiência prévia em IB/PE/consultoria, o CV mostrado não tem. | AK12: Aberta (prazo não indicado) | AL12: =IF(AK12="Prazo expirado","Prazo passado",IF(LEFT(AK12,11)="Monitorizar","Monitorizar",IF(Y12>=3.5,"Prioridade",IF(Y12>=3,"Candidatar (reach)","Reserva")))) -> Candidatar (reach) | AM12: Duração 5 meses (não 6). Pede ~6 meses de experiência prévia. | AN12: https://ikpartners.recruitee.com/o/capital-markets-off-cycle-analyst-2027 | AO12: Direto (site/ATS da empresa) | AP12: Verificada na página | AQ12: =IF(OR(AK12="Prazo expirado",LEFT(AK12,11)="Monitorizar"),0,1) -> 1 | AR12: =IF(AQ12=0,0,AH12) -> 0.01126 | AS12: =AR12*W12/5 -> 0.01126 | AT12: =AS12+W12/1000000+(1000-ROW())/1000000000 -> 0.011265988 | AU12: =RANK(AT12,$AT$4:$AT$227) -> 102 | AV12: =IF(AQ12=0,"",AF12) -> 60.5 | AW12: =IF(AQ12=0,"",AH12) -> 0.01126
A13: 10 | B13: BlackRock | C13: 2027 Off-cycle Internship Program, EMEA (Paris, Jan-Jun 2027) | D13: Asset Management | E13: Gestão de ativos | F13: França | G13: Paris | H13: Não indicado (provável presencial) | I13: Jan-Jun 2027 | J13: 6 meses | K13: Estágio em equipa específica (ex.: Private Debt, Investment Research, Analytics & Modeling) com objetivos e projetos próprios. | L13: Penúltimo ano de curso; graduação entre jul 2027 e 2028; avaliação pré-entrevista em 5 dias; só 1 candidatura por programa/ano. | M13: Inglês (francês provável) | N13: Exige penúltimo ano, provavelmente NÃO elegível | O13: 46295 | P13: =IF(ISNUMBER(O13),O13-TODAY(),"") -> -17 | Q13: Ver doc 'EMEA 2027 Internship Salary Ranges' (não acessível) | R13: 1800 | S13: 2800 | T13: =IF(R13="","",AVERAGE(R13,S13)) -> 2300 | U13: Estimativa (Paris, asset mgmt), valor bruto | V13: Muito alta | W13: 3 | X13: 1 | Y13: =ROUND(0.6*W13+0.4*X13,1) -> 2.2 | Z13: FR | AA13: 0.4 | AB13: =1-AA13*(1-INDEX('Perfil e pressupostos'!$C$14:$C$20,MATCH(Z13,'Perfil e pressupostos'!$A$14:$A$20,0))) -> 0.62 | AC13: 0.5 | AD13: 0 | AE13: 0.8 | AF13: =100*('Perfil e pressupostos'!$F$14*AB13+'Perfil e pressupostos'!$F$15*AC13+'Perfil e pressupostos'!$F$16*AD13+'Perfil e pressupostos'!$F$17*AE13)/'Perfil e pressupostos'!$F$18 -> 45.6 | AG13: =INDEX('Perfil e pressupostos'!$B$25:$B$28,MATCH(V13,'Perfil e pressupostos'!$A$25:$A$28,0)) -> 0.01 | AH13: =MIN('Perfil e pressupostos'!$F$29,AG13*('Perfil e pressupostos'!$F$25+'Perfil e pressupostos'!$F$26*AF13/100)*IF(AD13<='Perfil e pressupostos'!$F$28,'Perfil e pressupostos'!$F$27,1)) -> 0.0009472 | AI13: =IF(AQ13=0,"—",IF(AH13>='Perfil e pressupostos'!$F$30,"Boa",IF(AH13>='Perfil e pressupostos'!$F$31,"Média","Baixa"))) -> — | AJ13: Língua-chave FR (exigência 0.4); experiência prévia em finanças valorizada, CV tem pouca; provavelmente inelegível (penúltimo ano / prazo). | AK13: Prazo expirado | AL13: =IF(AK13="Prazo expirado","Prazo passado",IF(LEFT(AK13,11)="Monitorizar","Monitorizar",IF(Y13>=3.5,"Prioridade",IF(Y13>=3,"Candidatar (reach)","Reserva")))) -> Prazo passado | AM13: Prazo de 30/09/2026 já passou e exige penúltimo ano. | AN13: https://careers.blackrock.com/job/london/2027-off-cycle-internship-program-emea/45831/97104654800 | AO13: Página de carreiras (procurar a vaga) | AP13: Verificada na página | AQ13: =IF(OR(AK13="Prazo expirado",LEFT(AK13,11)="Monitorizar"),0,1) -> 0 | AR13: =IF(AQ13=0,0,AH13) -> 0 | AS13: =AR13*W13/5 -> 0 | AT13: =AS13+W13/1000000+(1000-ROW())/1000000000 -> 3.987e-06 | AU13: =RANK(AT13,$AT$4:$AT$227) -> 208 | AV13: =IF(AQ13=0,"",AF13) | AW13: =IF(AQ13=0,"",AH13)
A14: 11 | B14: BlackRock | C14: 2027 Off-cycle Internship Program, EMEA (Frankfurt/Munique, a partir de mar 2027) | D14: Asset Management | E14: Gestão de ativos | F14: Alemanha | G14: Frankfurt / Munique | H14: Não indicado (provável presencial) | I14: Mar-Set 2027 (Munique), não é janeiro | J14: ~6-7 meses | K14: Estágio em equipa específica (Private Debt em Munique, etc.). | L14: Penúltimo ano de curso; graduação jul 2027-2028; avaliação pré-entrevista. | M14: Inglês (alemão provável) | N14: Exige penúltimo ano, provavelmente NÃO elegível | O14: 46339 | P14: =IF(ISNUMBER(O14),O14-TODAY(),"") -> 27 | Q14: Ver doc 'EMEA 2027 Internship Salary Ranges' (não acessível) | R14: 1800 | S14: 2500 | T14: =IF(R14="","",AVERAGE(R14,S14)) -> 2150 | U14: Estimativa (Alemanha, asset mgmt), valor bruto | V14: Muito alta | W14: 3 | X14: 1 | Y14: =ROUND(0.6*W14+0.4*X14,1) -> 2.2 | Z14: DE | AA14: 0.3 | AB14: =1-AA14*(1-INDEX('Perfil e pressupostos'!$C$14:$C$20,MATCH(Z14,'Perfil e pressupostos'!$A$14:$A$20,0))) -> 0.715 | AC14: 0.5 | AD14: 0.1 | AE14: 0.8 | AF14: =100*('Perfil e pressupostos'!$F$14*AB14+'Perfil e pressupostos'!$F$15*AC14+'Perfil e pressupostos'!$F$16*AD14+'Perfil e pressupostos'!$F$17*AE14)/'Perfil e pressupostos'!$F$18 -> 50.95 | AG14: =INDEX('Perfil e pressupostos'!$B$25:$B$28,MATCH(V14,'Perfil e pressupostos'!$A$25:$A$28,0)) -> 0.01 | AH14: =MIN('Perfil e pressupostos'!$F$29,AG14*('Perfil e pressupostos'!$F$25+'Perfil e pressupostos'!$F$26*AF14/100)*IF(AD14<='Perfil e pressupostos'!$F$28,'Perfil e pressupostos'!$F$27,1)) -> 0.0010114 | AI14: =IF(AQ14=0,"—",IF(AH14>='Perfil e pressupostos'!$F$30,"Boa",IF(AH14>='Perfil e pressupostos'!$F$31,"Média","Baixa"))) -> Baixa | AJ14: Língua-chave DE (exigência 0.3); experiência prévia em finanças valorizada, CV tem pouca; provavelmente inelegível (penúltimo ano / prazo). | AK14: Aberta, prazo definido | AL14: =IF(AK14="Prazo expirado","Prazo passado",IF(LEFT(AK14,11)="Monitorizar","Monitorizar",IF(Y14>=3.5,"Prioridade",IF(Y14>=3,"Candidatar (reach)","Reserva")))) -> Reserva | AM14: Elegibilidade (penúltimo ano) provavelmente exclui-te; início em março. | AN14: https://careers.blackrock.com/job/london/2027-off-cycle-internship-program-emea/45831/97104654800 | AO14: Página de carreiras (procurar a vaga) | AP14: Verificada na página | AQ14: =IF(OR(AK14="Prazo expirado",LEFT(AK14,11)="Monitorizar"),0,1) -> 1 | AR14: =IF(AQ14=0,0,AH14) -> 0.0010114 | AS14: =AR14*W14/5 -> 0.00060684 | AT14: =AS14+W14/1000000+(1000-ROW())/1000000000 -> 0.000610826 | AU14: =RANK(AT14,$AT$4:$AT$227) -> 200 | AV14: =IF(AQ14=0,"",AF14) -> 50.95 | AW14: =IF(AQ14=0,"",AH14) -> 0.0010114
A15: 12 | B15: BNP Paribas | C15: Investment Banking Trainee, M&A Advisory (Lisboa) | D15: IB / M&A | E15: Banca de investimento | F15: Portugal | G15: Lisboa | H15: Híbrido | I15: Não indicado (confirmar) | J15: Não indicada | K15: Identificar oportunidades, apoio a pitches e teasers, análise setorial e financeira, modelos de valuation (múltiplos, DCF), bases de dados de deals, credenciais. | L15: Formação em finanças/gestão/economia; inglês fluente; modelação financeira; análise quantitativa; candidatura obrigatoriamente em inglês. | M15: Inglês fluente (português) | N15: Não indica | O15: Não indicado | P15: =IF(ISNUMBER(O15),O15-TODAY(),"") | Q15: Não indicado | R15: 1000 | S15: 1400 | T15: =IF(R15="","",AVERAGE(R15,S15)) -> 1200 | U15: Estimativa (Lisboa; ref. bolsa IEFP 1.181,69 €), valor bruto | V15: Média-alta | W15: 4 | X15: 4 | Y15: =ROUND(0.6*W15+0.4*X15,1) -> 4 | Z15: EN | AA15: 1 | AB15: =1-AA15*(1-INDEX('Perfil e pressupostos'!$C$14:$C$20,MATCH(Z15,'Perfil e pressupostos'!$A$14:$A$20,0))) -> 0.95 | AC15: 0.7 | AD15: 1 | AE15: 0.9 | AF15: =100*('Perfil e pressupostos'!$F$14*AB15+'Perfil e pressupostos'!$F$15*AC15+'Perfil e pressupostos'!$F$16*AD15+'Perfil e pressupostos'!$F$17*AE15)/'Perfil e pressupostos'!$F$18 -> 88 | AG15: =INDEX('Perfil e pressupostos'!$B$25:$B$28,MATCH(V15,'Perfil e pressupostos'!$A$25:$A$28,0)) -> 0.08 | AH15: =MIN('Perfil e pressupostos'!$F$29,AG15*('Perfil e pressupostos'!$F$25+'Perfil e pressupostos'!$F$26*AF15/100)*IF(AD15<='Perfil e pressupostos'!$F$28,'Perfil e pressupostos'!$F$27,1)) -> 0.11648 | AI15: =IF(AQ15=0,"—",IF(AH15>='Perfil e pressupostos'!$F$30,"Boa",IF(AH15>='Perfil e pressupostos'!$F$31,"Média","Baixa"))) -> Boa | AJ15: Língua-chave EN (exigência 1); não exige experiência prévia em finanças; aceita recém-licenciadas. | AK15: Aberta (prazo não indicado) | AL15: =IF(AK15="Prazo expirado","Prazo passado",IF(LEFT(AK15,11)="Monitorizar","Monitorizar",IF(Y15>=3.5,"Prioridade",IF(Y15>=3,"Candidatar (reach)","Reserva")))) -> Prioridade | AM15: Melhor opção em Portugal. Página atualizada a 24-07-2026, confirmar data de início e se ainda está ativa (job ID 91168). | AN15: https://www.bnpparibas.pt/en/jobs/investment-banking-trainee-ma-advisory/ | AO15: Direto (site/ATS da empresa) | AP15: Verificada na página | AQ15: =IF(OR(AK15="Prazo expirado",LEFT(AK15,11)="Monitorizar"),0,1) -> 1 | AR15: =IF(AQ15=0,0,AH15) -> 0.11648 | AS15: =AR15*W15/5 -> 0.093184 | AT15: =AS15+W15/1000000+(1000-ROW())/1000000000 -> 0.093188985 | AU15: =RANK(AT15,$AT$4:$AT$227) -> 7 | AV15: =IF(AQ15=0,"",AF15) -> 88 | AW15: =IF(AQ15=0,"",AH15) -> 0.11648
A16: 13 | B16: EY-Parthenon | C16: Business Analyst, EY-Parthenon M&A (Real Estate) (Lisboa) | D16: Big 4 / Transações | E16: Big 4 / consultoria | F16: Portugal | G16: Lisboa | H16: Híbrido | I16: Imediato | J16: Contrato (não é estágio) | K16: Analista júnior em M&A/transações imobiliárias. | L16: Júnior (0-2 anos de experiência). | M16: Inglês e português | N16: Recém-licenciada elegível | O16: Não indicado (publicada 11-08-2026) | P16: =IF(ISNUMBER(O16),O16-TODAY(),"") | Q16: 'Competitive' | R16: 1300 | S16: 1800 | T16: =IF(R16="","",AVERAGE(R16,S16)) -> 1550 | U16: Estimativa (Big 4 júnior Lisboa), valor bruto | V16: Média-alta | W16: 4 | X16: 3.5 | Y16: =ROUND(0.6*W16+0.4*X16,1) -> 3.8 | Z16: EN | AA16: 1 | AB16: =1-AA16*(1-INDEX('Perfil e pressupostos'!$C$14:$C$20,MATCH(Z16,'Perfil e pressupostos'!$A$14:$A$20,0))) -> 0.95 | AC16: 0.8 | AD16: 1 | AE16: 0.8 | AF16: =100*('Perfil e pressupostos'!$F$14*AB16+'Perfil e pressupostos'!$F$15*AC16+'Perfil e pressupostos'!$F$16*AD16+'Perfil e pressupostos'!$F$17*AE16)/'Perfil e pressupostos'!$F$18 -> 89.5 | AG16: =INDEX('Perfil e pressupostos'!$B$25:$B$28,MATCH(V16,'Perfil e pressupostos'!$A$25:$A$28,0)) -> 0.08 | AH16: =MIN('Perfil e pressupostos'!$F$29,AG16*('Perfil e pressupostos'!$F$25+'Perfil e pressupostos'!$F$26*AF16/100)*IF(AD16<='Perfil e pressupostos'!$F$28,'Perfil e pressupostos'!$F$27,1)) -> 0.11792 | AI16: =IF(AQ16=0,"—",IF(AH16>='Perfil e pressupostos'!$F$30,"Boa",IF(AH16>='Perfil e pressupostos'!$F$31,"Média","Baixa"))) -> Boa | AJ16: Língua-chave EN (exigência 1); não exige experiência prévia em finanças; aceita recém-licenciadas. | AK16: Aberta (prazo não indicado) | AL16: =IF(AK16="Prazo expirado","Prazo passado",IF(LEFT(AK16,11)="Monitorizar","Monitorizar",IF(Y16>=3.5,"Prioridade",IF(Y16>=3,"Candidatar (reach)","Reserva")))) -> Prioridade | AM16: Não é estágio, mas é a porta de entrada em M&A em Lisboa; bom plano B. | AN16: https://www.ey.com/pt_pt/careers | AO16: Página de carreiras (procurar a vaga) | AP16: Parcial (agregador/título) | AQ16: =IF(OR(AK16="Prazo expirado",LEFT(AK16,11)="Monitorizar"),0,1) -> 1 | AR16: =IF(AQ16=0,0,AH16) -> 0.11792 | AS16: =AR16*W16/5 -> 0.094336 | AT16: =AS16+W16/1000000+(1000-ROW())/1000000000 -> 0.094340984 | AU16: =RANK(AT16,$AT$4:$AT$227) -> 6 | AV16: =IF(AQ16=0,"",AF16) -> 89.5 | AW16: =IF(AQ16=0,"",AH16) -> 0.11792
A17: 14 | B17: Alantra | C17: Summer Intern, Investment Banking, FIG (Lisboa) | D17: IB / M&A | E17: Banca de investimento / boutique | F17: Portugal | G17: Lisboa | H17: Não indicado (provável presencial) | I17: Jun/Jul (verão) | J17: Não indicada | K17: Pitches, apoio a M&A buy-side/sell-side, data rooms, apoio a pricing/análise de crédito. | L17: Top da turma em finanças; Word/Excel/PowerPoint; direito a trabalhar na UE; para recém-licenciados; pode converter em Analyst. | M17: Português e inglês fluentes; espanhol/italiano desejável | N17: Recém-licenciados, encaixa | O17: Não aberta (anúncio de 2023) | P17: =IF(ISNUMBER(O17),O17-TODAY(),"") | Q17: 'Remunerado' | R17: 1000 | S17: 1400 | T17: =IF(R17="","",AVERAGE(R17,S17)) -> 1200 | U17: Estimativa (Lisboa), valor bruto | V17: Média-alta | W17: 4 | X17: 3 | Y17: =ROUND(0.6*W17+0.4*X17,1) -> 3.6 | Z17: EN | AA17: 1 | AB17: =1-AA17*(1-INDEX('Perfil e pressupostos'!$C$14:$C$20,MATCH(Z17,'Perfil e pressupostos'!$A$14:$A$20,0))) -> 0.95 | AC17: 0.7 | AD17: 1 | AE17: 0.8 | AF17: =100*('Perfil e pressupostos'!$F$14*AB17+'Perfil e pressupostos'!$F$15*AC17+'Perfil e pressupostos'!$F$16*AD17+'Perfil e pressupostos'!$F$17*AE17)/'Perfil e pressupostos'!$F$18 -> 86.5 | AG17: =INDEX('Perfil e pressupostos'!$B$25:$B$28,MATCH(V17,'Perfil e pressupostos'!$A$25:$A$28,0)) -> 0.08 | AH17: =MIN('Perfil e pressupostos'!$F$29,AG17*('Perfil e pressupostos'!$F$25+'Perfil e pressupostos'!$F$26*AF17/100)*IF(AD17<='Perfil e pressupostos'!$F$28,'Perfil e pressupostos'!$F$27,1)) -> 0.11504 | AI17: =IF(AQ17=0,"—",IF(AH17>='Perfil e pressupostos'!$F$30,"Boa",IF(AH17>='Perfil e pressupostos'!$F$31,"Média","Baixa"))) -> — | AJ17: Língua-chave EN (exigência 1); não exige experiência prévia em finanças; aceita recém-licenciadas. | AK17: Monitorizar (não aberta) | AL17: =IF(AK17="Prazo expirado","Prazo passado",IF(LEFT(AK17,11)="Monitorizar","Monitorizar",IF(Y17>=3.5,"Prioridade",IF(Y17>=3,"Candidatar (reach)","Reserva")))) -> Monitorizar | AM17: Anúncio visto é de 2023, de verão. Enviar candidatura espontânea à Alantra Lisboa. | AN17: https://alantra.wd3.myworkdayjobs.com/Alantra/job/Portugal---Lisbon/Sumer-Intern_JR132 | AO17: Direto (site/ATS da empresa) | AP17: Verificada na página | AQ17: =IF(OR(AK17="Prazo expirado",LEFT(AK17,11)="Monitorizar"),0,1) -> 0 | AR17: =IF(AQ17=0,0,AH17) -> 0 | AS17: =AR17*W17/5 -> 0 | AT17: =AS17+W17/1000000+(1000-ROW())/1000000000 -> 4.983e-06 | AU17: =RANK(AT17,$AT$4:$AT$227) -> 201 | AV17: =IF(AQ17=0,"",AF17) | AW17: =IF(AQ17=0,"",AH17)
A18: 15 | B18: Ardian | C18: Private Equity Buyout Stage, Janvier 2027 | D18: Private Equity | E18: VC / private equity | F18: França | G18: Paris | H18: Não indicado (provável presencial) | I18: Jan 2027 | J18: 6 meses | K18: Memos de investimento (em inglês), análise financeira, acompanhamento de due diligence, pesquisa de setores/comparáveis, monitorização de participadas. | L18: Último ano (end-of-studies) ou 2.º ano; modelação financeira e Excel fortes; exige convention de stage de uma instituição de ensino. | M18: Inglês e francês fluentes (essencial) | N18: Exige convenção de estágio, tens de estar inscrita | O18: Não indicado (publicada 05-08-2026) | P18: =IF(ISNUMBER(O18),O18-TODAY(),"") | Q18: 'Selon profil' + vales de refeição | R18: 1500 | S18: 2500 | T18: =IF(R18="","",AVERAGE(R18,S18)) -> 2000 | U18: Estimativa (Paris, PE), valor bruto | V18: Muito alta | W18: 5 | X18: 1 | Y18: =ROUND(0.6*W18+0.4*X18,1) -> 3.4 | Z18: FR | AA18: 1 | AB18: =1-AA18*(1-INDEX('Perfil e pressupostos'!$C$14:$C$20,MATCH(Z18,'Perfil e pressupostos'!$A$14:$A$20,0))) -> 0.05 | AC18: 0.3 | AD18: 0.3 | AE18: 0.8 | AF18: =100*('Perfil e pressupostos'!$F$14*AB18+'Perfil e pressupostos'!$F$15*AC18+'Perfil e pressupostos'!$F$16*AD18+'Perfil e pressupostos'!$F$17*AE18)/'Perfil e pressupostos'!$F$18 -> 30 | AG18: =INDEX('Perfil e pressupostos'!$B$25:$B$28,MATCH(V18,'Perfil e pressupostos'!$A$25:$A$28,0)) -> 0.01 | AH18: =MIN('Perfil e pressupostos'!$F$29,AG18*('Perfil e pressupostos'!$F$25+'Perfil e pressupostos'!$F$26*AF18/100)*IF(AD18<='Perfil e pressupostos'!$F$28,'Perfil e pressupostos'!$F$27,1)) -> 0.0076 | AI18: =IF(AQ18=0,"—",IF(AH18>='Perfil e pressupostos'!$F$30,"Boa",IF(AH18>='Perfil e pressupostos'!$F$31,"Média","Baixa"))) -> Baixa | AJ18: Língua-chave FR (exigência 1); experiência prévia em finanças valorizada, CV tem pouca; exige mestrado em curso ou convenção de estágio, risco. | AK18: Aberta (prazo não indicado) | AL18: =IF(AK18="Prazo expirado","Prazo passado",IF(LEFT(AK18,11)="Monitorizar","Monitorizar",IF(Y18>=3.5,"Prioridade",IF(Y18>=3,"Candidatar (reach)","Reserva")))) -> Candidatar (reach) | AM18: Francês fluente e convenção de estágio são os maiores riscos (podes estar ainda inscrita até janeiro?). | AN18: https://inforcapital.com/jobs/ardian-private-equity-buyout-stage-janvier-2027-i-paris-mf/ | AO18: Anúncio em plataforma | AP18: Verificada na página | AQ18: =IF(OR(AK18="Prazo expirado",LEFT(AK18,11)="Monitorizar"),0,1) -> 1 | AR18: =IF(AQ18=0,0,AH18) -> 0.0076 | AS18: =AR18*W18/5 -> 0.0076 | AT18: =AS18+W18/1000000+(1000-ROW())/1000000000 -> 0.007605982 | AU18: =RANK(AT18,$AT$4:$AT$227) -> 164 | AV18: =IF(AQ18=0,"",AF18) -> 30 | AW18: =IF(AQ18=0,"",AH18) -> 0.0076
A19: 16 | B19: Ardian | C19: Private Equity Co-Investment Stage, Janvier 2027 | D19: Private Equity | E19: VC / private equity | F19: França | G19: Paris | H19: Não indicado (provável presencial) | I19: Jan 2027 | J19: Provável 6 meses | K19: Co-investimento em private equity. | L19: Detalhes não obtidos (provável perfil igual ao Buyout). | M19: Inglês e francês provável | N19: Provável convenção de estágio | O19: Não indicado | P19: =IF(ISNUMBER(O19),O19-TODAY(),"") | Q19: Não indicado | R19: 1500 | S19: 2500 | T19: =IF(R19="","",AVERAGE(R19,S19)) -> 2000 | U19: Estimativa (Paris, PE), valor bruto | V19: Muito alta | W19: 5 | X19: 1 | Y19: =ROUND(0.6*W19+0.4*X19,1) -> 3.4 | Z19: FR | AA19: 0.8 | AB19: =1-AA19*(1-INDEX('Perfil e pressupostos'!$C$14:$C$20,MATCH(Z19,'Perfil e pressupostos'!$A$14:$A$20,0))) -> 0.24 | AC19: 0.3 | AD19: 0.3 | AE19: 0.8 | AF19: =100*('Perfil e pressupostos'!$F$14*AB19+'Perfil e pressupostos'!$F$15*AC19+'Perfil e pressupostos'!$F$16*AD19+'Perfil e pressupostos'!$F$17*AE19)/'Perfil e pressupostos'!$F$18 -> 35.7 | AG19: =INDEX('Perfil e pressupostos'!$B$25:$B$28,MATCH(V19,'Perfil e pressupostos'!$A$25:$A$28,0)) -> 0.01 | AH19: =MIN('Perfil e pressupostos'!$F$29,AG19*('Perfil e pressupostos'!$F$25+'Perfil e pressupostos'!$F$26*AF19/100)*IF(AD19<='Perfil e pressupostos'!$F$28,'Perfil e pressupostos'!$F$27,1)) -> 0.008284 | AI19: =IF(AQ19=0,"—",IF(AH19>='Perfil e pressupostos'!$F$30,"Boa",IF(AH19>='Perfil e pressupostos'!$F$31,"Média","Baixa"))) -> Baixa | AJ19: Língua-chave FR (exigência 0.8); experiência prévia em finanças valorizada, CV tem pouca; exige mestrado em curso ou convenção de estágio, risco. | AK19: Por confirmar | AL19: =IF(AK19="Prazo expirado","Prazo passado",IF(LEFT(AK19,11)="Monitorizar","Monitorizar",IF(Y19>=3.5,"Prioridade",IF(Y19>=3,"Candidatar (reach)","Reserva")))) -> Candidatar (reach) | AM19: Idem Buyout. | AN19: https://www.jobteaser.com/en/job-offers/6b4351d6-5d6f-4919-9301-8a260372988b-ardian-private-equity-co-investment-stage-janvier-2027-paris-m-f | AO19: Anúncio em plataforma | AP19: Parcial (agregador/título) | AQ19: =IF(OR(AK19="Prazo expirado",LEFT(AK19,11)="Monitorizar"),0,1) -> 1 | AR19: =IF(AQ19=0,0,AH19) -> 0.008284 | AS19: =AR19*W19/5 -> 0.008284 | AT19: =AS19+W19/1000000+(1000-ROW())/1000000000 -> 0.008289981 | AU19: =RANK(AT19,$AT$4:$AT$227) -> 139 | AV19: =IF(AQ19=0,"",AF19) -> 35.7 | AW19: =IF(AQ19=0,"",AH19) -> 0.008284
A20: 17 | B20: Ardian | C20: Private Equity Expansion Stage, Janvier 2027 | D20: Private Equity | E20: VC / private equity | F20: França | G20: Paris | H20: Não indicado (provável presencial) | I20: Jan 2027 | J20: Provável 6 meses | K20: Equipa Expansion (investimentos minoritários/growth em PE). | L20: Detalhes não obtidos. | M20: Inglês e francês provável | N20: Provável convenção de estágio | O20: Não indicado | P20: =IF(ISNUMBER(O20),O20-TODAY(),"") | Q20: Não indicado | R20: 1500 | S20: 2500 | T20: =IF(R20="","",AVERAGE(R20,S20)) -> 2000 | U20: Estimativa (Paris, PE), valor bruto | V20: Muito alta | W20: 5 | X20: 1 | Y20: =ROUND(0.6*W20+0.4*X20,1) -> 3.4 | Z20: FR | AA20: 0.8 | AB20: =1-AA20*(1-INDEX('Perfil e pressupostos'!$C$14:$C$20,MATCH(Z20,'Perfil e pressupostos'!$A$14:$A$20,0))) -> 0.24 | AC20: 0.3 | AD20: 0.3 | AE20: 0.8 | AF20: =100*('Perfil e pressupostos'!$F$14*AB20+'Perfil e pressupostos'!$F$15*AC20+'Perfil e pressupostos'!$F$16*AD20+'Perfil e pressupostos'!$F$17*AE20)/'Perfil e pressupostos'!$F$18 -> 35.7 | AG20: =INDEX('Perfil e pressupostos'!$B$25:$B$28,MATCH(V20,'Perfil e pressupostos'!$A$25:$A$28,0)) -> 0.01 | AH20: =MIN('Perfil e pressupostos'!$F$29,AG20*('Perfil e pressupostos'!$F$25+'Perfil e pressupostos'!$F$26*AF20/100)*IF(AD20<='Perfil e pressupostos'!$F$28,'Perfil e pressupostos'!$F$27,1)) -> 0.008284 | AI20: =IF(AQ20=0,"—",IF(AH20>='Perfil e pressupostos'!$F$30,"Boa",IF(AH20>='Perfil e pressupostos'!$F$31,"Média","Baixa"))) -> Baixa | AJ20: Língua-chave FR (exigência 0.8); experiência prévia em finanças valorizada, CV tem pouca; exige mestrado em curso ou convenção de estágio, risco. | AK20: Por confirmar | AL20: =IF(AK20="Prazo expirado","Prazo passado",IF(LEFT(AK20,11)="Monitorizar","Monitorizar",IF(Y20>=3.5,"Prioridade",IF(Y20>=3,"Candidatar (reach)","Reserva")))) -> Candidatar (reach) | AM20: Idem Buyout. | AN20: https://www.jobteaser.com/fr/job-offers/eb1aaf93-15ad-4de7-8761-4ec928254ea6-ardian-private-equity-expansion-stage-janvier-2027-paris-h-f | AO20: Anúncio em plataforma | AP20: Parcial (agregador/título) | AQ20: =IF(OR(AK20="Prazo expirado",LEFT(AK20,11)="Monitorizar"),0,1) -> 1 | AR20: =IF(AQ20=0,0,AH20) -> 0.008284 | AS20: =AR20*W20/5 -> 0.008284 | AT20: =AS20+W20/1000000+(1000-ROW())/1000000000 -> 0.00828998 | AU20: =RANK(AT20,$AT$4:$AT$227) -> 140 | AV20: =IF(AQ20=0,"",AF20) -> 35.7 | AW20: =IF(AQ20=0,"",AH20) -> 0.008284
